Workbook
Name ActiveScenario: Assumptions!$H$4
Name Admin_Cost: Assumptions!$C$78
Name Alpha_Solar: Assumptions!$C$35
Name Alpha_Wind: Assumptions!$C$36
Name Batt_w1h: Assumptions!$C$47
Name Batt_w2h: Assumptions!$C$48
Name Batt_w4h: Assumptions!$C$49
Name Batt_w8h: Assumptions!$C$50
Name Batt_WACC: Assumptions!$C$53
Name Battery_RTE: Assumptions!$C$44
Name CF_Solar: Assumptions!$C$33
Name CF_Wind: Assumptions!$C$34
Name Coal_Accel: Assumptions!$C$19
Name Coal_CFe: Assumptions!$C$15
Name Coal_CFp: Assumptions!$C$16
Name Coal_Degrade: Assumptions!$C$87
Name Coal_Esc: Assumptions!$C$18
Name Coal_FOM: Assumptions!$C$84
Name Coal_Heat_Rate: Assumptions!$C$83
Name Coal_Price: Assumptions!$C$86
Name Coal_SRMC: Assumptions!$C$17
Name Coal_Start: Assumptions!$C$14
Name Coal_VOM: Assumptions!$C$85
Name Contract_Years: Assumptions!$C$72
Name Curtail_Rate: Assumptions!$C$63
Name Curtail_Thresh: Assumptions!$C$62
Name Def_Elas: Assumptions!$C$60
Name Dem_Growth: Assumptions!$C$8
Name Dem_Start: Assumptions!$C$7
Name Direct_Flow: Assumptions!$C$43
Name Divest_Rate: Assumptions!$C$73
Name Drought_Gap: Assumptions!#REF!
Name ELCC_base: Assumptions!$C$38
Name ESEM_Build_Cap: Assumptions!$C$74
Name ESEM_On: Assumptions!$C$65
Name ESEM_Start: Assumptions!$C$66
Name ESEM_WACC_Disc: Assumptions!$C$57
Name Firm_CFe: Assumptions!$C$23
Name Firm_CFp: Assumptions!$C$24
Name Firm_Cov: Assumptions!$C$69
Name Firm_Decay: Assumptions!$C$22
Name Firm_Gen_CF: Assumptions!$C$30
Name Firm_LRMC: Assumptions!$C$27
Name Firm_Sprd: Assumptions!$C$28
Name Firm_SRMC: Assumptions!$C$25
Name Firm_Start: Assumptions!$C$21
Name Firm_Tight: Assumptions!$C$29
Name Firm_VC: Assumptions!$C$26
Name Fwd_Alpha: Assumptions!#REF!
Name Fwd_k: Assumptions!$C$61
Name Gas_WACC: Assumptions!$C$56
Name Lag: Assumptions!$C$70
Name Markup_Base: Assumptions!$C$75
Name Markup_Rate: Assumptions!$C$76
Name Other_Firm: Assumptions!$C$11
Name Other_Gen: Assumptions!#REF!
Name Peak_Growth: Assumptions!$C$10
Name Peak_Start: Assumptions!$C$9
Name RE_Cov: Assumptions!$C$68
Name Recycle_Lag: Assumptions!$C$71

Sheet Assumptions
A1: ESEM Model v2 — Assumptions & Scenario Parameters
A3: Parameter | B3: Description | C3: Active value | D3: Unit | E3: Source | F3: Low | G3: High | H3: Scenario label: | I3: Base | J3: High WACC | K3: No ESEM | L3: WACC disc
A4: Scenario | B4: Active scenario number (1=Base, 2=High WACC, 3=No ESEM, 4=WACC discount) | C4: 1 | H4: =CHOOSE($C$4,"Scenario A","Scenario B","Scenario C","Scenario D") -> Scenario A
A6: 1. DEMAND & SUPPLY
A7: Dem_Start | B7: Starting annual energy demand (TWh) | C7: =CHOOSE($C$4,I7,J7,K7,L7) -> 180 | D7: TWh | E7: AEMO 2024 | F7: 160 | G7: 200 | I7: 180 | J7: 180 | K7: 180 | L7: 180
A8: Dem_Growth | B8: Annual demand growth rate | C8: =CHOOSE($C$4,I8,J8,K8,L8) -> 0.025 | D8: %/yr | E8: AEMO ISP 2024 | F8: 0.01 | G8: 0.04 | I8: 0.025 | J8: 0.025 | K8: 0.025 | L8: 0.025
A9: Peak_Start | B9: Initial peak demand | C9: =CHOOSE($C$4,I9,J9,K9,L9) -> 36 | D9: GW | E9: AEMO 2024 | F9: 30 | G9: 42 | I9: 36 | J9: 36 | K9: 36 | L9: 36
A10: Peak_Growth | B10: Annual peak demand growth rate | C10: =CHOOSE($C$4,I10,J10,K10,L10) -> 0.02 | D10: %/yr | E10: Own estimate | F10: 0.01 | G10: 0.03 | I10: 0.02 | J10: 0.02 | K10: 0.02 | L10: 0.02
A11: Other_Firm | B11: Other firm capacity (interconnectors, DSR) | C11: =CHOOSE($C$4,I11,J11,K11,L11) -> 0 | D11: GW | F11: 0 | G11: 0 | I11: 0 | J11: 0 | K11: 0 | L11: 0
A12: VRE_PrePipe | B12: Pre-pipeline VRE under construction at t=0 | C12: =CHOOSE($C$4,I12,J12,K12,L12) -> 3 | D12: GW | E12: AEMO 2024 | F12: 0 | G12: 5 | I12: 3 | J12: 3 | K12: 3 | L12: 3
A13: 2. COAL — Baseload exit trajectory
A14: Coal_Start | B14: Initial coal capacity | C14: =CHOOSE($C$4,I14,J14,K14,L14) -> 22 | D14: GW | E14: AEMO 2024 | F14: 15 | G14: 25 | I14: 22 | J14: 22 | K14: 22 | L14: 22
A15: Coal_CFe | B15: Coal energy capacity factor (annual) | C15: =CHOOSE($C$4,I15,J15,K15,L15) -> 0.45 | D15: — | E15: AEMO 2024 | F15: 0.4 | G15: 0.5 | I15: 0.45 | J15: 0.45 | K15: 0.45 | L15: 0.45
A16: Coal_CFp | B16: Coal peak capacity factor | C16: =CHOOSE($C$4,I16,J16,K16,L16) -> 0.75 | D16: — | E16: Own estimate | F16: 0.65 | G16: 0.85 | I16: 0.75 | J16: 0.75 | K16: 0.75 | L16: 0.75
A17: Coal_SRMC | B17: Coal short-run marginal cost | C17: =CHOOSE($C$4,I17,J17,K17,L17) -> 80 | D17: $/MWh | E17: AEMO 2024 | F17: 60 | G17: 120 | I17: 80 | J17: 80 | K17: 80 | L17: 80
A18: Coal_Esc | B18: Coal SRMC annual escalation | C18: =CHOOSE($C$4,I18,J18,K18,L18) -> 0.04 | D18: %/yr | E18: Own estimate | F18: 0.02 | G18: 0.07 | I18: 0.04 | J18: 0.04 | K18: 0.04 | L18: 0.04
A19: Coal_Accel | B19: Coal economic exit acceleration factor | C19: =CHOOSE($C$4,I19,J19,K19,L19) -> 0.15 | D19: — | E19: Calibrated | F19: 0.05 | G19: 0.3 | I19: 0.15 | J19: 0.15 | K19: 0.15 | L19: 0.15
A20: 3. EXISTING DISPATCHABLE FIRMING
A21: Firm_Start | B21: Initial dispatchable firm capacity (GW) | C21: =CHOOSE($C$4,I21,J21,K21,L21) -> 22 | D21: GW | E21: AEMO 2024 | F21: 15 | G21: 28 | I21: 22 | J21: 22 | K21: 22 | L21: 22
A22: Firm_Decay | B22: Annual depreciation on legacy firm fleet | C22: =CHOOSE($C$4,I22,J22,K22,L22) -> 0 | D22: %/yr | E22: Own estimate | F22: 0 | G22: 0.05 | I22: 0 | J22: 0 | K22: 0 | L22: 0
A23: Firm_CFe | B23: Firming energy capacity factor (annual dispatch) | C23: =CHOOSE($C$4,I23,J23,K23,L23) -> 0.22 | D23: — | E23: Own estimate | F23: 0.15 | G23: 0.3 | I23: 0.22 | J23: 0.22 | K23: 0.22 | L23: 0.22
A24: Firm_CFp | B24: Firming peak capacity factor (availability) | C24: =CHOOSE($C$4,I24,J24,K24,L24) -> 0.9 | D24: — | E24: Own estimate | F24: 0.8 | G24: 1 | I24: 0.9 | J24: 0.9 | K24: 0.9 | L24: 0.9
A25: Firm_SRMC | B25: Firm dispatch cost — scarcity pivot at zero firming deficit (energy-only revenue floor) | C25: =CHOOSE($C$4,I25,J25,K25,L25) -> 180 | D25: $/MWh | E25: Own estimate | F25: 120 | G25: 250 | I25: 180 | J25: 180 | K25: 180 | L25: 180
A26: Firm_VC | B26: Gas variable cost (fuel + variable O&M) | C26: =CHOOSE($C$4,I26,J26,K26,L26) -> 120 | D26: $/MWh | E26: Own estimate | F26: 90 | G26: 150 | I26: 120 | J26: 120 | K26: 120 | L26: 120
A27: Firm_LRMC | B27: Firm LRMC — BA fixed cost / (CFe x 8760) + fuel (auto-updates with Gas_WACC) | C27: ='Building assets'!B92 -> 250.49 | D27: $/MWh | E27: Building Assets R94
A28: Firm_Sprd | B28: Private firming entry spread above LRMC | C28: =CHOOSE($C$4,I28,J28,K28,L28) -> 60 | D28: $/MWh | E28: Own estimate | F28: 30 | G28: 100 | I28: 60 | J28: 60 | K28: 60 | L28: 60
A29: Firm_Tight | B29: Scarcity price exponential coefficient | C29: =CHOOSE($C$4,I29,J29,K29,L29) -> 3.5 | D29: — | E29: Calibrated | F29: 2 | G29: 5 | I29: 3.5 | J29: 3.5 | K29: 3.5 | L29: 3.5
A30: Firm_Gen_CF | B30: Baseline annual energy capacity factor for legacy firm generationises. | C30: =CHOOSE($C$4,I30,J30,K30,L30) -> 0.05 | D30: — | E30: AEMO ISP 2024 | F30: 0.03 | G30: 0.12 | I30: 0.05 | J30: 0.05 | K30: 0.05 | L30: 0.05
A32: VRE_Start | B32: Initial VRE+storage capacity | C32: =CHOOSE($C$4,I32,J32,K32,L32) -> 30 | D32: GW | E32: AEMO 2024 | F32: 22 | G32: 35 | I32: 30 | J32: 30 | K32: 30 | L32: 30
A33: CF_Solar | B33: Solar capacity factor | C33: =CHOOSE($C$4,I33,J33,K33,L33) -> 0.22 | D33: — | E33: GenCost 2024 | F33: 0.18 | G33: 0.28 | I33: 0.22 | J33: 0.22 | K33: 0.22 | L33: 0.22
A34: CF_Wind | B34: Wind capacity factor | C34: =CHOOSE($C$4,I34,J34,K34,L34) -> 0.35 | D34: — | E34: GenCost 2024 | F34: 0.3 | G34: 0.42 | I34: 0.35 | J34: 0.35 | K34: 0.35 | L34: 0.35
A35: Alpha_Solar | B35: Solar fraction of VRE portfolio | C35: =CHOOSE($C$4,I35,J35,K35,L35) -> 0.67 | D35: — | E35: Own estimate | F35: 0.5 | G35: 0.8 | I35: 0.67 | J35: 0.67 | K35: 0.67 | L35: 0.67
A36: Alpha_Wind | B36: Wind share (= 1 − Alpha_Solar) — computed | C36: =1-Alpha_Solar -> 0.33 | D36: — | E36: Computed
A37: VRE_CFE | B37: VRE+storage capacity factor | C37: =CF_Solar*Alpha_Solar+CF_Wind*Alpha_Wind -> 0.2629
A38: ELCC_base | B38: VRE effective load carrying capability at zero penetration. | C38: =CHOOSE($C$4,I38,J38,K38,L38) -> 0.15 | D38: — | E38: AEMO ISP 2024 | F38: 0.1 | G38: 0.2 | I38: 0.15 | J38: 0.15 | K38: 0.15 | L38: 0.15
A39: VRE_ELCC | B39: VRE effective load carrying capability — endogenised as ELCC_base × (1 − VRE_Share0). Falls as VRE penetration rises, consistent with AEMO ISP. At 32% share (base): ~10%. At 80% share: ~3%. | C39: =ELCC_base*(1-VRE_Share0) -> 0.0924249 | D39: — | E39: Computed — =ELCC_base×(1−VRE_Share0)
A40: VRE_Ratio | B40: VRE nameplate per kW-storage (sizing ratio) | C40: =CHOOSE($C$4,I40,J40,K40,L40) -> 3 | D40: ratio | E40: Own estimate | F40: 2 | G40: 4 | I40: 3 | J40: 3 | K40: 3 | L40: 3
A41: VRE_Sprd | B41: Private VRE entry spread above forward price | C41: =CHOOSE($C$4,I41,J41,K41,L41) -> 4 | D41: $/MWh | E41: Calibrated | F41: 2 | G41: 8 | I41: 4 | J41: 4 | K41: 4 | L41: 4
A42: VRE_Dep | B42: VRE stock annual depreciation rate | C42: =CHOOSE($C$4,I42,J42,K42,L42) -> 0 | D42: %/yr | E42: Own estimate | F42: 0 | G42: 0.03 | I42: 0 | J42: 0 | K42: 0 | L42: 0
A43: Direct_Flow | B43: VRE direct-to-load fraction (bypasses battery) | C43: =CHOOSE($C$4,I43,J43,K43,L43) -> 0.8 | D43: — | E43: Estimate | F43: 0.65 | G43: 0.9 | I43: 0.8 | J43: 0.8 | K43: 0.8 | L43: 0.8
A44: Battery_RTE | B44: Battery round-trip efficiency | C44: =CHOOSE($C$4,I44,J44,K44,L44) -> 0.9 | D44: — | E44: GenCost 2024 | F44: 0.85 | G44: 0.95 | I44: 0.9 | J44: 0.9 | K44: 0.9 | L44: 0.9
A45: Y1_Build | B45: GW of VRE + Battery entering y1 | C45: =CHOOSE($C$4,I45,J45,K45,L45) -> 2 | D45: GW | F45: 1 | G45: 3 | I45: 2 | J45: 2 | K45: 2 | L45: 2
A46: 4b. BATTERY DURATION MIX (weights must sum to 1)
A47: Batt_w1h | B47: Portfolio weight: 1-hour battery | C47: =CHOOSE($C$4,I47,J47,K47,L47) -> 0.1 | D47: — | E47: Own estimate | F47: 0 | G47: 0.3 | I47: 0.1 | J47: 0.1 | K47: 0.1 | L47: 0.1
A48: Batt_w2h | B48: Portfolio weight: 2-hour battery | C48: =CHOOSE($C$4,I48,J48,K48,L48) -> 0.2 | D48: — | E48: Own estimate | F48: 0 | G48: 0.4 | I48: 0.2 | J48: 0.2 | K48: 0.2 | L48: 0.2
A49: Batt_w4h | B49: Portfolio weight: 4-hour battery | C49: =CHOOSE($C$4,I49,J49,K49,L49) -> 0.5 | D49: — | E49: Own estimate | F49: 0.2 | G49: 0.7 | I49: 0.5 | J49: 0.5 | K49: 0.5 | L49: 0.5
A50: Batt_w8h | B50: Portfolio weight: 8-hour battery | C50: =CHOOSE($C$4,I50,J50,K50,L50) -> 0.2 | D50: — | E50: Own estimate | F50: 0 | G50: 0.4 | I50: 0.2 | J50: 0.2 | K50: 0.2 | L50: 0.2
A51: Weight sum check (must = 1)
A52: 5. FINANCING (WACC)
A53: Batt_WACC | B53: Battery project WACC | C53: =CHOOSE($C$4,I53,J53,K53,L53) -> 0.08 | D53: % | E53: Own estimate | F53: 0.06 | G53: 0.12 | I53: 0.08 | J53: 0.11 | K53: 0.08 | L53: 0.06
A54: VRE_WACC_S | B54: Solar VRE project WACC | C54: =CHOOSE($C$4,I54,J54,K54,L54) -> 0.07 | D54: % | E54: Own estimate | F54: 0.05 | G54: 0.11 | I54: 0.07 | J54: 0.1 | K54: 0.07 | L54: 0.05
A55: VRE_WACC_W | B55: Wind VRE project WACC | C55: =CHOOSE($C$4,I55,J55,K55,L55) -> 0.08 | D55: % | E55: Own estimate | F55: 0.06 | G55: 0.12 | I55: 0.08 | J55: 0.11 | K55: 0.08 | L55: 0.06
A56: Gas_WACC | B56: Gas / firm capacity WACC | C56: =CHOOSE($C$4,I56,J56,K56,L56) -> 0.09 | D56: % | E56: Own estimate | F56: 0.07 | G56: 0.13 | I56: 0.09 | J56: 0.12 | K56: 0.09 | L56: 0.07
A57: ESEM_WACC_Disc | B57: WACC discount from ESEM CfD de-risking | C57: =CHOOSE($C$4,I57,J57,K57,L57) -> 0 | D57: % | E57: Policy | F57: 0 | G57: 0.03 | I57: 0 | J57: 0 | K57: 0 | L57: 0.02
A58: 6. PRICE FORMATION
A59: Surp_Elas | B59: Surplus elasticity: WS sensitivity to VRE surplus | C59: =CHOOSE($C$4,I59,J59,K59,L59) -> 4 | D59: — | F59: 1 | G59: 8 | I59: 4 | J59: 4 | K59: 4 | L59: 4
A60: Def_Elas | B60: Deficit elasticity: WS sensitivity to shortfall | C60: =CHOOSE($C$4,I60,J60,K60,L60) -> 5 | D60: — | F60: 2 | G60: 10 | I60: 5 | J60: 5 | K60: 5 | L60: 5
A61: Fwd_k | B61: Forward price logistic steepness (higher = faster alpha response to balance) | C61: =CHOOSE($C$4,I61,J61,K61,L61) -> 3 | D61: — | E61: Calibrated | F61: 2 | G61: 8 | I61: 3 | J61: 3 | K61: 3 | L61: 3
A62: Curtail_Thresh | B62: VRE proportion when curtailment begins. Set at VRE_Share0 | C62: =VRE_Share0 -> 0.383834 | D62: — | E62: Computed — =VRE_Share0
A63: Curtail_Rate | B63: Curtailment rate per unit VRE share above threshold | C63: =CHOOSE($C$4,I63,J63,K63,L63) -> 0.15 | D63: — | F63: 0.15 | G63: 0.4 | I63: 0.15 | J63: 0.15 | K63: 0.15 | L63: 0.15
A64: 7. ESEM DESIGN
A65: ESEM_On | B65: ESEM active switch (1 = on, 0 = off) | C65: 1 | D65: 0/1 | E65: Policy | F65: 0 | G65: 1 | I65: 1 | J65: 1 | K65: 0 | L65: 1
A66: ESEM_Start | B66: Year index when ESEM begins contracting | C66: =CHOOSE($C$4,I66,J66,K66,L66) -> 2 | D66: years | E66: Policy | F66: 1 | G66: 5 | I66: 2 | J66: 2 | K66: 2 | L66: 2
A67: VRE_ShareT | B67: Target VRE share of annual demand | C67: =CHOOSE($C$4,I67,J67,K67,L67) -> 1 | D67: — | E67: Policy | F67: 0.8 | G67: 1 | I67: 1 | J67: 1 | K67: 1 | L67: 1
A68: RE_Cov | B68: ESEM VRE coverage rate (fraction of shortfall) | C68: =CHOOSE($C$4,I68,J68,K68,L68) -> 1 | D68: — | E68: Policy | F68: 0.8 | G68: 1 | I68: 1 | J68: 1 | K68: 1 | L68: 1
A69: Firm_Cov | B69: ESEM firming coverage rate | C69: =CHOOSE($C$4,I69,J69,K69,L69) -> 0.9 | D69: — | E69: Policy | F69: 0.7 | G69: 1 | I69: 0.9 | J69: 0.9 | K69: 0.9 | L69: 0.9
A70: Lag | B70: Contracting-to-online lag (years) | C70: =CHOOSE($C$4,I70,J70,K70,L70) -> 3 | D70: years | E70: Policy | F70: 2 | G70: 5 | I70: 3 | J70: 3 | K70: 3 | L70: 3
A71: Recycle_Lag | B71: Years ESEM holds VRE contracts before selling to retailers | C71: =CHOOSE($C$4,I71,J71,K71,L71) -> 7 | D71: years | E71: Policy | F71: 5 | G71: 10 | I71: 7 | J71: 7 | K71: 7 | L71: 7
A72: Contract_Years | B72: Total VRE contract length | C72: =CHOOSE($C$4,I72,J72,K72,L72) -> 20 | D72: years | E72: Policy | F72: 15 | G72: 25 | I72: 20 | J72: 20 | K72: 20 | L72: 20
A73: Divest_Rate | B73: Annual offtake divestment rate = 1/(Contract_Years−Recycle_Lag) | C73: =1/(Contract_Years-Recycle_Lag) -> 0.076923077 | D73: — | E73: Computed
A74: ESEM_VRE_BuildCap | B74: Maximum capacity contracted by ESEM annually | C74: =CHOOSE($C$4,I74,J74,K74,L74) -> 6 | D74: GW | E74: Policy | F74: 3 | G74: 9 | I74: 6 | J74: 6 | K74: 6 | L74: 6
A75: Markup_Base | B75: Base ESEM procurement markup above LRMC | C75: =CHOOSE($C$4,I75,J75,K75,L75) -> 0.01 | D75: % | E75: Own estimate | F75: 0.02 | G75: 0.1 | I75: 0.01 | J75: 0.01 | K75: 0.01 | L75: 0.01
A76: Markup_Rate | B76: Supply curve steepness — additional markup per GW of VRE contracted in that year. | C76: =CHOOSE($C$4,I76,J76,K76,L76) -> 0.02 | D76: %/GW | E76: Own estimate | F76: 0 | G76: 0.02 | I76: 0.02 | J76: 0.02 | K76: 0.02 | L76: 0.02
A77: 8. CONTRACT ECONOMICS
A78: Admin_Cost | B78: Annual ESEM administration cost | C78: =CHOOSE($C$4,I78,J78,K78,L78) -> -37 | D78: $m/yr | E78: estimate | F78: 20 | G78: 60 | I78: -37 | J78: -37 | K78: -37 | L78: -37
A79: VRE_Share0 | B79: Initial VRE share of demand — computed from VRE_Start × VRE_CFe × 8760 / Dem_Start. Used as starting point for target ramp (R34) and to set curtailment threshold. | C79: =VRE_Start*VRE_CFe*8.76/Dem_Start -> 0.383834 | D79: — | E79: Computed
A80: 9. COMPUTED / ENDOGENISED PARAMETERS [no colour — reference only] | B80: These rows are derived from other assumptions. Do not edit directly — change the upstream parameters instead.
A83: Coal_Heat_Rate | B83: Thermal heat rate of existing black coal fleet (GJ per MWh dispatched). GenCost 2025-26 Table B.9 black coal: efficiency 42.12% → 3.6/0.4212. | C83: 8.547 | D83: GJ/MWh | E83: GenCost 2025-26 Table B.9
A84: Coal_FOM | B84: Fixed O&M for existing black coal plant ($/kW/yr). Accrues regardless of dispatch — labour, maintenance, insurance. GenCost 2025-26 Table B.9 black coal. | C84: 64.85 | D84: $/kW/yr | E84: GenCost 2025-26 Table B.9
A85: Coal_VOM | B85: Variable O&M for black coal ($/MWh dispatched). Consumables and wear proportional to output. GenCost 2025-26 Table B.9. | C85: 4.68 | D85: $/MWh | E85: GenCost 2025-26 Table B.9
A86: Coal_Price | B86: Domestic coal commodity price ($/GJ). Back-calculated to reconcile with Coal_SRMC=$80: (80 − VOM) / heat_rate = $8.81/GJ. GenCost uses $3/GJ (pre-2022 domestic contract); $8.81/GJ reflects post-2022 AUS domestic coal pricing. Escalates at Coal_Esc each year in Building Assets. | C86: 8.81 | D86: $/GJ | E86: Own estimate — back-calculated from Coal_SRMC
A87: Coal_Degrade | B87: Annual reliability degradation rate of existing coal fleet (%/yr). Captures ageing equipment and cycling damage as VRE grows. Applied to Coal_CFe and Coal_CFp in Building Assets Section E. | C87: 0.015 | D87: %/yr | E87: Own estimate — AEMO fleet age data

Sheet Building assets
A1: BUILDING ASSETS — VRE+Storage and Firming LRMC Derivation
A2: Derives the all-in LRMC ($/MWh) of new-build VRE+storage and firming capacity from first principles. Uses GenCost 2025-26 capex trajectories, asset-specific WACCs, and a Delivered Energy Factor (DEF) to convert annual costs to $/MWh. Section C output feeds Model row 22. Section D output feeds Assumptions Firm_LRMC.
A3: All parameters are set on the Assumptions sheet. Section A shows them here for transparency. Do not edit parameters in this sheet.
A5: SECTION A — PARAMETERS (controlled from Assumptions; shown here for transparency)
A6: Financing
A7: Battery WACC | B7: =Batt_WACC -> 0.08
A8: Solar WACC | B8: =VRE_WACC_S -> 0.07
A9: Wind WACC | B9: =VRE_WACC_W -> 0.08
A10: Gas OCGT WACC | B10: =Gas_WACC -> 0.09
A12: Economic lives (yrs) [GenCost 2025-26]
A13: Battery | B13: 20
A14: Solar PV | B14: 30
A15: Wind | B15: 25
A16: Gas OCGT | B16: 25
A18: Battery replacement
A19: Cell replacement fraction of original capex | B19: 0.5
A20: Cell replacement year | B20: 12
A22: Portfolio composition
A23: VRE:storage ratio (kW VRE per kW storage) | B23: =VRE_Ratio -> 3
A24: Solar share of VRE portfolio | B24: =Alpha_Solar -> 0.67
A25: Wind share of VRE portfolio | B25: =Alpha_Wind -> 0.33
A26: Solar capacity factor | B26: =CF_Solar -> 0.22
A27: Wind capacity factor | B27: =CF_Wind -> 0.35
A28: Battery round-trip efficiency | B28: =Battery_RTE -> 0.9
A29: Direct-to-load fraction (bypasses storage) | B29: =Direct_Flow -> 0.8
A31: Battery duration weights (set on Assumptions; sum must = 1)
A32: w_1h | B32: =Batt_w1h -> 0.1
A33: w_2h | B33: =Batt_w2h -> 0.2
A34: w_4h | B34: =Batt_w4h -> 0.5
A35: w_8h | B35: =Batt_w8h -> 0.2
A36: Weight sum check | B36: =IF(ABS(B32+B33+B34+B35-1)<0.001,"check!","verify battery") -> check!
A37: Weighted avg duration (hrs) | B37: =1*B32+2*B33+4*B34+8*B35 -> 4.1
A38: Firming dispatch
A39: Firm dispatch CF (Firm_CFe) | B39: =Firm_CFe -> 0.22
A40: Firm variable cost $/MWh (fuel + var O&M) | B40: =Firm_VC -> 120
A42: SECTION B — CAPEX REFERENCE DATA (GenCost 2025-26, Current Policies scenario, 2025-26 $A)
A43: Source: Graham, P. and Hayward, J. 2025, GenCost 2025-26: Consultation draft, CSIRO, Australia. Appendix Table B.1.
A44: Year (model index t) | B44: =Model!C2 -> 0 | C44: =Model!D2 -> 1 | D44: =Model!E2 -> 2 | E44: =Model!F2 -> 3 | F44: =Model!G2 -> 4 | G44: =Model!H2 -> 5 | H44: =Model!I2 -> 6 | I44: =Model!J2 -> 7 | ... AA44: =Model!AB2 -> 25
A45: VRE+Storage capex ($/kW of nameplate capacity for each technology)
A46: 1h battery ($/kW) | B46: 760 | C46: 747 | D46: 740 | E46: 734 | F46: 717 | G46: 698 | H46: 689 | I46: 676 | J46: 647 | K46: 627 | L46: 611 | M46: 597 | N46: 585 | O46: 573 | P46: 568 | Q46: 562 | R46: 558 | S46: 555 | T46: 552 | U46: 550 | V46: 548 | W46: 547 | X46: 545 | Y46: 541 | Z46: 537 | AA46: 538
A47: 2h battery ($/kW) | B47: 1028 | C47: 1010 | D47: 1000 | E47: 994 | F47: 968 | G47: 942 | H47: 926 | I47: 906 | J47: 870 | K47: 844 | L47: 822 | M47: 800 | N47: 782 | O47: 764 | P47: 756 | Q47: 748 | R47: 744 | S47: 738 | T47: 734 | U47: 732 | V47: 728 | W47: 726 | X47: 724 | Y47: 720 | Z47: 716 | AA47: 716
A48: 4h battery ($/kW) | B48: 1508 | C48: 1484 | D48: 1468 | E48: 1456 | F48: 1420 | G48: 1380 | H48: 1352 | I48: 1320 | J48: 1272 | K48: 1232 | L48: 1196 | M48: 1164 | N48: 1136 | O48: 1108 | P48: 1096 | Q48: 1084 | R48: 1076 | S48: 1068 | T48: 1060 | U48: 1056 | V48: 1052 | W48: 1048 | X48: 1048 | Y48: 1040 | Z48: 1036 | AA48: 1036
A49: 8h battery ($/kW) | B49: 2408 | C49: 2376 | D49: 2352 | E49: 2336 | F49: 2272 | G49: 2208 | H49: 2152 | I49: 2096 | J49: 2024 | K49: 1968 | L49: 1912 | M49: 1856 | N49: 1808 | O49: 1760 | P49: 1736 | Q49: 1720 | R49: 1704 | S49: 1688 | T49: 1680 | U49: 1672 | V49: 1664 | W49: 1656 | X49: 1656 | Y49: 1648 | Z49: 1640 | AA49: 1640
A50: Solar PV ($/kW) | B50: 1381 | C50: 1187 | D50: 1066 | E50: 989 | F50: 930 | G50: 872 | H50: 831 | I50: 806 | J50: 788 | K50: 772 | L50: 759 | M50: 749 | N50: 742 | O50: 734 | P50: 725 | Q50: 717 | R50: 709 | S50: 704 | T50: 698 | U50: 691 | V50: 685 | W50: 679 | X50: 675 | Y50: 668 | Z50: 664 | AA50: 660
A51: Wind onshore ($/kW) | B51: 3108 | C51: 2976 | D51: 2855 | E51: 2742 | F51: 2636 | G51: 2536 | H51: 2445 | I51: 2365 | J51: 2301 | K51: 2285 | L51: 2252 | M51: 2244 | N51: 2235 | O51: 2217 | P51: 2201 | Q51: 2182 | R51: 2169 | S51: 2160 | T51: 2154 | U51: 2148 | V51: 2144 | W51: 2141 | X51: 2139 | Y51: 2138 | Z51: 2137 | AA51: 2136
A52: Firming capex ($/kW of nameplate capacity)
A53: Small OCGT ($/kW) | B53: 2824 | C53: 2716 | D53: 2566 | E53: 2427 | F53: 2296 | G53: 2173 | H53: 2056 | I53: 1946 | J53: 1842 | K53: 1776 | L53: 1747 | M53: 1752 | N53: 1757 | O53: 1762 | P53: 1767 | Q53: 1770 | R53: 1773 | S53: 1776 | T53: 1780 | U53: 1783 | V53: 1786 | W53: 1789 | X53: 1792 | Y53: 1795 | Z53: 1798 | AA53: 1801
A54: Large OCGT ($/kW) | B54: 1694 | C54: 1629 | D54: 1540 | E54: 1456 | F54: 1377 | G54: 1304 | H54: 1233 | I54: 1167 | J54: 1105 | K54: 1066 | L54: 1048 | M54: 1051 | N54: 1054 | O54: 1057 | P54: 1060 | Q54: 1062 | R54: 1064 | S54: 1066 | T54: 1068 | U54: 1070 | V54: 1071 | W54: 1073 | X54: 1075 | Y54: 1077 | Z54: 1079 | AA54: 1081
A56: SECTION C — VRE+STORAGE LRMC
A57: All costs expressed per kW of battery storage capacity installed. The bundle comprises 1 kW of storage backed by VRE_Ratio kW of generation. Output row feeds Model row 22 directly.
A59: C1 — Blended capex per kW of storage ($/kW) [weights from Assumptions; data from Section B]
A60: Blended battery capex ($/kW-storage) | B60: =Batt_w1h*B46+Batt_w2h*B47+Batt_w4h*B48+Batt_w8h*B49 -> 1517.2 | C60: =Batt_w1h*C46+Batt_w2h*C47+Batt_w4h*C48+Batt_w8h*C49 -> 1493.9 | D60: =Batt_w1h*D46+Batt_w2h*D47+Batt_w4h*D48+Batt_w8h*D49 -> 1478.4 | E60: =Batt_w1h*E46+Batt_w2h*E47+Batt_w4h*E48+Batt_w8h*E49 -> 1467.4 | F60: =Batt_w1h*F46+Batt_w2h*F47+Batt_w4h*F48+Batt_w8h*F49 -> 1429.7 | G60: =Batt_w1h*G46+Batt_w2h*G47+Batt_w4h*G48+Batt_w8h*G49 -> 1389.8 | H60: =Batt_w1h*H46+Batt_w2h*H47+Batt_w4h*H48+Batt_w8h*H49 -> 1360.5 | I60: =Batt_w1h*I46+Batt_w2h*I47+Batt_w4h*I48+Batt_w8h*I49 -> 1328 | ... AA60: =Batt_w1h*AA46+Batt_w2h*AA47+Batt_w4h*AA48+Batt_w8h*AA49 -> 1043
A61: Solar capex × ratio ($/kW-storage) | B61: =Alpha_Solar*VRE_Ratio*B50 -> 2775.81 | C61: =Alpha_Solar*VRE_Ratio*C50 -> 2385.87 | D61: =Alpha_Solar*VRE_Ratio*D50 -> 2142.66 | E61: =Alpha_Solar*VRE_Ratio*E50 -> 1987.89 | F61: =Alpha_Solar*VRE_Ratio*F50 -> 1869.3 | G61: =Alpha_Solar*VRE_Ratio*G50 -> 1752.72 | H61: =Alpha_Solar*VRE_Ratio*H50 -> 1670.31 | I61: =Alpha_Solar*VRE_Ratio*I50 -> 1620.06 | ... AA61: =Alpha_Solar*VRE_Ratio*AA50 -> 1326.6
A62: Wind capex × ratio ($/kW-storage) | B62: =Alpha_Wind*VRE_Ratio*B51 -> 3076.92 | C62: =Alpha_Wind*VRE_Ratio*C51 -> 2946.24 | D62: =Alpha_Wind*VRE_Ratio*D51 -> 2826.45 | E62: =Alpha_Wind*VRE_Ratio*E51 -> 2714.58 | F62: =Alpha_Wind*VRE_Ratio*F51 -> 2609.64 | G62: =Alpha_Wind*VRE_Ratio*G51 -> 2510.64 | H62: =Alpha_Wind*VRE_Ratio*H51 -> 2420.55 | I62: =Alpha_Wind*VRE_Ratio*I51 -> 2341.35 | ... AA62: =Alpha_Wind*VRE_Ratio*AA51 -> 2114.64
A64: C2 — All-in annual cost per kW of storage ($/kW/yr) [capital annuity + O&M + battery replacement]
A65: Battery — capital annuity [PMT at Batt_WACC, 20yr life] | B65: =PMT(Batt_WACC,$B$13,B60)*-1 -> 154.53017 | C65: =PMT(Batt_WACC,$B$13,C60)*-1 -> 152.15701 | D65: =PMT(Batt_WACC,$B$13,D60)*-1 -> 150.57831 | E65: =PMT(Batt_WACC,$B$13,E60)*-1 -> 149.45793 | F65: =PMT(Batt_WACC,$B$13,F60)*-1 -> 145.6181 | G65: =PMT(Batt_WACC,$B$13,G60)*-1 -> 141.5542 | H65: =PMT(Batt_WACC,$B$13,H60)*-1 -> 138.56993 | I65: =PMT(Batt_WACC,$B$13,I60)*-1 -> 135.25973 | ... AA65: =PMT(Batt_WACC,$B$13,AA60)*-1 -> 106.23185
A66: Battery — fixed O&M (routine only: monitoring, insurance, maintenance) [$/kW/yr; own estimate ~$7–13 by duration. Excludes augmentation — handled separately via replacement annuity row above] | B66: =Batt_w1h*7+Batt_w2h*8+Batt_w4h*10+Batt_w8h*13 -> 9.9 | C66: =Batt_w1h*7+Batt_w2h*8+Batt_w4h*10+Batt_w8h*13 -> 9.9 | D66: =Batt_w1h*7+Batt_w2h*8+Batt_w4h*10+Batt_w8h*13 -> 9.9 | E66: =Batt_w1h*7+Batt_w2h*8+Batt_w4h*10+Batt_w8h*13 -> 9.9 | F66: =Batt_w1h*7+Batt_w2h*8+Batt_w4h*10+Batt_w8h*13 -> 9.9 | G66: =Batt_w1h*7+Batt_w2h*8+Batt_w4h*10+Batt_w8h*13 -> 9.9 | H66: =Batt_w1h*7+Batt_w2h*8+Batt_w4h*10+Batt_w8h*13 -> 9.9 | I66: =Batt_w1h*7+Batt_w2h*8+Batt_w4h*10+Batt_w8h*13 -> 9.9 | ... AA66: =Batt_w1h*7+Batt_w2h*8+Batt_w4h*10+Batt_w8h*13 -> 9.9
A67: Battery — cell replacement annuity [50% capex at Year 12, discounted to PV] | B67: =PMT(Batt_WACC,$B$13,Repl_Frac*B60*(1+Batt_WACC)^(-Repl_Year))*-1 -> 30.683029 | C67: =PMT(Batt_WACC,$B$13,Repl_Frac*C60*(1+Batt_WACC)^(-Repl_Year))*-1 -> 30.211822 | D67: =PMT(Batt_WACC,$B$13,Repl_Frac*D60*(1+Batt_WACC)^(-Repl_Year))*-1 -> 29.898358 | E67: =PMT(Batt_WACC,$B$13,Repl_Frac*E60*(1+Batt_WACC)^(-Repl_Year))*-1 -> 29.6759 | F67: =PMT(Batt_WACC,$B$13,Repl_Frac*F60*(1+Batt_WACC)^(-Repl_Year))*-1 -> 28.913476 | G67: =PMT(Batt_WACC,$B$13,Repl_Frac*G60*(1+Batt_WACC)^(-Repl_Year))*-1 -> 28.10656 | H67: =PMT(Batt_WACC,$B$13,Repl_Frac*H60*(1+Batt_WACC)^(-Repl_Year))*-1 -> 27.514013 | I67: =PMT(Batt_WACC,$B$13,Repl_Frac*I60*(1+Batt_WACC)^(-Repl_Year))*-1 -> 26.856751 | ... AA67: =PMT(Batt_WACC,$B$13,Repl_Frac*AA60*(1+Batt_WACC)^(-Repl_Year))*-1 -> 21.093065
A68: Solar — capital annuity × ratio [PMT at VRE_WACC_S, 30yr life] | B68: =PMT(VRE_WACC_S,$B$14,B61)*-1 -> 223.69254 | C68: =PMT(VRE_WACC_S,$B$14,C61)*-1 -> 192.26868 | D68: =PMT(VRE_WACC_S,$B$14,D61)*-1 -> 172.66926 | E68: =PMT(VRE_WACC_S,$B$14,E61)*-1 -> 160.19691 | F68: =PMT(VRE_WACC_S,$B$14,F61)*-1 -> 150.64016 | G68: =PMT(VRE_WACC_S,$B$14,G61)*-1 -> 141.2454 | H68: =PMT(VRE_WACC_S,$B$14,H61)*-1 -> 134.60428 | I68: =PMT(VRE_WACC_S,$B$14,I61)*-1 -> 130.55481 | ... AA68: =PMT(VRE_WACC_S,$B$14,AA61)*-1 -> 106.90592
A69: Solar — fixed O&M × ratio [$12/kW/yr; GenCost 2025-26 Table B.9] | B69: =12*Alpha_Solar*VRE_Ratio -> 24.12 | C69: =12*Alpha_Solar*VRE_Ratio -> 24.12 | D69: =12*Alpha_Solar*VRE_Ratio -> 24.12 | E69: =12*Alpha_Solar*VRE_Ratio -> 24.12 | F69: =12*Alpha_Solar*VRE_Ratio -> 24.12 | G69: =12*Alpha_Solar*VRE_Ratio -> 24.12 | H69: =12*Alpha_Solar*VRE_Ratio -> 24.12 | I69: =12*Alpha_Solar*VRE_Ratio -> 24.12 | ... AA69: =12*Alpha_Solar*VRE_Ratio -> 24.12
A70: Wind — capital annuity × ratio [PMT at VRE_WACC_W, 25yr life] | B70: =PMT(VRE_WACC_W,$B$15,B62)*-1 -> 288.24211 | C70: =PMT(VRE_WACC_W,$B$15,C62)*-1 -> 276.00017 | D70: =PMT(VRE_WACC_W,$B$15,D62)*-1 -> 264.77839 | E70: =PMT(VRE_WACC_W,$B$15,E62)*-1 -> 254.29854 | F70: =PMT(VRE_WACC_W,$B$15,F62)*-1 -> 244.46789 | G70: =PMT(VRE_WACC_W,$B$15,G62)*-1 -> 235.19369 | H70: =PMT(VRE_WACC_W,$B$15,H62)*-1 -> 226.75417 | I70: =PMT(VRE_WACC_W,$B$15,I62)*-1 -> 219.33481 | ... AA70: =PMT(VRE_WACC_W,$B$15,AA62)*-1 -> 198.09689
A71: Wind — fixed O&M × ratio [$29/kW/yr; GenCost 2025-26 Table B.9] | B71: =29*Alpha_Wind*VRE_Ratio -> 28.71 | C71: =29*Alpha_Wind*VRE_Ratio -> 28.71 | D71: =29*Alpha_Wind*VRE_Ratio -> 28.71 | E71: =29*Alpha_Wind*VRE_Ratio -> 28.71 | F71: =29*Alpha_Wind*VRE_Ratio -> 28.71 | G71: =29*Alpha_Wind*VRE_Ratio -> 28.71 | H71: =29*Alpha_Wind*VRE_Ratio -> 28.71 | I71: =29*Alpha_Wind*VRE_Ratio -> 28.71 | ... AA71: =29*Alpha_Wind*VRE_Ratio -> 28.71
A72: TOTAL all-in annual cost ($/kW-storage/yr) | B72: =B65+B66+B67+B68+B69+B70+B71 -> 759.87785 | C72: =C65+C66+C67+C68+C69+C70+C71 -> 713.36769 | D72: =D65+D66+D67+D68+D69+D70+D71 -> 680.65431 | E72: =E65+E66+E67+E68+E69+E70+E71 -> 656.35928 | F72: =F65+F66+F67+F68+F69+F70+F71 -> 632.36963 | G72: =G65+G66+G67+G68+G69+G70+G71 -> 608.82985 | H72: =H65+H66+H67+H68+H69+H70+H71 -> 590.17239 | I72: =I65+I66+I67+I68+I69+I70+I71 -> 574.7361 | ... AA72: =AA65+AA66+AA67+AA68+AA69+AA70+AA71 -> 495.05774
A74: C3 — Delivered Energy Factor and LRMC [DEF = MWh delivered per kW-storage per hour; accounts for VRE:storage ratio, RTE losses, direct flow, drought]
A75: VRE blended capacity factor (Alpha_Solar×CF_Solar + Alpha_Wind×CF_Wind) | B75: =Alpha_Solar*CF_Solar+Alpha_Wind*CF_Wind -> 0.2629 | C75: =Alpha_Solar*CF_Solar+Alpha_Wind*CF_Wind -> 0.2629 | D75: =Alpha_Solar*CF_Solar+Alpha_Wind*CF_Wind -> 0.2629 | E75: =Alpha_Solar*CF_Solar+Alpha_Wind*CF_Wind -> 0.2629 | F75: =Alpha_Solar*CF_Solar+Alpha_Wind*CF_Wind -> 0.2629 | G75: =Alpha_Solar*CF_Solar+Alpha_Wind*CF_Wind -> 0.2629 | H75: =Alpha_Solar*CF_Solar+Alpha_Wind*CF_Wind -> 0.2629 | I75: =Alpha_Solar*CF_Solar+Alpha_Wind*CF_Wind -> 0.2629 | ... AA75: =Alpha_Solar*CF_Solar+Alpha_Wind*CF_Wind -> 0.2629
A76: Delivered Energy Factor (DEF) = (Direct_Flow + (1−Direct_Flow)×RTE) × VRE_Ratio × VRE_CF_blended | B76: =(Direct_Flow+(1-Direct_Flow)*Battery_RTE)*VRE_Ratio*(Alpha_Solar*CF_Solar+Alpha_Wind*CF_Wind) -> 0.772926 | C76: =(Direct_Flow+(1-Direct_Flow)*Battery_RTE)*VRE_Ratio*(Alpha_Solar*CF_Solar+Alpha_Wind*CF_Wind) -> 0.772926 | D76: =(Direct_Flow+(1-Direct_Flow)*Battery_RTE)*VRE_Ratio*(Alpha_Solar*CF_Solar+Alpha_Wind*CF_Wind) -> 0.772926 | E76: =(Direct_Flow+(1-Direct_Flow)*Battery_RTE)*VRE_Ratio*(Alpha_Solar*CF_Solar+Alpha_Wind*CF_Wind) -> 0.772926 | F76: =(Direct_Flow+(1-Direct_Flow)*Battery_RTE)*VRE_Ratio*(Alpha_Solar*CF_Solar+Alpha_Wind*CF_Wind) -> 0.772926 | G76: =(Direct_Flow+(1-Direct_Flow)*Battery_RTE)*VRE_Ratio*(Alpha_Solar*CF_Solar+Alpha_Wind*CF_Wind) -> 0.772926 | H76: =(Direct_Flow+(1-Direct_Flow)*Battery_RTE)*VRE_Ratio*(Alpha_Solar*CF_Solar+Alpha_Wind*CF_Wind) -> 0.772926 | I76: =(Direct_Flow+(1-Direct_Flow)*Battery_RTE)*VRE_Ratio*(Alpha_Solar*CF_Solar+Alpha_Wind*CF_Wind) -> 0.772926 | ... AA76: =(Direct_Flow+(1-Direct_Flow)*Battery_RTE)*VRE_Ratio*(Alpha_Solar*CF_Solar+Alpha_Wind*CF_Wind) -> 0.772926
A77: ↓ OUTPUT: feeds Model row 22
A78: ★ VRE+STORAGE LRMC ($/MWh) | B78: =1000*B72/(8760*B76) -> 112.22814 | C78: =1000*C72/(8760*C76) -> 105.35894 | D78: =1000*D72/(8760*D76) -> 100.52743 | E78: =1000*E72/(8760*E76) -> 96.939239 | F78: =1000*F72/(8760*F76) -> 93.396152 | G78: =1000*G72/(8760*G76) -> 89.919507 | H78: =1000*H72/(8760*H76) -> 87.163942 | I78: =1000*I72/(8760*I76) -> 84.884121 | ... AA78: =1000*AA72/(8760*AA76) -> 73.116236
A81: SECTION D — FIRMING LRMC (Gas OCGT peaking capacity)
A82: Firming recovers capital through scarcity pricing during high-demand events, not continuous dispatch. LRMC converts fixed costs to $/MWh at the assumed dispatch frequency (Firm_CFe). Output (single value, Year 1) feeds Assumptions Firm_LRMC.
A83: D1/D2 — All-in annual cost ($/kW/yr)
A84: Blended OCGT capex — AVERAGE(small, large) ($/kW) | B84: =AVERAGE(B53,B54) -> 2259 | C84: =AVERAGE(C53,C54) -> 2172.5 | D84: =AVERAGE(D53,D54) -> 2053 | E84: =AVERAGE(E53,E54) -> 1941.5 | F84: =AVERAGE(F53,F54) -> 1836.5 | G84: =AVERAGE(G53,G54) -> 1738.5 | H84: =AVERAGE(H53,H54) -> 1644.5 | I84: =AVERAGE(I53,I54) -> 1556.5 | ... AA84: =AVERAGE(AA53,AA54) -> 1441
A85: Capital annuity [PMT at Gas_WACC, 25yr life] | B85: =PMT(Gas_WACC,$B$16,B84)*-1 -> 229.98032 | C85: =PMT(Gas_WACC,$B$16,C84)*-1 -> 221.17408 | D85: =PMT(Gas_WACC,$B$16,D84)*-1 -> 209.00823 | E85: =PMT(Gas_WACC,$B$16,E84)*-1 -> 197.65684 | F85: =PMT(Gas_WACC,$B$16,F84)*-1 -> 186.96718 | G85: =PMT(Gas_WACC,$B$16,G84)*-1 -> 176.99017 | H85: =PMT(Gas_WACC,$B$16,H84)*-1 -> 167.42038 | I85: =PMT(Gas_WACC,$B$16,I84)*-1 -> 158.46143 | ... AA85: =PMT(Gas_WACC,$B$16,AA84)*-1 -> 146.70281
A86: Fixed O&M — AVERAGE($17 small, $26 large/kW/yr) [GenCost 2025-26 Table B.9] | B86: =AVERAGE(17,26) -> 21.5 | C86: =AVERAGE(17,26) -> 21.5 | D86: =AVERAGE(17,26) -> 21.5 | E86: =AVERAGE(17,26) -> 21.5 | F86: =AVERAGE(17,26) -> 21.5 | G86: =AVERAGE(17,26) -> 21.5 | H86: =AVERAGE(17,26) -> 21.5 | I86: =AVERAGE(17,26) -> 21.5 | ... AA86: =AVERAGE(17,26) -> 21.5
A87: TOTAL fixed cost ($/kW/yr) | B87: =B85+B86 -> 251.48032 | C87: =C85+C86 -> 242.67408 | D87: =D85+D86 -> 230.50823 | E87: =E85+E86 -> 219.15684 | F87: =F85+F86 -> 208.46718 | G87: =G85+G86 -> 198.49017 | H87: =H85+H86 -> 188.92038 | I87: =I85+I86 -> 179.96143 | ... AA87: =AA85+AA86 -> 168.20281
A89: D3 — Sensitivity: implied $/MWh at various dispatch frequencies (Year 1 capex)
A90: D3 — Sensitivity: fixed cost ($/MWh) at various dispatch frequencies [Year 1 capex] | B90: Firm_CFe (active) | C90: 3% | D90: 5% | E90: 8% | F90: 10%
A91: Fixed cost ($/MWh excl. fuel) — add Firm_VC for all-in Firm_LRMC | B91: =B87*1000/(8760*Firm_CFe) -> 130.49 | C91: =B87*1000/(8760*0.03) -> 956.92664 | D91: =B87*1000/(8760*0.05) -> 574.15598 | E91: =B87*1000/(8760*0.08) -> 358.84749 | F91: =B87*1000/(8760*0.1) -> 287.07799
A92: ★ FIRM LRMC ($/MWh) — time-varying across all years [Assumptions Firm_LRMC references col B (Year 1); Model R49 and private firm accumulator use year-indexed values] | B92: =B87*1000/(8760*Firm_CFe)+Firm_VC -> 250.49 | C92: =C87*1000/(8760*Firm_CFe)+Firm_VC -> 245.92055 | D92: =D87*1000/(8760*Firm_CFe)+Firm_VC -> 239.60784 | E92: =E87*1000/(8760*Firm_CFe)+Firm_VC -> 233.71774 | F92: =F87*1000/(8760*Firm_CFe)+Firm_VC -> 228.17101 | G92: =G87*1000/(8760*Firm_CFe)+Firm_VC -> 222.99407 | H92: =H87*1000/(8760*Firm_CFe)+Firm_VC -> 218.02842 | I92: =I87*1000/(8760*Firm_CFe)+Firm_VC -> 213.37974 | ... AA92: =AA87*1000/(8760*Firm_CFe)+Firm_VC -> 207.27833
A94: SECTION E — COAL COST STRUCTURE (existing fleet — no capex annuity; sunk cost excluded)
A95: Source: GenCost 2025-26 Table B.9 (black coal). No capital recovery — existing fleet capex is sunk. Fixed O&M and variable/fuel costs only. Coal commodity price back-calculated to reconcile with Coal_SRMC assumption. Output feeds Model rows 13, 15, 16 and Total System Cost section.
A97: E1 — Physical parameters (constants, from Assumptions)
A98: Heat rate (GJ/MWh) [GenCost B.9: efficiency 42.12%] | B98: =Coal_Heat_Rate -> 8.547
A99: Fixed O&M ($/kW/yr) [GenCost B.9] | B99: =Coal_FOM -> 64.85
A100: Variable O&M ($/MWh) [GenCost B.9] | B100: =Coal_VOM -> 4.68
A102: E2 — Time-varying cost trajectories (escalate at Coal_Esc each year)
A103: Year (model index t) | B103: =Model!B2 -> Unit: years from base | C103: =Model!C2 -> 0 | D103: =Model!D2 -> 1 | E103: =Model!E2 -> 2 | F103: =Model!F2 -> 3 | G103: =Model!G2 -> 4 | H103: =Model!H2 -> 5 | I103: =Model!I2 -> 6 | ... AA103: =Model!AA2 -> 24
A104: Coal commodity price ($/GJ) — escalates at Coal_Esc each year. Year 1: $8.81/GJ (back-calculated from Coal_SRMC=$80). | B104: =Coal_Price -> 8.81 | C104: =Coal_Price*(1+Coal_Esc)^1 -> 9.1624 | D104: =Coal_Price*(1+Coal_Esc)^2 -> 9.528896 | E104: =Coal_Price*(1+Coal_Esc)^3 -> 9.9100518 | F104: =Coal_Price*(1+Coal_Esc)^4 -> 10.306454 | G104: =Coal_Price*(1+Coal_Esc)^5 -> 10.718712 | H104: =Coal_Price*(1+Coal_Esc)^6 -> 11.147461 | I104: =Coal_Price*(1+Coal_Esc)^7 -> 11.593359 | J104: =Coal_Price*(1+Coal_Esc)^8 -> 12.057093 | K104: =Coal_Price*(1+Coal_Esc)^9 -> 12.539377 | L104: =Coal_Price*(1+Coal_Esc)^10 -> 13.040952 | M104: =Coal_Price*(1+Coal_Esc)^11 -> 13.56259 | N104: =Coal_Price*(1+Coal_Esc)^12 -> 14.105094 | O104: =Coal_Price*(1+Coal_Esc)^13 -> 14.669298 | P104: =Coal_Price*(1+Coal_Esc)^14 -> 15.25607 | Q104: =Coal_Price*(1+Coal_Esc)^15 -> 15.866312 | R104: =Coal_Price*(1+Coal_Esc)^16 -> 16.500965 | S104: =Coal_Price*(1+Coal_Esc)^17 -> 17.161003 | T104: =Coal_Price*(1+Coal_Esc)^18 -> 17.847444 | U104: =Coal_Price*(1+Coal_Esc)^19 -> 18.561341 | V104: =Coal_Price*(1+Coal_Esc)^20 -> 19.303795 | W104: =Coal_Price*(1+Coal_Esc)^21 -> 20.075947 | X104: =Coal_Price*(1+Coal_Esc)^22 -> 20.878985 | Y104: =Coal_Price*(1+Coal_Esc)^23 -> 21.714144 | Z104: =Coal_Price*(1+Coal_Esc)^24 -> 22.58271 | AA104: =Coal_Price*(1+Coal_Esc)^25 -> 23.486018
A105: Fuel cost ($/MWh) = heat_rate × coal_price. Time-varying as price escalates. | B105: =B104*Coal_Heat_Rate -> 75.29907 | C105: =C104*Coal_Heat_Rate -> 78.311033 | D105: =D104*Coal_Heat_Rate -> 81.443474 | E105: =E104*Coal_Heat_Rate -> 84.701213 | F105: =F104*Coal_Heat_Rate -> 88.089262 | G105: =G104*Coal_Heat_Rate -> 91.612832 | H105: =H104*Coal_Heat_Rate -> 95.277345 | I105: =I104*Coal_Heat_Rate -> 99.088439 | ... AA105: =AA104*Coal_Heat_Rate -> 200.735
A106: ★ Derived SRMC ($/MWh) = fuel cost + variable O&M. Feeds Model R13 — replaces static Coal_SRMC assumption. | B106: =B105+Coal_VOM -> 79.97907 | C106: =C105+Coal_VOM -> 82.991033 | D106: =D105+Coal_VOM -> 86.123474 | E106: =E105+Coal_VOM -> 89.381213 | F106: =F105+Coal_VOM -> 92.769262 | G106: =G105+Coal_VOM -> 96.292832 | H106: =H105+Coal_VOM -> 99.957345 | I106: =I105+Coal_VOM -> 103.76844 | ... AA106: =AA105+Coal_VOM -> 205.415
A107: Reconciliation: derived SRMC vs Coal_SRMC assumption at t=0 (should be <$1 difference). | B107: =IF(ABS(B106-Coal_SRMC)<1,"OK — reconciles to Coal_SRMC","⚠ CHECK coal price / heat rate") -> OK — reconciles to Coal_SRMC
A108: Annual fixed cost ($m) = Coal_capacity × Coal_FOM / 1,000. Feeds Total System Cost — exists regardless of dispatch. | B108: =Model!B14*Coal_FOM/1000 -> #VALUE! | C108: =Model!C14*Coal_FOM/1000 -> 1.4267 | D108: =Model!D14*Coal_FOM/1000 -> 1.4267 | E108: =Model!E14*Coal_FOM/1000 -> 1.4267 | F108: =Model!F14*Coal_FOM/1000 -> 1.4267 | G108: =Model!G14*Coal_FOM/1000 -> 1.4267 | H108: =Model!H14*Coal_FOM/1000 -> 1.4267 | I108: =Model!I14*Coal_FOM/1000 -> 1.4267 | ... AA108: =Model!AA14*Coal_FOM/1000 -> 0.57317954
A109: E3 — Reliability degradation
A110: ★ Coal_CFe (time-varying) = Coal_CFe_start × (1−Coal_Degrade)^t. Feeds Model R15 (generation) and Total System Cost. | B110: =Coal_CFe -> 0.45 | C110: =Coal_CFe*(1-Coal_Degrade)^1 -> 0.44325 | D110: =Coal_CFe*(1-Coal_Degrade)^2 -> 0.43660125 | E110: =Coal_CFe*(1-Coal_Degrade)^3 -> 0.43005223 | F110: =Coal_CFe*(1-Coal_Degrade)^4 -> 0.42360145 | G110: =Coal_CFe*(1-Coal_Degrade)^5 -> 0.41724743 | H110: =Coal_CFe*(1-Coal_Degrade)^6 -> 0.41098871 | I110: =Coal_CFe*(1-Coal_Degrade)^7 -> 0.40482388 | J110: =Coal_CFe*(1-Coal_Degrade)^8 -> 0.39875153 | K110: =Coal_CFe*(1-Coal_Degrade)^9 -> 0.39277025 | L110: =Coal_CFe*(1-Coal_Degrade)^10 -> 0.3868787 | M110: =Coal_CFe*(1-Coal_Degrade)^11 -> 0.38107552 | N110: =Coal_CFe*(1-Coal_Degrade)^12 -> 0.37535939 | O110: =Coal_CFe*(1-Coal_Degrade)^13 -> 0.36972899 | P110: =Coal_CFe*(1-Coal_Degrade)^14 -> 0.36418306 | Q110: =Coal_CFe*(1-Coal_Degrade)^15 -> 0.35872031 | R110: =Coal_CFe*(1-Coal_Degrade)^16 -> 0.35333951 | S110: =Coal_CFe*(1-Coal_Degrade)^17 -> 0.34803942 | T110: =Coal_CFe*(1-Coal_Degrade)^18 -> 0.34281883 | U110: =Coal_CFe*(1-Coal_Degrade)^19 -> 0.33767654 | V110: =Coal_CFe*(1-Coal_Degrade)^20 -> 0.3326114 | W110: =Coal_CFe*(1-Coal_Degrade)^21 -> 0.32762222 | X110: =Coal_CFe*(1-Coal_Degrade)^22 -> 0.32270789 | Y110: =Coal_CFe*(1-Coal_Degrade)^23 -> 0.31786727 | Z110: =Coal_CFe*(1-Coal_Degrade)^24 -> 0.31309926 | AA110: =Coal_CFe*(1-Coal_Degrade)^25 -> 0.30840277
A111: ★ Coal_CFp (time-varying) = Coal_CFp_start × (1−Coal_Degrade)^t. Feeds Model R16 (firming availability). | B111: =Coal_CFp -> 0.75 | C111: =Coal_CFp*(1-Coal_Degrade)^1 -> 0.73875 | D111: =Coal_CFp*(1-Coal_Degrade)^2 -> 0.72766875 | E111: =Coal_CFp*(1-Coal_Degrade)^3 -> 0.71675372 | F111: =Coal_CFp*(1-Coal_Degrade)^4 -> 0.70600241 | G111: =Coal_CFp*(1-Coal_Degrade)^5 -> 0.69541238 | H111: =Coal_CFp*(1-Coal_Degrade)^6 -> 0.68498119 | I111: =Coal_CFp*(1-Coal_Degrade)^7 -> 0.67470647 | J111: =Coal_CFp*(1-Coal_Degrade)^8 -> 0.66458588 | K111: =Coal_CFp*(1-Coal_Degrade)^9 -> 0.65461709 | L111: =Coal_CFp*(1-Coal_Degrade)^10 -> 0.64479783 | M111: =Coal_CFp*(1-Coal_Degrade)^11 -> 0.63512586 | N111: =Coal_CFp*(1-Coal_Degrade)^12 -> 0.62559898 | O111: =Coal_CFp*(1-Coal_Degrade)^13 -> 0.61621499 | P111: =Coal_CFp*(1-Coal_Degrade)^14 -> 0.60697177 | Q111: =Coal_CFp*(1-Coal_Degrade)^15 -> 0.59786719 | R111: =Coal_CFp*(1-Coal_Degrade)^16 -> 0.58889918 | S111: =Coal_CFp*(1-Coal_Degrade)^17 -> 0.58006569 | T111: =Coal_CFp*(1-Coal_Degrade)^18 -> 0.57136471 | U111: =Coal_CFp*(1-Coal_Degrade)^19 -> 0.56279424 | V111: =Coal_CFp*(1-Coal_Degrade)^20 -> 0.55435233 | W111: =Coal_CFp*(1-Coal_Degrade)^21 -> 0.54603704 | X111: =Coal_CFp*(1-Coal_Degrade)^22 -> 0.53784648 | Y111: =Coal_CFp*(1-Coal_Degrade)^23 -> 0.52977879 | Z111: =Coal_CFp*(1-Coal_Degrade)^24 -> 0.52183211 | AA111: =Coal_CFp*(1-Coal_Degrade)^25 -> 0.51400462

Sheet Baseline
A1: ESEM Baseline — No ESEM, No Government Intervention [market dynamics identical to Model, ESEM rows = 0]
A2: Year index (t) | B2: Unit: years from base | C2: → | D2: 0 | E2: 1 | F2: 2 | G2: 3 | H2: 4 | I2: 5 | J2: 6 | K2: 7 | L2: 8 | M2: 9 | N2: 10 | O2: 11 | P2: 12 | Q2: 13 | R2: 14 | S2: 15 | T2: 16 | U2: 17 | V2: 18 | W2: 19 | X2: 20 | Y2: 21 | Z2: 22 | AA2: 23 | AB2: 24 | AC2: 25
A3: Year label | D3: Year 1 | E3: Year 2 | F3: Year 3 | G3: Year 4 | H3: Year 5 | I3: Year 6 | J3: Year 7 | K3: Year 8 | L3: Year 9 | M3: Year 10 | N3: Year 11 | O3: Year 12 | P3: Year 13 | Q3: Year 14 | R3: Year 15 | S3: Year 16 | T3: Year 17 | U3: Year 18 | V3: Year 19 | W3: Year 20 | X3: Year 21 | Y3: Year 22 | Z3: Year 23 | AA3: Year 24 | AB3: Year 25 | AC3: Year 26
A5: STEP 1 — DEMAND
A6: Demand shock (reserved for scenario use) | B6: ±frac | D6: =0 -> 0 | E6: =0 -> 0 | F6: =0 -> 0 | G6: =0 -> 0 | H6: =0 -> 0 | I6: =0 -> 0 | J6: =0 -> 0 | K6: =0 -> 0 | ... AC6: =0 -> 0
A7: Supply shock (reserved for scenario use) | B7: ±frac | D7: =0 -> 0 | E7: =0 -> 0 | F7: =0 -> 0 | G7: =0 -> 0 | H7: =0 -> 0 | I7: =0 -> 0 | J7: =0 -> 0 | K7: =0 -> 0 | ... AC7: =0 -> 0
A8: Base energy demand — grows at Dem_Growth%/yr from Dem_Start (TWh) | B8: TWh | D8: =Dem_Start -> 180 | E8: =Dem_Start*(1+Dem_Growth)^E2 -> 184.5 | F8: =Dem_Start*(1+Dem_Growth)^F2 -> 189.1125 | G8: =Dem_Start*(1+Dem_Growth)^G2 -> 193.84031 | H8: =Dem_Start*(1+Dem_Growth)^H2 -> 198.68632 | I8: =Dem_Start*(1+Dem_Growth)^I2 -> 203.65348 | J8: =Dem_Start*(1+Dem_Growth)^J2 -> 208.74482 | K8: =Dem_Start*(1+Dem_Growth)^K2 -> 213.96344 | L8: =Dem_Start*(1+Dem_Growth)^L2 -> 219.31252 | ... AC8: =Dem_Start*(1+Dem_Growth)^AC2 -> 333.70994
A9: Effective energy demand — base × demand shock multiplier (TWh) | B9: TWh | C9: R6 demand shock is 0 in base case. Scenarios can inject a step-change in demand. | D9: =D8 -> 180 | E9: =E8*(1+E6) -> 184.5 | F9: =F8*(1+F6) -> 189.1125 | G9: =G8*(1+G6) -> 193.84031 | H9: =H8*(1+H6) -> 198.68632 | I9: =I8*(1+I6) -> 203.65348 | J9: =J8*(1+J6) -> 208.74482 | K9: =K8*(1+K6) -> 213.96344 | L9: =L8*(1+L6) -> 219.31252 | ... AC9: =AC8*(1+AC6) -> 333.70994
A10: Base peak demand — grows at Peak_Growth%/yr from Peak_Start (GW) | B10: GW | D10: =Peak_Start -> 36 | E10: =Peak_Start*(1+Peak_Growth)^E2 -> 36.72 | F10: =Peak_Start*(1+Peak_Growth)^F2 -> 37.4544 | G10: =Peak_Start*(1+Peak_Growth)^G2 -> 38.203488 | H10: =Peak_Start*(1+Peak_Growth)^H2 -> 38.967558 | I10: =Peak_Start*(1+Peak_Growth)^I2 -> 39.746909 | J10: =Peak_Start*(1+Peak_Growth)^J2 -> 40.541847 | K10: =Peak_Start*(1+Peak_Growth)^K2 -> 41.352684 | L10: =Peak_Start*(1+Peak_Growth)^L2 -> 42.179738 | ... AC10: =Peak_Start*(1+Peak_Growth)^AC2 -> 59.061816
A11: Effective peak demand — used for firming adequacy test in R30 (GW) | B11: GW | C11: Firming adequacy: total firm capacity ≥ peak demand. Deficit triggers ESEM firming contracts. | D11: =D10 -> 36 | E11: =E10*(1+E6) -> 36.72 | F11: =F10*(1+F6) -> 37.4544 | G11: =G10*(1+G6) -> 38.203488 | H11: =H10*(1+H6) -> 38.967558 | I11: =I10*(1+I6) -> 39.746909 | J11: =J10*(1+J6) -> 40.541847 | K11: =K10*(1+K6) -> 41.352684 | L11: =L10*(1+L6) -> 42.179738 | ... AC11: =AC10*(1+AC6) -> 59.061816
A12: STEP 2A — COAL
A13: Coal SRMC — short-run dispatch cost, escalated for carbon over time ($/MWh) | B13: $/MWh | C13: As carbon cost rises, coal SRMC rises. When WS falls below coal SRMC, coal is uneconomic → retires. | D13: =Coal_SRMC -> 80 | E13: =Coal_SRMC*(1+Coal_Esc)^E2 -> 83.2 | F13: =Coal_SRMC*(1+Coal_Esc)^F2 -> 86.528 | G13: =Coal_SRMC*(1+Coal_Esc)^G2 -> 89.98912 | H13: =Coal_SRMC*(1+Coal_Esc)^H2 -> 93.588685 | I13: =Coal_SRMC*(1+Coal_Esc)^I2 -> 97.332232 | J13: =Coal_SRMC*(1+Coal_Esc)^J2 -> 101.22552 | K13: =Coal_SRMC*(1+Coal_Esc)^K2 -> 105.27454 | L13: =Coal_SRMC*(1+Coal_Esc)^L2 -> 109.48552 | ... AC13: =Coal_SRMC*(1+Coal_Esc)^AC2 -> 213.26691
A14: Coal capacity — retires when WS stays below coal SRMC (GW) | B14: GW | C14: Retirement rate = Coal_Accel × max(0, (SRMC−WS)/SRMC). Faster retirement when WS is deeply below SRMC. | D14: =Coal_Start -> 22 | E14: =MAX(0,D14*(1-Coal_Accel*MAX(0,(D13-D27)/D13))) -> 18.7 | F14: =MAX(0,E14*(1-Coal_Accel*MAX(0,(E13-E27)/E13))) -> #REF! | G14: =MAX(0,F14*(1-Coal_Accel*MAX(0,(F13-F27)/F13))) -> #REF! | H14: =MAX(0,G14*(1-Coal_Accel*MAX(0,(G13-G27)/G13))) -> #REF! | I14: =MAX(0,H14*(1-Coal_Accel*MAX(0,(H13-H27)/H13))) -> #REF! | J14: =MAX(0,I14*(1-Coal_Accel*MAX(0,(I13-I27)/I13))) -> #REF! | K14: =MAX(0,J14*(1-Coal_Accel*MAX(0,(J13-J27)/J13))) -> #REF! | L14: =MAX(0,K14*(1-Coal_Accel*MAX(0,(K13-K27)/K13))) -> #REF! | ... AC14: =MAX(0,AB14*(1-Coal_Accel*MAX(0,(AB13-AB27)/AB13))) -> #REF!
A15: Coal generation — capacity × coal capacity factor × 8760 hrs (TWh) | B15: TWh | D15: =D14*Coal_CFe*8.76 -> 86.724 | E15: =E14*Coal_CFe*8.76*(1+E7) -> 73.7154 | F15: =F14*Coal_CFe*8.76*(1+F7) -> #REF! | G15: =G14*Coal_CFe*8.76*(1+G7) -> #REF! | H15: =H14*Coal_CFe*8.76*(1+H7) -> #REF! | I15: =I14*Coal_CFe*8.76*(1+I7) -> #REF! | J15: =J14*Coal_CFe*8.76*(1+J7) -> #REF! | K15: =K14*Coal_CFe*8.76*(1+K7) -> #REF! | L15: =L14*Coal_CFe*8.76*(1+L7) -> #REF! | ... AC15: =AC14*Coal_CFe*8.76*(1+AC7) -> #REF!
A16: Coal peak availability — capacity × peak CF (used in firming balance R30) (GW) | B16: GW | D16: =D14*Coal_CFp -> 16.5 | E16: =E14*Coal_CFp -> 14.025 | F16: =F14*Coal_CFp -> #REF! | G16: =G14*Coal_CFp -> #REF! | H16: =H14*Coal_CFp -> #REF! | I16: =I14*Coal_CFp -> #REF! | J16: =J14*Coal_CFp -> #REF! | K16: =K14*Coal_CFp -> #REF! | ... AC16: =AC14*Coal_CFp -> #REF!
A17: STEP 2B — LEGACY DISPATCHABLE FIRMING
A18: Legacy firm capacity — existing gas/hydro/diesel decaying at Firm_Decay%/yr (GW) | B18: GW | C18: Exponential decay = asset ageing + economic exit. No retirement trigger — legacy firm retires on schedule. ESEM firming contracts (R44) replace this as it disappears. | D18: =Firm_Start -> 22 | E18: =Firm_Start*(1-Firm_Decay)^E2 -> 22 | F18: =Firm_Start*(1-Firm_Decay)^F2 -> 22 | G18: =Firm_Start*(1-Firm_Decay)^G2 -> 22 | H18: =Firm_Start*(1-Firm_Decay)^H2 -> 22 | I18: =Firm_Start*(1-Firm_Decay)^I2 -> 22 | J18: =Firm_Start*(1-Firm_Decay)^J2 -> 22 | K18: =Firm_Start*(1-Firm_Decay)^K2 -> 22 | L18: =Firm_Start*(1-Firm_Decay)^L2 -> 22 | ... AC18: =Firm_Start*(1-Firm_Decay)^AC2 -> 22
A19: Legacy firm peak availability — feeds the firming adequacy test in R30 (GW) | B19: GW | D19: =D18*Firm_CFp -> 19.8 | E19: =E18*Firm_CFp -> 19.8 | F19: =F18*Firm_CFp -> 19.8 | G19: =G18*Firm_CFp -> 19.8 | H19: =H18*Firm_CFp -> 19.8 | I19: =I18*Firm_CFp -> 19.8 | J19: =J18*Firm_CFp -> 19.8 | K19: =K18*Firm_CFp -> 19.8 | ... AC19: =AC18*Firm_CFp -> 19.8
A20: Legacy firm generation — energy output at dispatch CF (TWh) | B20: TWh | D20: =D18*Firm_CFe*8.76 -> 42.3984 | E20: =E18*Firm_CFe*8.76 -> 42.3984 | F20: =F18*Firm_CFe*8.76 -> 42.3984 | G20: =G18*Firm_CFe*8.76 -> 42.3984 | H20: =H18*Firm_CFe*8.76 -> 42.3984 | I20: =I18*Firm_CFe*8.76 -> 42.3984 | J20: =J18*Firm_CFe*8.76 -> 42.3984 | K20: =K18*Firm_CFe*8.76 -> 42.3984 | ... AC20: =AC18*Firm_CFe*8.76 -> 42.3984
A21: STEP 2C — VRE + STORAGE
A22: VRE+Storage LRMC ($/MWh) — from Building Assets R78 | B22: $/MWh | D22: =IFERROR('Building assets'!B79,0) -> 0 | E22: =IFERROR('Building assets'!C79,0) -> 0 | F22: =IFERROR('Building assets'!D79,0) -> 0 | G22: =IFERROR('Building assets'!E79,0) -> 0 | H22: =IFERROR('Building assets'!F79,0) -> 0 | I22: =IFERROR('Building assets'!G79,0) -> 0 | J22: =IFERROR('Building assets'!H79,0) -> 0 | K22: =IFERROR('Building assets'!I79,0) -> 0 | ... AC22: =IFERROR('Building assets'!AA79,0) -> 0
A23: VRE+Storage online — existing + pipeline + ESEM stock + private stock (GW) | B23: GW | C23: VRE_Start = existing fleet. VRE_PrePipe = committed pipeline (phasing in over Lag yrs). R43 = ESEM-contracted stock (online after Lag). R40 = private merchant stock. | D23: =VRE_Start+VRE_PrePipe+D43+D40 -> 33 | E23: =VRE_Start+VRE_PrePipe*MIN(E2,Lag)+E43+E40 -> #REF! | F23: =VRE_Start+VRE_PrePipe*MIN(F2,Lag)+F43+F40 -> #REF! | G23: =VRE_Start+VRE_PrePipe*MIN(G2,Lag)+G43+G40 -> #REF! | H23: =VRE_Start+VRE_PrePipe*MIN(H2,Lag)+H43+H40 -> #REF! | I23: =VRE_Start+VRE_PrePipe*MIN(I2,Lag)+I43+I40 -> #REF! | J23: =VRE_Start+VRE_PrePipe*MIN(J2,Lag)+J43+J40 -> #REF! | K23: =VRE_Start+VRE_PrePipe*MIN(K2,Lag)+K43+K40 -> #REF! | L23: =VRE_Start+VRE_PrePipe*MIN(L2,Lag)+L43+L40 -> #REF! | ... AC23: =VRE_Start+VRE_PrePipe*MIN(AC2,Lag)+AC43+AC40 -> #REF!
A24: VRE+Storage generation — online GW × CF × 8760 × (1−curtailment) (TWh) | B24: TWh | C24: Curtailment (R28) reduces gross generation when VRE share exceeds Curtail_Thresh. At 60% VRE share: zero curtailment. At 80%: (0.80−0.60)×0.25 = 5% of gross generation lost. Supply shock (R7) scales net generation for scenario use. | D24: =D23*VRE_CFe*8.76*(1-D28) -> 75.999132 | E24: =E23*VRE_CFe*8.76*(1-E28)*(1+E7) -> #REF! | F24: =F23*VRE_CFe*8.76*(1-F28)*(1+F7) -> #REF! | G24: =G23*VRE_CFe*8.76*(1-G28)*(1+G7) -> #REF! | H24: =H23*VRE_CFe*8.76*(1-H28)*(1+H7) -> #REF! | I24: =I23*VRE_CFe*8.76*(1-I28)*(1+I7) -> #REF! | J24: =J23*VRE_CFe*8.76*(1-J28)*(1+J7) -> #REF! | K24: =K23*VRE_CFe*8.76*(1-K28)*(1+K7) -> #REF! | L24: =L23*VRE_CFe*8.76*(1-L28)*(1+L7) -> #REF! | ... AC24: =AC23*VRE_CFe*8.76*(1-AC28)*(1+AC7) -> #REF!
A25: STEP 3 — PRICE FORMATION
A26: Energy balance — (coal + VRE + other) minus demand; surplus +ve, deficit -ve (TWh) | B26: TWh | C26: The key supply-demand signal. Surplus pushes WS below LRMC. Deficit pushes WS above LRMC. Other_Gen = hydro/nuclear/geothermal (fixed exogenous input). | D26: =D15+D24+Other_Gen-D9 -> #REF! | E26: =E15+E24+Other_Gen-E9 -> #REF! | F26: =F15+F24+Other_Gen-F9 -> #REF! | G26: =G15+G24+Other_Gen-G9 -> #REF! | H26: =H15+H24+Other_Gen-H9 -> #REF! | I26: =I15+I24+Other_Gen-I9 -> #REF! | J26: =J15+J24+Other_Gen-J9 -> #REF! | K26: =K15+K24+Other_Gen-K9 -> #REF! | ... AC26: =AC15+AC24+Other_Gen-AC9 -> #REF!
A27: Average wholesale spot price ($/MWh) — pivots around LRMC | B27: $/MWh | C27: Pivot = LRMC. Surplus→WS<LRMC (merit order). Deficit→WS>LRMC (investment signal). No coal ceiling. | D27: =D22 -> 0 | E27: =E22*EXP(IF(D26>=0,-Surp_Elas,Def_Elas)*ABS(D26/D9)) -> #REF! | F27: =F22*EXP(IF(E26>=0,-Surp_Elas,Def_Elas)*ABS(E26/E9)) -> #REF! | G27: =G22*EXP(IF(F26>=0,-Surp_Elas,Def_Elas)*ABS(F26/F9)) -> #REF! | H27: =H22*EXP(IF(G26>=0,-Surp_Elas,Def_Elas)*ABS(G26/G9)) -> #REF! | I27: =I22*EXP(IF(H26>=0,-Surp_Elas,Def_Elas)*ABS(H26/H9)) -> #REF! | J27: =J22*EXP(IF(I26>=0,-Surp_Elas,Def_Elas)*ABS(I26/I9)) -> #REF! | K27: =K22*EXP(IF(J26>=0,-Surp_Elas,Def_Elas)*ABS(J26/J9)) -> #REF! | L27: =L22*EXP(IF(K26>=0,-Surp_Elas,Def_Elas)*ABS(K26/K9)) -> #REF! | ... AC27: =AC22*EXP(IF(AB26>=0,-Surp_Elas,Def_Elas)*ABS(AB26/AB9)) -> #REF!
A28: VRE curtailment fraction — share of gross generation lost when VRE floods grid (hidden intermediate) | B28: — | C28: Uses prior-year VRE share (R36) to avoid circular reference. Zero until VRE share crosses Curtail_Thresh (~60%). Grows linearly with penetration above threshold. Feeds R24 generation. | D28: =0 -> 0 | E28: =MAX(0,(D36-Curtail_Thresh)*Curtail_Rate) -> 0.00575751 | F28: =MAX(0,(E36-Curtail_Thresh)*Curtail_Rate) -> #REF! | G28: =MAX(0,(F36-Curtail_Thresh)*Curtail_Rate) -> #REF! | H28: =MAX(0,(G36-Curtail_Thresh)*Curtail_Rate) -> #REF! | I28: =MAX(0,(H36-Curtail_Thresh)*Curtail_Rate) -> #REF! | J28: =MAX(0,(I36-Curtail_Thresh)*Curtail_Rate) -> #REF! | K28: =MAX(0,(J36-Curtail_Thresh)*Curtail_Rate) -> #REF! | L28: =MAX(0,(K36-Curtail_Thresh)*Curtail_Rate) -> #REF! | ... AC28: =MAX(0,(AB36-Curtail_Thresh)*Curtail_Rate) -> #REF!
A29: Forward price — weighted average of LRMC and spot (investment signal, $/MWh) | B29: $/MWh | C29: Private VRE entry (R37) triggered when fwd > LRMC. Fwd_Alpha weights current LRMC vs current spot. Higher Fwd_Alpha = more forward-looking investors (weight on long-run cost over short-run price). | D29: =Fwd_Alpha*D22+(1-Fwd_Alpha)*D27 -> #REF! | E29: =Fwd_Alpha*E22+(1-Fwd_Alpha)*E27 -> #REF! | F29: =Fwd_Alpha*F22+(1-Fwd_Alpha)*F27 -> #REF! | G29: =Fwd_Alpha*G22+(1-Fwd_Alpha)*G27 -> #REF! | H29: =Fwd_Alpha*H22+(1-Fwd_Alpha)*H27 -> #REF! | I29: =Fwd_Alpha*I22+(1-Fwd_Alpha)*I27 -> #REF! | J29: =Fwd_Alpha*J22+(1-Fwd_Alpha)*J27 -> #REF! | K29: =Fwd_Alpha*K22+(1-Fwd_Alpha)*K27 -> #REF! | ... AC29: =Fwd_Alpha*AC22+(1-Fwd_Alpha)*AC27 -> #REF!
A30: Firming balance — total firm peak availability minus peak demand; +ve = surplus (GW) | B30: GW | C30: All sources in available GW (×CFp). R16=coal×CFp, R19=legacy×CFp already applied. ESEM stock ({p}44) and private firm ({p}51) multiplied by Firm_CFp here. Prior-year lag on both avoids circular reference and is physically realistic (new capacity cannot contribute to adequacy in its first year). | D30: =D16+D19+D44*Firm_CFp+D23*VRE_ELCC+Other_Firm-D11 -> 3.3500217 | E30: =E16+E19+D44*Firm_CFp+D51*Firm_CFp+E23*VRE_ELCC+Other_Firm-E11 -> #REF! | F30: =F16+F19+E44*Firm_CFp+E51*Firm_CFp+F23*VRE_ELCC+Other_Firm-F11 -> #REF! | G30: =G16+G19+F44*Firm_CFp+F51*Firm_CFp+G23*VRE_ELCC+Other_Firm-G11 -> #REF! | H30: =H16+H19+G44*Firm_CFp+G51*Firm_CFp+H23*VRE_ELCC+Other_Firm-H11 -> #REF! | I30: =I16+I19+H44*Firm_CFp+H51*Firm_CFp+I23*VRE_ELCC+Other_Firm-I11 -> #REF! | J30: =J16+J19+I44*Firm_CFp+I51*Firm_CFp+J23*VRE_ELCC+Other_Firm-J11 -> #REF! | K30: =K16+K19+J44*Firm_CFp+J51*Firm_CFp+K23*VRE_ELCC+Other_Firm-K11 -> #REF! | L30: =L16+L19+K44*Firm_CFp+K51*Firm_CFp+L23*VRE_ELCC+Other_Firm-L11 -> #REF! | ... AC30: =AC16+AC19+AB44*Firm_CFp+AB51*Firm_CFp+AC23*VRE_ELCC+Other_Firm-AC11 -> #REF!
A31: Firming deficit fraction — max(0, deficit/peak); zero when firm capacity is adequate | B31: — | C31: Input to scarcity formula R32. As firm capacity retires (R18/R16) faster than ESEM replaces it, deficit rises → scarcity rises → private firm investment signal strengthens. | D31: =MAX(0,-D30/D11) -> 0 | E31: =MAX(0,-E30/E11) -> #REF! | F31: =MAX(0,-F30/F11) -> #REF! | G31: =MAX(0,-G30/G11) -> #REF! | H31: =MAX(0,-H30/H11) -> #REF! | I31: =MAX(0,-I30/I11) -> #REF! | J31: =MAX(0,-J30/J11) -> #REF! | K31: =MAX(0,-K30/K11) -> #REF! | ... AC31: =MAX(0,-AC30/AC11) -> #REF!
A32: Scarcity price — pivots around Firm_SRMC (dispatch cost); rises toward Firm_LRMC as firming tightens ($/MWh) | B32: $/MWh | C32: Pivot = Firm_SRMC (energy-only dispatch cost, ~$180). At zero deficit: scarcity=Firm_SRMC < Firm_LRMC → "missing money" gap. Private firm entry (R50) triggered only when scarcity rises above Firm_LRMC (~8% deficit). ESEM cap payment (R57) bridges Firm_SRMC→Firm_LRMC to attract investment before the grid is that tight. | D32: =Firm_SRMC*EXP(Firm_Tight*D31) -> 180 | E32: =Firm_SRMC*EXP(Firm_Tight*E31) -> #REF! | F32: =Firm_SRMC*EXP(Firm_Tight*F31) -> #REF! | G32: =Firm_SRMC*EXP(Firm_Tight*G31) -> #REF! | H32: =Firm_SRMC*EXP(Firm_Tight*H31) -> #REF! | I32: =Firm_SRMC*EXP(Firm_Tight*I31) -> #REF! | J32: =Firm_SRMC*EXP(Firm_Tight*J31) -> #REF! | K32: =Firm_SRMC*EXP(Firm_Tight*K31) -> #REF! | ... AC32: =Firm_SRMC*EXP(Firm_Tight*AC31) -> #REF!
A33: STEP 4 — MARKET ENTRY
A34: VRE target share of demand — linear ramp from VRE_Share0 to VRE_ShareT over 25 yrs | B34: — | C34: Policy target: society wants VRE to supply VRE_ShareT% of energy by yr 25. ESEM fills the gap between target and what private investors will build. | D34: =VRE_Share0+(VRE_ShareT-VRE_Share0)/25*D2 -> 0.383834 | E34: =VRE_Share0+(VRE_ShareT-VRE_Share0)/25*E2 -> 0.40848064 | F34: =VRE_Share0+(VRE_ShareT-VRE_Share0)/25*F2 -> 0.43312728 | G34: =VRE_Share0+(VRE_ShareT-VRE_Share0)/25*G2 -> 0.45777392 | H34: =VRE_Share0+(VRE_ShareT-VRE_Share0)/25*H2 -> 0.48242056 | I34: =VRE_Share0+(VRE_ShareT-VRE_Share0)/25*I2 -> 0.5070672 | J34: =VRE_Share0+(VRE_ShareT-VRE_Share0)/25*J2 -> 0.53171384 | K34: =VRE_Share0+(VRE_ShareT-VRE_Share0)/25*K2 -> 0.55636048 | ... AC34: =VRE_Share0+(VRE_ShareT-VRE_Share0)/25*AC2 -> 1
A35: VRE target capacity implied by share × demand ÷ (CF × 8760) (GW) | B35: GW | C35: Converts target TWh share into required GW of installed capacity at the blended VRE capacity factor. | D35: =D34*D9/(VRE_CFe*8.76) -> 30 | E35: =E34*E9/(VRE_CFe*8.76) -> 32.72451 | F35: =F34*F9/(VRE_CFe*8.76) -> 35.566496 | G35: =G34*G9/(VRE_CFe*8.76) -> 38.530128 | H35: =H34*H9/(VRE_CFe*8.76) -> 41.619713 | I35: =I34*I9/(VRE_CFe*8.76) -> 44.839696 | J35: =J34*J9/(VRE_CFe*8.76) -> 48.194665 | K35: =K34*K9/(VRE_CFe*8.76) -> 51.689359 | ... AC35: =AC34*AC9/(VRE_CFe*8.76) -> 144.90202
A36: Current VRE share of demand — actual VRE TWh ÷ demand TWh | B36: — | C36: Used in checks sheet. If this exceeds VRE target (R34) ESEM contracts nothing — private market leading. | D36: =IF(D9>0,D24/D9,0) -> 0.4222174 | E36: =IF(E9>0,E24/E9,0) -> #REF! | F36: =IF(F9>0,F24/F9,0) -> #REF! | G36: =IF(G9>0,G24/G9,0) -> #REF! | H36: =IF(H9>0,H24/H9,0) -> #REF! | I36: =IF(I9>0,I24/I9,0) -> #REF! | J36: =IF(J9>0,J24/J9,0) -> #REF! | K36: =IF(K9>0,K24/K9,0) -> #REF! | ... AC36: =IF(AC9>0,AC24/AC9,0) -> #REF!
A37: Private VRE build — linear supply curve: GW/yr per $/MWh above LRMC (GW/yr) | B37: GW/yr | C37: VRE_Sprd = spread required to attract investment above LRMC. When fwd = LRMC: zero private build. When fwd > LRMC: build accelerates linearly. No ESEM needed if private market fills the gap first. | D37: =MAX(0,(D29-D22)/VRE_Sprd) -> #REF! | E37: =MAX(0,(E29-E22)/VRE_Sprd) -> #REF! | F37: =MAX(0,(F29-F22)/VRE_Sprd) -> #REF! | G37: =MAX(0,(G29-G22)/VRE_Sprd) -> #REF! | H37: =MAX(0,(H29-H22)/VRE_Sprd) -> #REF! | I37: =MAX(0,(I29-I22)/VRE_Sprd) -> #REF! | J37: =MAX(0,(J29-J22)/VRE_Sprd) -> #REF! | K37: =MAX(0,(K29-K22)/VRE_Sprd) -> #REF! | ... AC37: =MAX(0,(AC29-AC22)/VRE_Sprd) -> #REF!
A38: ESEM VRE contracted — covers RE_Cov fraction of shortfall to target, per year (GW/yr) | B38: GW/yr | C38: Contracts signed now; plants online after Lag years. Yr1: prior VRE = VRE_Start+PrePipe. Yr2+: uses prior-col R23 to avoid circular reference. RE_Cov < 1 leaves room for private build. Contracts: ESEM holds for Recycle_Lag yrs, then sells. | D38: 0 | E38: 0 | F38: 0 | G38: 0 | H38: 0 | I38: 0 | J38: 0 | K38: 0 | L38: 0 | M38: 0 | N38: 0 | O38: 0 | P38: 0 | Q38: 0 | R38: 0 | S38: 0 | T38: 0 | U38: 0 | V38: 0 | W38: 0 | X38: 0 | Y38: 0 | Z38: 0 | AA38: 0 | AB38: 0 | AC38: 0
A39: Firming shortfall — peak demand minus firm peak availability (GW) | B39: GW | C39: Mirrors firming balance (R30): all firm sources in available GW (×Firm_CFp). Prior-year ESEM ({p}44×CFp) and prior-year private ({p}51×CFp) avoid circular reference and correctly reflect capacity already reliably online. ESEM contracts only what legacy + existing firm stock cannot cover. | D39: =MAX(0,D11-(D16+D19+D23*VRE_ELCC+Other_Firm)) -> 0 | E39: =MAX(0,E11-(E16+E19+D44*Firm_CFp+D51*Firm_CFp+E23*VRE_ELCC+Other_Firm)) -> #REF! | F39: =MAX(0,F11-(F16+F19+E44*Firm_CFp+E51*Firm_CFp+F23*VRE_ELCC+Other_Firm)) -> #REF! | G39: =MAX(0,G11-(G16+G19+F44*Firm_CFp+F51*Firm_CFp+G23*VRE_ELCC+Other_Firm)) -> #REF! | H39: =MAX(0,H11-(H16+H19+G44*Firm_CFp+G51*Firm_CFp+H23*VRE_ELCC+Other_Firm)) -> #REF! | I39: =MAX(0,I11-(I16+I19+H44*Firm_CFp+H51*Firm_CFp+I23*VRE_ELCC+Other_Firm)) -> #REF! | J39: =MAX(0,J11-(J16+J19+I44*Firm_CFp+I51*Firm_CFp+J23*VRE_ELCC+Other_Firm)) -> #REF! | K39: =MAX(0,K11-(K16+K19+J44*Firm_CFp+J51*Firm_CFp+K23*VRE_ELCC+Other_Firm)) -> #REF! | L39: =MAX(0,L11-(L16+L19+K44*Firm_CFp+K51*Firm_CFp+L23*VRE_ELCC+Other_Firm)) -> #REF! | ... AC39: =MAX(0,AC11-(AC16+AC19+AB44*Firm_CFp+AB51*Firm_CFp+AC23*VRE_ELCC+Other_Firm)) -> #REF!
A40: Private VRE cumulative stock — builds when fwd > LRMC, depreciates at VRE_Dep (GW) | B40: GW | C40: Merchant VRE: no ESEM de-risking, builds only when market signal strong. This competes with and reduces ESEM contracted volumes (via R23 → R38). | D40: =0 -> 0 | E40: =D40*(1-VRE_Dep)+E37 -> #REF! | F40: =E40*(1-VRE_Dep)+F37 -> #REF! | G40: =F40*(1-VRE_Dep)+G37 -> #REF! | H40: =G40*(1-VRE_Dep)+H37 -> #REF! | I40: =H40*(1-VRE_Dep)+I37 -> #REF! | J40: =I40*(1-VRE_Dep)+J37 -> #REF! | K40: =J40*(1-VRE_Dep)+K37 -> #REF! | L40: =K40*(1-VRE_Dep)+L37 -> #REF! | ... AC40: =AB40*(1-VRE_Dep)+AC37 -> #REF!
A41: ESEM firming contracted — covers Firm_Cov fraction of firming shortfall (GW/yr) | B41: GW/yr | C41: ESEM signs cap contracts with firm generators → gives them revenue certainty to invest. Cap contracts then sold on to retailers (R57). Net margin feeds levy (R63). | D41: 0 | E41: 0 | F41: 0 | G41: 0 | H41: 0 | I41: 0 | J41: 0 | K41: 0 | L41: 0 | M41: 0 | N41: 0 | O41: 0 | P41: 0 | Q41: 0 | R41: 0 | S41: 0 | T41: 0 | U41: 0 | V41: 0 | W41: 0 | X41: 0 | Y41: 0 | Z41: 0 | AA41: 0 | AB41: 0 | AC41: 0
A42: STEP 5 — CUMULATIVE STOCKS
A43: ESEM VRE cumulative stock — contracted GW that is now online and generating (GW) | B43: GW | C43: Stock accumulates as ESEM contracts (R38) come online after Lag years, depreciating at VRE_Dep. ESEM still holds the two-way CfD contracts for Recycle_Lag years; recycling revenue (R49) realised once contracts sold to retailers. | D43: 0 | E43: 0 | F43: 0 | G43: 0 | H43: 0 | I43: 0 | J43: 0 | K43: 0 | L43: 0 | M43: 0 | N43: 0 | O43: 0 | P43: 0 | Q43: 0 | R43: 0 | S43: 0 | T43: 0 | U43: 0 | V43: 0 | W43: 0 | X43: 0 | Y43: 0 | Z43: 0 | AA43: 0 | AB43: 0 | AC43: 0
A44: ESEM firming cumulative stock — ESEM-contracted firm capacity online (GW) | B44: GW | C44: Accumulates as ESEM firm contracts (R41) come online. No depreciation — firm assets long-lived. This stock underpins the cap mechanism (R46 mirrors R44 → feeds R56/R57). | D44: 0 | E44: 0 | F44: 0 | G44: 0 | H44: 0 | I44: 0 | J44: 0 | K44: 0 | L44: 0 | M44: 0 | N44: 0 | O44: 0 | P44: 0 | Q44: 0 | R44: 0 | S44: 0 | T44: 0 | U44: 0 | V44: 0 | W44: 0 | X44: 0 | Y44: 0 | Z44: 0 | AA44: 0 | AB44: 0 | AC44: 0
A45: STEP 6 — ESEM COST RECOVERY
D46: 0 | E46: 0 | F46: 0 | G46: 0 | H46: 0 | I46: 0 | J46: 0 | K46: 0 | L46: 0 | M46: 0 | N46: 0 | O46: 0 | P46: 0 | Q46: 0 | R46: 0 | S46: 0 | T46: 0 | U46: 0 | V46: 0 | W46: 0 | X46: 0 | Y46: 0 | Z46: 0 | AA46: 0 | AB46: 0 | AC46: 0
A47: VRE GW recycled — contracts sold to retailers (GW contracted Recycle_Lag yrs ago) | B47: GW/yr | C47: ESEM holds VRE contracts for Recycle_Lag yrs (admin only). Then sells to retailers — OFFSET looks back Recycle_Lag cols to find the matching contracting year. Zero until yr = Recycle_Lag. | D47: 0 | E47: 0 | F47: 0 | G47: 0 | H47: 0 | I47: 0 | J47: 0 | K47: 0 | L47: 0 | M47: 0 | N47: 0 | O47: 0 | P47: 0 | Q47: 0 | R47: 0 | S47: 0 | T47: 0 | U47: 0 | V47: 0 | W47: 0 | X47: 0 | Y47: 0 | Z47: 0 | AA47: 0 | AB47: 0 | AC47: 0
A48: Vintage LRMC — strike price locked when VRE contracts were first signed ($/MWh) | B48: $/MWh | C48: Hidden intermediate. OFFSET retrieves LRMC from Recycle_Lag yrs ago — this is the fixed strike in the VRE contract. | D48: 0 | E48: 0 | F48: 0 | G48: 0 | H48: 0 | I48: 0 | J48: 0 | K48: 0 | L48: 0 | M48: 0 | N48: 0 | O48: 0 | P48: 0 | Q48: 0 | R48: 0 | S48: 0 | T48: 0 | U48: 0 | V48: 0 | W48: 0 | X48: 0 | Y48: 0 | Z48: 0 | AA48: 0 | AB48: 0 | AC48: 0
A49: Recycling revenue — (fwd−vintage_LRMC) × recycled GW × energy × remaining yrs ($m) | B49: $m | C49: Positive when fwd > vintage_LRMC (market developed — ESEM sold low, buys high). Negative when fwd < vintage_LRMC (early years, ESEM pays the difference). Retailers receive the contract and take on two-way obligation for remaining yrs. | D49: 0 | E49: 0 | F49: 0 | G49: 0 | H49: 0 | I49: 0 | J49: 0 | K49: 0 | L49: 0 | M49: 0 | N49: 0 | O49: 0 | P49: 0 | Q49: 0 | R49: 0 | S49: 0 | T49: 0 | U49: 0 | V49: 0 | W49: 0 | X49: 0 | Y49: 0 | Z49: 0 | AA49: 0 | AB49: 0 | AC49: 0
A50: Private firm build — enters when scarcity > Firm_LRMC (no ESEM support needed) (GW/yr) | B50: GW/yr | C50: Analogous to private VRE (R37) but for firm capacity. Firm_Sprd = $/MWh above Firm_LRMC needed to attract investment (risk premium). At Firm_SRMC anchor, scarcity must rise ~8% deficit before private firm enters. ESEM caps attract firm investment BEFORE this point via capacity payment. | D50: =MAX(0,(D32-Firm_LRMC)/Firm_Sprd) -> 0 | E50: =MAX(0,(E32-Firm_LRMC)/Firm_Sprd) -> #REF! | F50: =MAX(0,(F32-Firm_LRMC)/Firm_Sprd) -> #REF! | G50: =MAX(0,(G32-Firm_LRMC)/Firm_Sprd) -> #REF! | H50: =MAX(0,(H32-Firm_LRMC)/Firm_Sprd) -> #REF! | I50: =MAX(0,(I32-Firm_LRMC)/Firm_Sprd) -> #REF! | J50: =MAX(0,(J32-Firm_LRMC)/Firm_Sprd) -> #REF! | K50: =MAX(0,(K32-Firm_LRMC)/Firm_Sprd) -> #REF! | ... AC50: =MAX(0,(AC32-Firm_LRMC)/Firm_Sprd) -> #REF!
A51: Private firm cumulative stock — merchant firm capacity built without ESEM support (GW) | B51: GW | C51: Accumulates as private firm builds (R50). Reduces firming shortfall (R39) → reduces ESEM contracting. Also feeds firming balance (R30) with 1-year lag (prior col) to avoid circular reference. Depreciates at Firm_Decay. In baseline (no ESEM): deficit likely larger → higher scarcity → more private build. | D51: =0 -> 0 | E51: =D51*(1-Firm_Decay)+E50 -> #REF! | F51: =E51*(1-Firm_Decay)+F50 -> #REF! | G51: =F51*(1-Firm_Decay)+G50 -> #REF! | H51: =G51*(1-Firm_Decay)+H50 -> #REF! | I51: =H51*(1-Firm_Decay)+I50 -> #REF! | J51: =I51*(1-Firm_Decay)+J50 -> #REF! | K51: =J51*(1-Firm_Decay)+K50 -> #REF! | L51: =K51*(1-Firm_Decay)+L50 -> #REF! | ... AC51: =AB51*(1-Firm_Decay)+AC50 -> #REF!
A52: — FIRMING CfD —
A53: Firming CfD — (scarcity−Firm_LRMC)×firm GW×Firm_CFe×8760 ($m, −ve = ESEM cost) | B53: $m | C53: CFe (energy dispatch factor ~0.22) not CFp (availability ~0.90): CfD settles on actual MWh dispatched, not availability hours. Negative when scarcity<Firm_LRMC: ESEM pays firm generators the gap (missing money subsidy). Positive when scarcity>Firm_LRMC: generators pay ESEM (cost recovery in tight years). | D53: 0 | E53: 0 | F53: 0 | G53: 0 | H53: 0 | I53: 0 | J53: 0 | K53: 0 | L53: 0 | M53: 0 | N53: 0 | O53: 0 | P53: 0 | Q53: 0 | R53: 0 | S53: 0 | T53: 0 | U53: 0 | V53: 0 | W53: 0 | X53: 0 | Y53: 0 | Z53: 0 | AA53: 0 | AB53: 0 | AC53: 0
A54: [Removed — firming CfD replaces cap mechanism] | D54: 0 | E54: 0 | F54: 0 | G54: 0 | H54: 0 | I54: 0 | J54: 0 | K54: 0 | L54: 0 | M54: 0 | N54: 0 | O54: 0 | P54: 0 | Q54: 0 | R54: 0 | S54: 0 | T54: 0 | U54: 0 | V54: 0 | W54: 0 | X54: 0 | Y54: 0 | Z54: 0 | AA54: 0 | AB54: 0 | AC54: 0
A55: [Removed — firming CfD replaces cap mechanism] | D55: 0 | E55: 0 | F55: 0 | G55: 0 | H55: 0 | I55: 0 | J55: 0 | K55: 0 | L55: 0 | M55: 0 | N55: 0 | O55: 0 | P55: 0 | Q55: 0 | R55: 0 | S55: 0 | T55: 0 | U55: 0 | V55: 0 | W55: 0 | X55: 0 | Y55: 0 | Z55: 0 | AA55: 0 | AB55: 0 | AC55: 0
A56: [Removed — firming CfD replaces cap mechanism] | D56: 0 | E56: 0 | F56: 0 | G56: 0 | H56: 0 | I56: 0 | J56: 0 | K56: 0 | L56: 0 | M56: 0 | N56: 0 | O56: 0 | P56: 0 | Q56: 0 | R56: 0 | S56: 0 | T56: 0 | U56: 0 | V56: 0 | W56: 0 | X56: 0 | Y56: 0 | Z56: 0 | AA56: 0 | AB56: 0 | AC56: 0
A57: [Removed — firming CfD replaces cap mechanism] | D57: 0 | E57: 0 | F57: 0 | G57: 0 | H57: 0 | I57: 0 | J57: 0 | K57: 0 | L57: 0 | M57: 0 | N57: 0 | O57: 0 | P57: 0 | Q57: 0 | R57: 0 | S57: 0 | T57: 0 | U57: 0 | V57: 0 | W57: 0 | X57: 0 | Y57: 0 | Z57: 0 | AA57: 0 | AB57: 0 | AC57: 0
A58: [Removed — firming CfD replaces cap mechanism] | D58: 0 | E58: 0 | F58: 0 | G58: 0 | H58: 0 | I58: 0 | J58: 0 | K58: 0 | L58: 0 | M58: 0 | N58: 0 | O58: 0 | P58: 0 | Q58: 0 | R58: 0 | S58: 0 | T58: 0 | U58: 0 | V58: 0 | W58: 0 | X58: 0 | Y58: 0 | Z58: 0 | AA58: 0 | AB58: 0 | AC58: 0
A59: — FISCAL SUMMARY —
A60: Admin cost — always negative (outflow) ($m/yr) | B60: $m | C60: Hidden intermediate. Negative by convention: admin is always a cost outflow. | D60: 0 | E60: 0 | F60: 0 | G60: 0 | H60: 0 | I60: 0 | J60: 0 | K60: 0 | L60: 0 | M60: 0 | N60: 0 | O60: 0 | P60: 0 | Q60: 0 | R60: 0 | S60: 0 | T60: 0 | U60: 0 | V60: 0 | W60: 0 | X60: 0 | Y60: 0 | Z60: 0 | AA60: 0 | AB60: 0 | AC60: 0
A61: Net annual ESEM P&L — sum of all signed flows; negative = cost to consumers ($m) | B61: $m | C61: Sign convention: all flows negative when cost, positive when revenue. R60 = −Admin (always −ve). R49 = recycling (−ve when fwd < vintage LRMC, i.e. ESEM pays to recycle early). R53 = firming CfD (−ve when scarcity < Firm_LRMC = missing money subsidy). Negative net = consumers pay levy. Positive net = levy is a rebate. | D61: 0 | E61: 0 | F61: 0 | G61: 0 | H61: 0 | I61: 0 | J61: 0 | K61: 0 | L61: 0 | M61: 0 | N61: 0 | O61: 0 | P61: 0 | Q61: 0 | R61: 0 | S61: 0 | T61: 0 | U61: 0 | V61: 0 | W61: 0 | X61: 0 | Y61: 0 | Z61: 0 | AA61: 0 | AB61: 0 | AC61: 0
A62: Cumulative ESEM P&L — running total; negative = cumulative cost to consumers ($bn) | B62: $bn | C62: Tracks total fiscal exposure. Increasingly negative as ESEM subsidises investment. | D62: 0 | E62: 0 | F62: 0 | G62: 0 | H62: 0 | I62: 0 | J62: 0 | K62: 0 | L62: 0 | M62: 0 | N62: 0 | O62: 0 | P62: 0 | Q62: 0 | R62: 0 | S62: 0 | T62: 0 | U62: 0 | V62: 0 | W62: 0 | X62: 0 | Y62: 0 | Z62: 0 | AA62: 0 | AB62: 0 | AC62: 0
A63: ESEM levy — −P&L ÷ demand; positive = consumers pay, negative = rebate ($/MWh) | B63: $/MWh | C63: Levy = −(net P&L) ÷ demand. Positive when P&L negative (ESEM costs money → consumers pay). Broadly positive during holding period (admin only) and firming subsidy years. Can turn negative if recycling revenue flows exceed ongoing costs. | D63: 0 | E63: 0 | F63: 0 | G63: 0 | H63: 0 | I63: 0 | J63: 0 | K63: 0 | L63: 0 | M63: 0 | N63: 0 | O63: 0 | P63: 0 | Q63: 0 | R63: 0 | S63: 0 | T63: 0 | U63: 0 | V63: 0 | W63: 0 | X63: 0 | Y63: 0 | Z63: 0 | AA63: 0 | AB63: 0 | AC63: 0
A64: STEP 7 — CONSUMER PRICES
A65: Consumer price — wholesale spot price + ESEM levy ($/MWh) | B65: $/MWh | C65: The ultimate policy question: is the consumer better off with ESEM? Compare with Baseline (R65 = WS only, no levy). ESEM wins if lower LRMC due to lower WACC offsets the levy — i.e., de-risking saves more than administration costs. | D65: =D27 -> 0 | E65: =E27 -> #REF! | F65: =F27 -> #REF! | G65: =G27 -> #REF! | H65: =H27 -> #REF! | I65: =I27 -> #REF! | J65: =J27 -> #REF! | K65: =K27 -> #REF! | ... AC65: =AC27 -> #REF!
A66: Merchant viability — wholesale price ÷ LRMC; >1 = merchant investment viable | B66: — | C66: Ratio < 1 = private market cannot recover LRMC from merchant revenues alone → ESEM needed. Ratio > 1 = private VRE entry profitable → private build (R37) accelerates → ESEM contracts less. | D66: =IF(D22>0,D27/D22,0) -> 0 | E66: =IF(E22>0,E27/E22,0) -> 0 | F66: =IF(F22>0,F27/F22,0) -> 0 | G66: =IF(G22>0,G27/G22,0) -> 0 | H66: =IF(H22>0,H27/H22,0) -> 0 | I66: =IF(I22>0,I27/I22,0) -> 0 | J66: =IF(J22>0,J27/J22,0) -> 0 | K66: =IF(K22>0,K27/K22,0) -> 0 | ... AC66: =IF(AC22>0,AC27/AC22,0) -> 0

Sheet Model
A1: ESEM Model — Time Series Calculations [formulas only — do not edit]
A2: Year index (t) | B2: Unit: years from base | C2: 0 | D2: 1 | E2: 2 | F2: 3 | G2: 4 | H2: 5 | I2: 6 | J2: 7 | K2: 8 | L2: 9 | M2: 10 | N2: 11 | O2: 12 | P2: 13 | Q2: 14 | R2: 15 | S2: 16 | T2: 17 | U2: 18 | V2: 19 | W2: 20 | X2: 21 | Y2: 22 | Z2: 23 | AA2: 24 | AB2: 25
A3: Year label | C3: Year 1 | D3: Year 2 | E3: Year 3 | F3: Year 4 | G3: Year 5 | H3: Year 6 | I3: Year 7 | J3: Year 8 | K3: Year 9 | L3: Year 10 | M3: Year 11 | N3: Year 12 | O3: Year 13 | P3: Year 14 | Q3: Year 15 | R3: Year 16 | S3: Year 17 | T3: Year 18 | U3: Year 19 | V3: Year 20 | W3: Year 21 | X3: Year 22 | Y3: Year 23 | Z3: Year 24 | AA3: Year 25 | AB3: Year 26
A5: DEMAND
A6: Demand shock (reserved for scenario use) | B6: ±frac | C6: 0 | D6: =0 -> 0 | E6: =0 -> 0 | F6: =0 -> 0 | G6: =0 -> 0 | H6: =0 -> 0 | I6: =0 -> 0 | J6: =0 -> 0 | K6: =0 -> 0 | ... AB6: =0 -> 0
A7: Supply shock (reserved for scenario use) | B7: ±frac | C7: 0 | D7: =0 -> 0 | E7: =0 -> 0 | F7: =0 -> 0 | G7: =0 -> 0 | H7: =0 -> 0 | I7: =0 -> 0 | J7: =0 -> 0 | K7: =0 -> 0 | ... AB7: =0 -> 0
A8: Base energy demand | B8: TWh | C8: =Dem_Start -> 180 | D8: =Dem_Start*(1+Dem_Growth)^D2 -> 184.5 | E8: =Dem_Start*(1+Dem_Growth)^E2 -> 189.1125 | F8: =Dem_Start*(1+Dem_Growth)^F2 -> 193.84031 | G8: =Dem_Start*(1+Dem_Growth)^G2 -> 198.68632 | H8: =Dem_Start*(1+Dem_Growth)^H2 -> 203.65348 | I8: =Dem_Start*(1+Dem_Growth)^I2 -> 208.74482 | J8: =Dem_Start*(1+Dem_Growth)^J2 -> 213.96344 | K8: =Dem_Start*(1+Dem_Growth)^K2 -> 219.31252 | ... AB8: =Dem_Start*(1+Dem_Growth)^AB2 -> 333.70994
A9: Effective energy demand | B9: TWh | C9: =C8 -> 180 | D9: =D8*(1+D6) -> 184.5 | E9: =E8*(1+E6) -> 189.1125 | F9: =F8*(1+F6) -> 193.84031 | G9: =G8*(1+G6) -> 198.68632 | H9: =H8*(1+H6) -> 203.65348 | I9: =I8*(1+I6) -> 208.74482 | J9: =J8*(1+J6) -> 213.96344 | K9: =K8*(1+K6) -> 219.31252 | ... AB9: =AB8*(1+AB6) -> 333.70994
A10: Base peak demand | B10: GW | C10: =Peak_Start -> 36 | D10: =Peak_Start*(1+Peak_Growth)^D2 -> 36.72 | E10: =Peak_Start*(1+Peak_Growth)^E2 -> 37.4544 | F10: =Peak_Start*(1+Peak_Growth)^F2 -> 38.203488 | G10: =Peak_Start*(1+Peak_Growth)^G2 -> 38.967558 | H10: =Peak_Start*(1+Peak_Growth)^H2 -> 39.746909 | I10: =Peak_Start*(1+Peak_Growth)^I2 -> 40.541847 | J10: =Peak_Start*(1+Peak_Growth)^J2 -> 41.352684 | K10: =Peak_Start*(1+Peak_Growth)^K2 -> 42.179738 | ... AB10: =Peak_Start*(1+Peak_Growth)^AB2 -> 59.061816
A11: Effective peak demand | B11: GW | C11: =C10 -> 36 | D11: =D10*(1+D6) -> 36.72 | E11: =E10*(1+E6) -> 37.4544 | F11: =F10*(1+F6) -> 38.203488 | G11: =G10*(1+G6) -> 38.967558 | H11: =H10*(1+H6) -> 39.746909 | I11: =I10*(1+I6) -> 40.541847 | J11: =J10*(1+J6) -> 41.352684 | K11: =K10*(1+K6) -> 42.179738 | ... AB11: =AB10*(1+AB6) -> 59.061816
A12: COAL
A13: Coal SRMC ($/MWh) — derived from BA Section E (fuel + VOM), escalating | B13: $/MWh | C13: =IFERROR('Building assets'!B106,Coal_SRMC) -> 79.97907 | D13: =IFERROR('Building assets'!C106,Coal_SRMC) -> 82.991033 | E13: =IFERROR('Building assets'!D106,Coal_SRMC) -> 86.123474 | F13: =IFERROR('Building assets'!E106,Coal_SRMC) -> 89.381213 | G13: =IFERROR('Building assets'!F106,Coal_SRMC) -> 92.769262 | H13: =IFERROR('Building assets'!G106,Coal_SRMC) -> 96.292832 | I13: =IFERROR('Building assets'!H106,Coal_SRMC) -> 99.957345 | J13: =IFERROR('Building assets'!I106,Coal_SRMC) -> 103.76844 | ... AB13: =IFERROR('Building assets'!AA106,Coal_SRMC) -> 205.415
A14: Coal capacity | B14: GW | C14: =Coal_Start -> 22 | D14: =MAX(0,C14*(1-Coal_Accel*MAX(0,(C13-C27)/C13))) -> 22 | E14: =MAX(0,D14*(1-Coal_Accel*MAX(0,(D13-D27)/D13))) -> 22 | F14: =MAX(0,E14*(1-Coal_Accel*MAX(0,(E13-E27)/E13))) -> 22 | G14: =MAX(0,F14*(1-Coal_Accel*MAX(0,(F13-F27)/F13))) -> 22 | H14: =MAX(0,G14*(1-Coal_Accel*MAX(0,(G13-G27)/G13))) -> 22 | I14: =MAX(0,H14*(1-Coal_Accel*MAX(0,(H13-H27)/H13))) -> 22 | J14: =MAX(0,I14*(1-Coal_Accel*MAX(0,(I13-I27)/I13))) -> 22 | K14: =MAX(0,J14*(1-Coal_Accel*MAX(0,(J13-J27)/J13))) -> 21.91168 | ... AB14: =MAX(0,AA14*(1-Coal_Accel*MAX(0,(AA13-AA27)/AA13))) -> 8.0227624
A15: Coal generation (TWh) — uses time-varying CFe with reliability degradation | B15: TWh | C15: =C14*IFERROR('Building assets'!B110,Coal_CFe)*8.76 -> 86.724 | D15: =D14*IFERROR('Building assets'!C110,Coal_CFe)*8.76 -> 85.42314 | E15: =E14*IFERROR('Building assets'!D110,Coal_CFe)*8.76 -> 84.141793 | F15: =F14*IFERROR('Building assets'!E110,Coal_CFe)*8.76 -> 82.879666 | G15: =G14*IFERROR('Building assets'!F110,Coal_CFe)*8.76 -> 81.636471 | H15: =H14*IFERROR('Building assets'!G110,Coal_CFe)*8.76 -> 80.411924 | I15: =I14*IFERROR('Building assets'!H110,Coal_CFe)*8.76 -> 79.205745 | J15: =J14*IFERROR('Building assets'!I110,Coal_CFe)*8.76 -> 78.017659 | ... AB15: =AB14*IFERROR('Building assets'!AA110,Coal_CFe)*8.76 -> 21.674362
A16: Coal firming availability (GW) — uses time-varying CFp with reliability degradation | B16: GW | C16: =C14*IFERROR('Building assets'!B111,Coal_CFp) -> 16.5 | D16: =D14*IFERROR('Building assets'!C111,Coal_CFp) -> 16.2525 | E16: =E14*IFERROR('Building assets'!D111,Coal_CFp) -> 16.008712 | F16: =F14*IFERROR('Building assets'!E111,Coal_CFp) -> 15.768582 | G16: =G14*IFERROR('Building assets'!F111,Coal_CFp) -> 15.532053 | H16: =H14*IFERROR('Building assets'!G111,Coal_CFp) -> 15.299072 | I16: =I14*IFERROR('Building assets'!H111,Coal_CFp) -> 15.069586 | J16: =J14*IFERROR('Building assets'!I111,Coal_CFp) -> 14.843542 | ... AB16: =AB14*IFERROR('Building assets'!AA111,Coal_CFp) -> 4.123737
A17: LEGACY DISPATCHABLE FIRMING
A18: Legacy firm capacity | B18: GW | C18: =Firm_Start -> 22 | D18: =Firm_Start*(1-Firm_Decay)^D2 -> 22 | E18: =Firm_Start*(1-Firm_Decay)^E2 -> 22 | F18: =Firm_Start*(1-Firm_Decay)^F2 -> 22 | G18: =Firm_Start*(1-Firm_Decay)^G2 -> 22 | H18: =Firm_Start*(1-Firm_Decay)^H2 -> 22 | I18: =Firm_Start*(1-Firm_Decay)^I2 -> 22 | J18: =Firm_Start*(1-Firm_Decay)^J2 -> 22 | K18: =Firm_Start*(1-Firm_Decay)^K2 -> 22 | ... AB18: =Firm_Start*(1-Firm_Decay)^AB2 -> 22
A19: Legacy firm peak availability | B19: GW | C19: =C18*Firm_CFp -> 19.8 | D19: =D18*Firm_CFp -> 19.8 | E19: =E18*Firm_CFp -> 19.8 | F19: =F18*Firm_CFp -> 19.8 | G19: =G18*Firm_CFp -> 19.8 | H19: =H18*Firm_CFp -> 19.8 | I19: =I18*Firm_CFp -> 19.8 | J19: =J18*Firm_CFp -> 19.8 | ... AB19: =AB18*Firm_CFp -> 19.8
A20: Legacy firm generation | B20: TWh | C20: =C18*Firm_CFe*8.76 -> 42.3984 | D20: =D18*Firm_CFe*8.76 -> 42.3984 | E20: =E18*Firm_CFe*8.76 -> 42.3984 | F20: =F18*Firm_CFe*8.76 -> 42.3984 | G20: =G18*Firm_CFe*8.76 -> 42.3984 | H20: =H18*Firm_CFe*8.76 -> 42.3984 | I20: =I18*Firm_CFe*8.76 -> 42.3984 | J20: =J18*Firm_CFe*8.76 -> 42.3984 | ... AB20: =AB18*Firm_CFe*8.76 -> 42.3984
A21: VRE + STORAGE
A22: VRE+Storage LRMC (curtailment-adjusted) | B22: $/MWh | C22: =IFERROR('Building assets'!B78,0) -> 112.22814 | D22: ='Building assets'!C78/(1-MAX(0,C28)) -> 105.35894 | E22: ='Building assets'!D78/(1-MAX(0,D28)) -> 101.50142 | F22: ='Building assets'!E78/(1-MAX(0,E28)) -> 97.872068 | G22: ='Building assets'!F78/(1-MAX(0,F28)) -> 95.138254 | H22: ='Building assets'!G78/(1-MAX(0,G28)) -> 91.853257 | I22: ='Building assets'!H78/(1-MAX(0,H28)) -> 88.844946 | J22: ='Building assets'!I78/(1-MAX(0,I28)) -> 86.775365 | K22: ='Building assets'!J78/(1-MAX(0,J28)) -> 84.717968 | ... AB22: ='Building assets'!AA78/(1-MAX(0,AA28)) -> 78.824379
A23: VRE+Storage online | B23: GW | C23: =VRE_Start+VRE_PrePipe+C43+C40 -> 35 | D23: =VRE_Start+VRE_PrePipe*MIN(D2,Lag)+D43+D40 -> 36.187673 | E23: =VRE_Start+VRE_PrePipe*MIN(E2,Lag)+E43+E40 -> 41.94278 | F23: =VRE_Start+VRE_PrePipe*MIN(F2,Lag)+F43+F40 -> 44.94278 | G23: =VRE_Start+VRE_PrePipe*MIN(G2,Lag)+G43+G40 -> 44.94278 | H23: =VRE_Start+VRE_PrePipe*MIN(H2,Lag)+H43+H40 -> 47.693266 | I23: =VRE_Start+VRE_PrePipe*MIN(I2,Lag)+I43+I40 -> 50.262399 | J23: =VRE_Start+VRE_PrePipe*MIN(J2,Lag)+J43+J40 -> 53.231679 | K23: =VRE_Start+VRE_PrePipe*MIN(K2,Lag)+K43+K40 -> 56.612355 | ... AB23: =VRE_Start+VRE_PrePipe*MIN(AB2,Lag)+AB43+AB40 -> 140.48582
A24: VRE+Storage generation (curtailment-adjusted) | B24: TWh | C24: =C23*VRE_CFe*8.76*(1-C28) -> 80.60514 | D24: =D23*VRE_CFe*8.76*(1-D28)*(1+D7) -> 82.540633 | E24: =E23*VRE_CFe*8.76*(1-E28)*(1+E7) -> 95.673738 | F24: =F23*VRE_CFe*8.76*(1-F28)*(1+F7) -> 101.60812 | G24: =G23*VRE_CFe*8.76*(1-G28)*(1+G7) -> 101.32439 | H24: =H23*VRE_CFe*8.76*(1-H28)*(1+H7) -> 107.75958 | I24: =I23*VRE_CFe*8.76*(1-I28)*(1+I7) -> 113.23167 | J24: =J23*VRE_CFe*8.76*(1-J28)*(1+J7) -> 119.67617 | K24: =K23*VRE_CFe*8.76*(1-K28)*(1+K7) -> 126.94635 | ... AB24: =AB23*VRE_CFe*8.76*(1-AB28)*(1+AB7) -> 299.34219
A25: PRICE FORMATION
A26: Energy balance (TWh) — coal + VRE + total firm capacity (legacy + ESEM-contracted + private) × Firm_Gen_CF + other − demand | B26: TWh | C26: =C15+C24+(C18+C44+C50)*Firm_Gen_CF*8.76-C9 -> -3.03486 | D26: =D15+D24+(D18+D44+D50)*Firm_Gen_CF*8.76-D9 -> -6.900227 | E26: =E15+E24+(E18+E44+E50)*Firm_Gen_CF*8.76-E9 -> 0.33903056 | F26: =F15+F24+(F18+F44+F50)*Firm_Gen_CF*8.76-F9 -> 0.28347605 | G26: =G15+G24+(G18+G44+G50)*Firm_Gen_CF*8.76-G9 -> -6.0894642 | H26: =H15+H24+(H18+H44+H50)*Firm_Gen_CF*8.76-H9 -> -5.751447 | I26: =I15+I24+(I18+I44+I50)*Firm_Gen_CF*8.76-I9 -> -6.3337635 | J26: =J15+J24+(J18+J44+J50)*Firm_Gen_CF*8.76-J9 -> -6.1680261 | ... AB26: =AB15+AB24+(AB18+AB44+AB50)*Firm_Gen_CF*8.76-AB9 -> 6.8551743
A27: Average wholesale spot price | B27: $/MWh | C27: =C22 -> 112.22814 | D27: =D22*EXP(IF(C26>=0,-Surp_Elas,Def_Elas)*ABS(C26/C9)) -> 114.62601 | E27: =E22*EXP(IF(D26>=0,-Surp_Elas,Def_Elas)*ABS(D26/D9)) -> 122.37264 | F27: =F22*EXP(IF(E26>=0,-Surp_Elas,Def_Elas)*ABS(E26/E9)) -> 97.17274 | G27: =G22*EXP(IF(F26>=0,-Surp_Elas,Def_Elas)*ABS(F26/F9)) -> 94.58335 | H27: =H22*EXP(IF(G26>=0,-Surp_Elas,Def_Elas)*ABS(G26/G9)) -> 107.06493 | I27: =I22*EXP(IF(H26>=0,-Surp_Elas,Def_Elas)*ABS(H26/H9)) -> 102.31941 | J27: =J22*EXP(IF(I26>=0,-Surp_Elas,Def_Elas)*ABS(I26/I9)) -> 100.99121 | K27: =K22*EXP(IF(J26>=0,-Surp_Elas,Def_Elas)*ABS(J26/J9)) -> 97.852878 | ... AB27: =AB22*EXP(IF(AA26>=0,-Surp_Elas,Def_Elas)*ABS(AA26/AA9)) -> 74.212876 | AC27: =AVERAGE(C27:AB27) -> 92.877016
A28: VRE curtailment fraction | B28: — | C28: =0 -> 0 | D28: =MAX(0,(C36-Curtail_Thresh)*Curtail_Rate) -> 0.00959585 | E28: =MAX(0,(D36-Curtail_Thresh)*Curtail_Rate) -> 0.0095311057 | F28: =MAX(0,(E36-Curtail_Thresh)*Curtail_Rate) -> 0.018311267 | G28: =MAX(0,(F36-Curtail_Thresh)*Curtail_Rate) -> 0.021052602 | H28: =MAX(0,(G36-Curtail_Thresh)*Curtail_Rate) -> 0.018920643 | I28: =MAX(0,(H36-Curtail_Thresh)*Curtail_Rate) -> 0.021794707 | J28: =MAX(0,(I36-Curtail_Thresh)*Curtail_Rate) -> 0.023790995 | K28: =MAX(0,(J36-Curtail_Thresh)*Curtail_Rate) -> 0.026324399 | ... AB28: =MAX(0,(AA36-Curtail_Thresh)*Curtail_Rate) -> 0.074789069
A29: Forward price (logistic-weighted LRMC and spot) | B29: $/MWh | C29: =(1/(1+EXP(-Fwd_k*(C26/C9))))*C22+(1-(1/(1+EXP(-Fwd_k*(C26/C9)))))*C27 -> 112.22814 | D29: =(1/(1+EXP(-Fwd_k*(C26/C9))))*D22+(1-(1/(1+EXP(-Fwd_k*(C26/C9)))))*D27 -> 110.10963 | E29: =(1/(1+EXP(-Fwd_k*(D26/D9))))*E22+(1-(1/(1+EXP(-Fwd_k*(D26/D9)))))*E27 -> 112.52185 | F29: =(1/(1+EXP(-Fwd_k*(E26/E9))))*F22+(1-(1/(1+EXP(-Fwd_k*(E26/E9)))))*F27 -> 97.523344 | G29: =(1/(1+EXP(-Fwd_k*(F26/F9))))*G22+(1-(1/(1+EXP(-Fwd_k*(F26/F9)))))*G27 -> 94.861411 | H29: =(1/(1+EXP(-Fwd_k*(G26/G9))))*H22+(1-(1/(1+EXP(-Fwd_k*(G26/G9)))))*H27 -> 99.808508 | I29: =(1/(1+EXP(-Fwd_k*(H26/H9))))*I22+(1-(1/(1+EXP(-Fwd_k*(H26/H9)))))*I27 -> 95.867408 | J29: =(1/(1+EXP(-Fwd_k*(I26/I9))))*J22+(1-(1/(1+EXP(-Fwd_k*(I26/I9)))))*J27 -> 94.206566 | K29: =(1/(1+EXP(-Fwd_k*(J26/J9))))*K22+(1-(1/(1+EXP(-Fwd_k*(J26/J9)))))*K27 -> 91.569231 | ... AB29: =(1/(1+EXP(-Fwd_k*(AA26/AA9))))*AB22+(1-(1/(1+EXP(-Fwd_k*(AA26/AA9)))))*AB27 -> 76.570744
A30: Firming balance | B30: GW | C30: =C16+C19+C44*Firm_CFp+C23*VRE_ELCC+Other_Firm-C11 -> 3.5348715 | D30: =D16+D19+C44*Firm_CFp+C50*Firm_CFp+D23*VRE_ELCC+Other_Firm-D11 -> 2.677142 | E30: =E16+E19+D44*Firm_CFp+D50*Firm_CFp+E23*VRE_ELCC+Other_Firm-E11 -> 2.2308697 | F30: =F16+F19+E44*Firm_CFp+E50*Firm_CFp+F23*VRE_ELCC+Other_Firm-F11 -> 1.5189257 | G30: =G16+G19+F44*Firm_CFp+F50*Firm_CFp+G23*VRE_ELCC+Other_Firm-G11 -> 0.51832723 | H30: =H16+H19+G44*Firm_CFp+G50*Firm_CFp+H23*VRE_ELCC+Other_Firm-H11 -> -0.23979125 | I30: =I16+I19+H44*Firm_CFp+H50*Firm_CFp+I23*VRE_ELCC+Other_Firm-I11 -> -0.8325328 | J30: =J16+J19+I44*Firm_CFp+I50*Firm_CFp+J23*VRE_ELCC+Other_Firm-J11 -> -1.0954343 | K30: =K16+K19+J44*Firm_CFp+J50*Firm_CFp+K23*VRE_ELCC+Other_Firm-K11 -> -1.6284744 | ... AB30: =AB16+AB19+AA44*Firm_CFp+AA50*Firm_CFp+AB23*VRE_ELCC+Other_Firm-AB11 -> -3.0299645
A31: Firming deficit fraction | B31: — | C31: =MAX(0,-C30/C11) -> 0 | D31: =MAX(0,-D30/D11) -> 0 | E31: =MAX(0,-E30/E11) -> 0 | F31: =MAX(0,-F30/F11) -> 0 | G31: =MAX(0,-G30/G11) -> 0 | H31: =MAX(0,-H30/H11) -> 0.0060329535 | I31: =MAX(0,-I30/I11) -> 0.020535147 | J31: =MAX(0,-J30/J11) -> 0.026490041 | ... AB31: =MAX(0,-AB30/AB11) -> 0.051301581
A32: Scarcity price | B32: $/MWh | C32: =Firm_SRMC*EXP(Firm_Tight*C31) -> 180 | D32: =Firm_SRMC*EXP(Firm_Tight*D31) -> 180 | E32: =Firm_SRMC*EXP(Firm_Tight*E31) -> 180 | F32: =Firm_SRMC*EXP(Firm_Tight*F31) -> 180 | G32: =Firm_SRMC*EXP(Firm_Tight*G31) -> 180 | H32: =Firm_SRMC*EXP(Firm_Tight*H31) -> 183.84117 | I32: =Firm_SRMC*EXP(Firm_Tight*I31) -> 193.4134 | J32: =Firm_SRMC*EXP(Firm_Tight*J31) -> 197.48685 | ... AB32: =Firm_SRMC*EXP(Firm_Tight*AB31) -> 215.40336
A33: MARKET ENTRY
A34: VRE target share of demand (linear ramp to y26) | B34: — | C34: =VRE_Share0+(VRE_ShareT-VRE_Share0)/25*C2 -> 0.383834 | D34: =VRE_Share0+(VRE_ShareT-VRE_Share0)/25*D2 -> 0.40848064 | E34: =VRE_Share0+(VRE_ShareT-VRE_Share0)/25*E2 -> 0.43312728 | F34: =VRE_Share0+(VRE_ShareT-VRE_Share0)/25*F2 -> 0.45777392 | G34: =VRE_Share0+(VRE_ShareT-VRE_Share0)/25*G2 -> 0.48242056 | H34: =VRE_Share0+(VRE_ShareT-VRE_Share0)/25*H2 -> 0.5070672 | I34: =VRE_Share0+(VRE_ShareT-VRE_Share0)/25*I2 -> 0.53171384 | J34: =VRE_Share0+(VRE_ShareT-VRE_Share0)/25*J2 -> 0.55636048 | ... AB34: =VRE_Share0+(VRE_ShareT-VRE_Share0)/25*AB2 -> 1
A35: VRE target capacity (curtailment-adjusted) | B35: GW | C35: =C34*C9/(VRE_CFe*8.76*MAX(1-C28,0.01)) -> 30 | D35: =D34*D9/(VRE_CFe*8.76*MAX(1-D28,0.01)) -> 33.041572 | E35: =E34*E9/(VRE_CFe*8.76*MAX(1-E28,0.01)) -> 35.908746 | F35: =F34*F9/(VRE_CFe*8.76*MAX(1-F28,0.01)) -> 39.248824 | G35: =G34*G9/(VRE_CFe*8.76*MAX(1-G28,0.01)) -> 42.514759 | H35: =H34*H9/(VRE_CFe*8.76*MAX(1-H28,0.01)) -> 45.704454 | I35: =I34*I9/(VRE_CFe*8.76*MAX(1-I28,0.01)) -> 49.268457 | J35: =J34*J9/(VRE_CFe*8.76*MAX(1-J28,0.01)) -> 52.94907 | ... AB35: =AB34*AB9/(VRE_CFe*8.76*MAX(1-AB28,0.01)) -> 156.61512
A36: Current VRE share of demand | B36: — | C36: =C24/C9 -> 0.44780633 | D36: =IF(D9>0,D24/D9,0) -> 0.4473747 | E36: =IF(E9>0,E24/E9,0) -> 0.50590912 | F36: =IF(F9>0,F24/F9,0) -> 0.52418468 | G36: =IF(G9>0,G24/G9,0) -> 0.50997162 | H36: =IF(H9>0,H24/H9,0) -> 0.52913205 | I36: =IF(I9>0,I24/I9,0) -> 0.54244063 | J36: =IF(J9>0,J24/J9,0) -> 0.55932999 | K36: =IF(K9>0,K24/K9,0) -> 0.57883765 | ... AB36: =IF(AB9>0,AB24/AB9,0) -> 0.89701311
A37: Private VRE build — linear supply curve | B37: GW/yr | C37: 2 | D37: =MAX(0,(D29-D22)/VRE_Sprd) -> 1.1876725 | E37: =MAX(0,(E29-E22)/VRE_Sprd) -> 2.755107 | F37: =MAX(0,(F29-F22)/VRE_Sprd) -> 0 | G37: =MAX(0,(G29-G22)/VRE_Sprd) -> 0 | H37: =MAX(0,(H29-H22)/VRE_Sprd) -> 1.9888128 | I37: =MAX(0,(I29-I22)/VRE_Sprd) -> 1.7556157 | J37: =MAX(0,(J29-J22)/VRE_Sprd) -> 1.8578004 | K37: =MAX(0,(K29-K22)/VRE_Sprd) -> 1.7128157 | ... AB37: =MAX(0,(AB29-AB22)/VRE_Sprd) -> 0
A38: ESEM VRE contracted | B38: GW/yr | C38: =IF(ESEM_On*(C2>=ESEM_Start),MAX(0,(C35-B23)),0) -> 0 | D38: =IF(ESEM_On*(D2>=ESEM_Start),MAX(0,(D35-C23)),0) -> 0 | E38: =IF(ESEM_On*(E2>=ESEM_Start),MAX(0,(E35-D23)),0) -> 0 | F38: =IF(ESEM_On*(F2>=ESEM_Start),MAX(0,(F35-E23-(E43-C43))*RE_Cov),0) -> 0 | G38: =IF(ESEM_On*(G2>=ESEM_Start),MIN(MAX(0,(G35-F23-(F43-D43))), ESEM_Build_Cap),0) -> 0 | H38: =IF(ESEM_On*(H2>=ESEM_Start),MIN(MAX(0,(H35-G23-(G43-E43))), ESEM_Build_Cap),0) -> 0.76167405 | I38: =IF(ESEM_On*(I2>=ESEM_Start),MIN(MAX(0,(I35-H23-(H43-F43))), ESEM_Build_Cap),0) -> 0.81351661 | J38: =IF(ESEM_On*(J2>=ESEM_Start),MIN(MAX(0,(J35-I23-(I43-G43))), ESEM_Build_Cap),0) -> 1.1114804 | K38: =IF(ESEM_On*(K2>=ESEM_Start),MIN(MAX(0,(K35-J23-(J43-H43))), ESEM_Build_Cap),0) -> 1.6678602 | L38: =IF(ESEM_On*(L2>=ESEM_Start),MIN(MAX(0,(L35-K23-(K43-I43))), ESEM_Build_Cap),0) -> 1.5072626 | M38: =IF(ESEM_On*(M2>=ESEM_Start),MIN(MAX(0,(M35-L23-(L43-J43))), ESEM_Build_Cap),0) -> 2.3762458 | N38: =IF(ESEM_On*(N2>=ESEM_Start),MIN(MAX(0,(N35-M23-(M43-K43))), ESEM_Build_Cap),0) -> 2.1141849 | ... AB38: =IF(ESEM_On*(AB2>=ESEM_Start),MIN(MAX(0,(AB35-AA23-(AA43-Y43))), ESEM_Build_Cap),0) -> 6
A39: Firming shortfall | B39: GW | C39: =MAX(0,C11-(C16+C19+C23*VRE_ELCC+Other_Firm)) -> 0 | D39: =MAX(0,D11-(D16+D19+C44*Firm_CFp+C50*Firm_CFp+D23*VRE_ELCC+Other_Firm)) -> 0 | E39: =MAX(0,E11-(E16+E19+D44*Firm_CFp+D50*Firm_CFp+E23*VRE_ELCC+Other_Firm)) -> 0 | F39: =MAX(0,F11-(F16+F19+E44*Firm_CFp+E50*Firm_CFp+F23*VRE_ELCC+Other_Firm)) -> 0 | G39: =MAX(0,G11-(G16+G19+F44*Firm_CFp+F50*Firm_CFp+G23*VRE_ELCC+Other_Firm)) -> 0 | H39: =MAX(0,H11-(H16+H19+G44*Firm_CFp+G50*Firm_CFp+H23*VRE_ELCC+Other_Firm)) -> 0.23979125 | I39: =MAX(0,I11-(I16+I19+H44*Firm_CFp+H50*Firm_CFp+I23*VRE_ELCC+Other_Firm)) -> 0.8325328 | J39: =MAX(0,J11-(J16+J19+I44*Firm_CFp+I50*Firm_CFp+J23*VRE_ELCC+Other_Firm)) -> 1.0954343 | K39: =MAX(0,K11-(K16+K19+J44*Firm_CFp+J50*Firm_CFp+K23*VRE_ELCC+Other_Firm)) -> 1.6284744 | ... AB39: =MAX(0,AB11-(AB16+AB19+AA44*Firm_CFp+AA50*Firm_CFp+AB23*VRE_ELCC+Other_Firm)) -> 3.0299645
A40: Private VRE cumulative stock | B40: GW | C40: =C37 -> 2 | D40: =C40*(1-VRE_Dep)+D37 -> 3.1876725 | E40: =D40*(1-VRE_Dep)+E37 -> 5.9427795 | F40: =E40*(1-VRE_Dep)+F37 -> 5.9427795 | G40: =F40*(1-VRE_Dep)+G37 -> 5.9427795 | H40: =G40*(1-VRE_Dep)+H37 -> 7.9315923 | I40: =H40*(1-VRE_Dep)+I37 -> 9.687208 | J40: =I40*(1-VRE_Dep)+J37 -> 11.545008 | K40: =J40*(1-VRE_Dep)+K37 -> 13.257824 | ... AB40: =AA40*(1-VRE_Dep)+AB37 -> 28.450731
A41: ESEM firming contracted | B41: GW/yr | C41: =IF(ESEM_On*(C2>=ESEM_Start),MAX(0,C39*Firm_Cov),0) -> 0 | D41: =IF(ESEM_On*(D2>=ESEM_Start),MAX(0,D39*Firm_Cov),0) -> 0 | E41: =IF(ESEM_On*(E2>=ESEM_Start),MAX(0,E39*Firm_Cov),0) -> 0 | F41: =IF(ESEM_On*(F2>=ESEM_Start),MAX(0,(F39-(E44-C44))*Firm_Cov),0) -> 0 | G41: =IF(ESEM_On*(G2>=ESEM_Start),MAX(0,(G39-(F44-D44))*Firm_Cov),0) -> 0 | H41: =IF(ESEM_On*(H2>=ESEM_Start),MAX(0,(H39-(G44-E44))*Firm_Cov),0) -> 0.21581213 | I41: =IF(ESEM_On*(I2>=ESEM_Start),MAX(0,(I39-(H44-F44))*Firm_Cov),0) -> 0.55504861 | J41: =IF(ESEM_On*(J2>=ESEM_Start),MAX(0,(J39-(I44-G44))*Firm_Cov),0) -> 0.29211621 | K41: =IF(ESEM_On*(K2>=ESEM_Start),MAX(0,(K39-(J44-H44))*Firm_Cov),0) -> 0.70317861 | L41: =IF(ESEM_On*(L2>=ESEM_Start),MAX(0,(L39-(K44-I44))*Firm_Cov),0) -> 0.88977911 | M41: =IF(ESEM_On*(M2>=ESEM_Start),MAX(0,(M39-(L44-J44))*Firm_Cov),0) -> 0.47874248 | ... AB41: =IF(ESEM_On*(AB2>=ESEM_Start),MAX(0,(AB39-(AA44-Y44))*Firm_Cov),0) -> 1.247414
A42: CUMULATIVE STOCKS
A43: ESEM VRE cumulative stock | B43: GW | C43: =0 -> 0 | D43: =C43*(1-VRE_Dep)+D38 -> 0 | E43: =D43*(1-VRE_Dep)+E38 -> 0 | F43: =E43*(1-VRE_Dep)+F38 -> 0 | G43: =F43*(1-VRE_Dep)+G38 -> 0 | H43: =G43*(1-VRE_Dep)+H38 -> 0.76167405 | I43: =H43*(1-VRE_Dep)+I38 -> 1.5751907 | J43: =I43*(1-VRE_Dep)+J38 -> 2.686671 | K43: =J43*(1-VRE_Dep)+K38 -> 4.3545312 | ... AB43: =AA43*(1-VRE_Dep)+AB38 -> 73.035086
A44: ESEM firming cumulative stock | B44: GW | C44: =0 -> 0 | D44: =C44+D41 -> 0 | E44: =D44+E41 -> 0 | F44: =E44+F41 -> 0 | G44: =F44+G41 -> 0 | H44: =G44+H41 -> 0.21581213 | I44: =H44+I41 -> 0.77086074 | J44: =I44+J41 -> 1.062977 | K44: =J44+K41 -> 1.7661556 | ... AB44: =AA44+AB41 -> 18.623218
A45: ESEM COST RECOVERY
A46: VRE settled stock (held by ESEMA pending offtake sale) | B46: GW | C46: =0 -> 0 | D46: =MAX(0,C46*(1-Divest_Rate)) -> 0 | E46: =MAX(0,D46*(1-Divest_Rate)) -> 0 | F46: =MAX(0,E46*(1-Divest_Rate)+IF(ESEM_On=1,C38,0)) -> 0 | G46: =MAX(0,F46*(1-Divest_Rate)+IF(ESEM_On=1,D38,0)) -> 0 | H46: =MAX(0,G46*(1-Divest_Rate)+IF(ESEM_On=1,E38,0)) -> 0 | I46: =MAX(0,H46*(1-Divest_Rate)+IF(ESEM_On=1,F38,0)) -> 0 | J46: =MAX(0,I46*(1-Divest_Rate)+IF(ESEM_On=1,G38,0)) -> 0 | K46: =MAX(0,J46*(1-Divest_Rate)+IF(ESEM_On=1,H38,0)) -> 0.76167405 | L46: =MAX(0,K46*(1-Divest_Rate)+IF(ESEM_On=1,I38,0)) -> 1.5166004 | M46: =MAX(0,L46*(1-Divest_Rate)+IF(ESEM_On=1,J38,0)) -> 2.5114192 | ... AB46: =MAX(0,AA46*(1-Divest_Rate)+IF(ESEM_On=1,Y38,0)) -> 36.423594
A47: VRE strike accumulator ($/MWh·GW) — GW × LRMC × (1 + Markup_Base + Markup_Rate × GW_contracted) | B47: $/MWh·GW | C47: =0 -> 0 | D47: =MAX(0,C47*(1-Divest_Rate)) -> 0 | E47: =MAX(0,D47*(1-Divest_Rate)) -> 0 | F47: =MAX(0,E47*(1-Divest_Rate)+IF(ESEM_On=1,C38*C22*(1+Markup_Base+Markup_Rate*C38),0)) -> 0 | G47: =MAX(0,F47*(1-Divest_Rate)+IF(ESEM_On=1,D38*D22*(1+Markup_Base+Markup_Rate*D38),0)) -> 0 | H47: =MAX(0,G47*(1-Divest_Rate)+IF(ESEM_On=1,E38*E22*(1+Markup_Base+Markup_Rate*E38),0)) -> 0 | I47: =MAX(0,H47*(1-Divest_Rate)+IF(ESEM_On=1,F38*F22*(1+Markup_Base+Markup_Rate*F38),0)) -> 0 | J47: =MAX(0,I47*(1-Divest_Rate)+IF(ESEM_On=1,G38*G22*(1+Markup_Base+Markup_Rate*G38),0)) -> 0 | K47: =MAX(0,J47*(1-Divest_Rate)+IF(ESEM_On=1,H38*H22*(1+Markup_Base+Markup_Rate*H38),0)) -> 71.727633 | L47: =MAX(0,K47*(1-Divest_Rate)+IF(ESEM_On=1,I38*I22*(1+Markup_Base+Markup_Rate*I38),0)) -> 140.3857 | M47: =MAX(0,L47*(1-Divest_Rate)+IF(ESEM_On=1,J38*J22*(1+Markup_Base+Markup_Rate*J38),0)) -> 229.14443 | ... AB47: =MAX(0,AA47*(1-Divest_Rate)+IF(ESEM_On=1,Y38*Y22*(1+Markup_Base+Markup_Rate*Y38),0)) -> 3175.4358
A48: VRE blended strike ($/MWh) (weighted LRMC at contracting) | B48: $/MWh | C48: =IF(C46>0,C47/C46,C22) -> 112.22814 | D48: =IF(D46>0,D47/D46,D22) -> 105.35894 | E48: =IF(E46>0,E47/E46,E22) -> 101.50142 | F48: =IF(F46>0,F47/F46,F22) -> 97.872068 | G48: =IF(G46>0,G47/G46,G22) -> 95.138254 | H48: =IF(H46>0,H47/H46,H22) -> 91.853257 | I48: =IF(I46>0,I47/I46,I22) -> 88.844946 | J48: =IF(J46>0,J47/J46,J22) -> 86.775365 | ... AB48: =IF(AB46>0,AB47/AB46,AB22) -> 87.180738
A49: Private firm build — enters when scarcity price > time-varying Firm_LRMC + Firm_Sprd | B49: GW/yr | C49: =MAX(0,(C32-IFERROR('Building assets'!B92,Firm_LRMC))/Firm_Sprd) -> 0 | D49: =MAX(0,(D32-IFERROR('Building assets'!C92,Firm_LRMC))/Firm_Sprd) -> 0 | E49: =MAX(0,(E32-IFERROR('Building assets'!D92,Firm_LRMC))/Firm_Sprd) -> 0 | F49: =MAX(0,(F32-IFERROR('Building assets'!E92,Firm_LRMC))/Firm_Sprd) -> 0 | G49: =MAX(0,(G32-IFERROR('Building assets'!F92,Firm_LRMC))/Firm_Sprd) -> 0 | H49: =MAX(0,(H32-IFERROR('Building assets'!G92,Firm_LRMC))/Firm_Sprd) -> 0 | I49: =MAX(0,(I32-IFERROR('Building assets'!H92,Firm_LRMC))/Firm_Sprd) -> 0 | J49: =MAX(0,(J32-IFERROR('Building assets'!I92,Firm_LRMC))/Firm_Sprd) -> 0 | ... AB49: =MAX(0,(AB32-IFERROR('Building assets'!AA92,Firm_LRMC))/Firm_Sprd) -> 0.13541716
A50: Private firm cumulative stock | B50: GW | C50: =0 -> 0 | D50: =C50*(1-Firm_Decay)+D49 -> 0 | E50: =D50*(1-Firm_Decay)+E49 -> 0 | F50: =E50*(1-Firm_Decay)+F49 -> 0 | G50: =F50*(1-Firm_Decay)+G49 -> 0 | H50: =G50*(1-Firm_Decay)+H49 -> 0 | I50: =H50*(1-Firm_Decay)+I49 -> 0 | J50: =I50*(1-Firm_Decay)+J49 -> 0 | K50: =J50*(1-Firm_Decay)+K49 -> 0 | ... AB50: =AA50*(1-Firm_Decay)+AB49 -> 4.0081987
A51: Firm settled stock (online, held by ESEMA pending offtake sale) | B51: GW | C51: =0 -> 0 | D51: =MAX(0,C51*(1-Divest_Rate)) -> 0 | E51: =MAX(0,D51*(1-Divest_Rate)) -> 0 | F51: =MAX(0,E51*(1-Divest_Rate)+IF(ESEM_On=1,C41,0)) -> 0 | G51: =MAX(0,F51*(1-Divest_Rate)+IF(ESEM_On=1,D41,0)) -> 0 | H51: =MAX(0,G51*(1-Divest_Rate)+IF(ESEM_On=1,E41,0)) -> 0 | I51: =MAX(0,H51*(1-Divest_Rate)+IF(ESEM_On=1,F41,0)) -> 0 | J51: =MAX(0,I51*(1-Divest_Rate)+IF(ESEM_On=1,G41,0)) -> 0 | K51: =MAX(0,J51*(1-Divest_Rate)+IF(ESEM_On=1,H41,0)) -> 0.21581213 | L51: =MAX(0,K51*(1-Divest_Rate)+IF(ESEM_On=1,I41,0)) -> 0.7542598 | M51: =MAX(0,L51*(1-Divest_Rate)+IF(ESEM_On=1,J41,0)) -> 0.98835603 | ... AB51: =MAX(0,AA51*(1-Divest_Rate)+IF(ESEM_On=1,Y41,0)) -> 9.719398
A52: Firm strike accumulator ($/MWh·GW) — GW × Firm_LRMC × (1 + Markup_Base) | B52: $/MWh·GW | C52: =0 -> 0 | D52: =MAX(0,C52*(1-Divest_Rate)) -> 0 | E52: =MAX(0,D52*(1-Divest_Rate)) -> 0 | F52: =MAX(0,E52*(1-Divest_Rate)+IF(ESEM_On=1,C41*Firm_LRMC*(1+Markup_Base),0)) -> 0 | G52: =MAX(0,F52*(1-Divest_Rate)+IF(ESEM_On=1,D41*Firm_LRMC*(1+Markup_Base),0)) -> 0 | H52: =MAX(0,G52*(1-Divest_Rate)+IF(ESEM_On=1,E41*Firm_LRMC*(1+Markup_Base),0)) -> 0 | I52: =MAX(0,H52*(1-Divest_Rate)+IF(ESEM_On=1,F41*Firm_LRMC*(1+Markup_Base),0)) -> 0 | J52: =MAX(0,I52*(1-Divest_Rate)+IF(ESEM_On=1,G41*Firm_LRMC*(1+Markup_Base),0)) -> 0 | K52: =MAX(0,J52*(1-Divest_Rate)+IF(ESEM_On=1,H41*Firm_LRMC*(1+Markup_Base),0)) -> 54.599366 | L52: =MAX(0,K52*(1-Divest_Rate)+IF(ESEM_On=1,I41*Firm_LRMC*(1+Markup_Base),0)) -> 190.82388 | M52: =MAX(0,L52*(1-Divest_Rate)+IF(ESEM_On=1,J41*Firm_LRMC*(1+Markup_Base),0)) -> 250.04903 | ... AB52: =MAX(0,AA52*(1-Divest_Rate)+IF(ESEM_On=1,Y41*Firm_LRMC*(1+Markup_Base),0)) -> 2458.9581
A53: Firm blended strike (weighted Firm_LRMC at contracting) | B53: $/MWh | C53: =IF(C51>0,C52/C51,Firm_LRMC) -> 250.49 | D53: =IF(D51>0,D52/D51,Firm_LRMC) -> 250.49 | E53: =IF(E51>0,E52/E51,Firm_LRMC) -> 250.49 | F53: =IF(F51>0,F52/F51,Firm_LRMC) -> 250.49 | G53: =IF(G51>0,G52/G51,Firm_LRMC) -> 250.49 | H53: =IF(H51>0,H52/H51,Firm_LRMC) -> 250.49 | I53: =IF(I51>0,I52/I51,Firm_LRMC) -> 250.49 | J53: =IF(J51>0,J52/J51,Firm_LRMC) -> 250.49 | ... AB53: =IF(AB51>0,AB52/AB51,Firm_LRMC) -> 252.9949
A54: ESEM OFFTAKE & BALANCING
A55: VRE GW divested (offtake agreements sold to retailers) | B55: GW/yr | C55: =IF(C2>=Recycle_Lag,Divest_Rate*C46,0) -> 0 | D55: =IF(D2>=Recycle_Lag,Divest_Rate*C46,0) -> 0 | E55: =IF(E2>=Recycle_Lag,Divest_Rate*D46,0) -> 0 | F55: =IF(F2>=Recycle_Lag,Divest_Rate*E46,0) -> 0 | G55: =IF(G2>=Recycle_Lag,Divest_Rate*F46,0) -> 0 | H55: =IF(H2>=Recycle_Lag,Divest_Rate*G46,0) -> 0 | I55: =IF(I2>=Recycle_Lag,Divest_Rate*H46,0) -> 0 | J55: =IF(J2>=Recycle_Lag,Divest_Rate*I46,0) -> 0 | K55: =IF(K2>=Recycle_Lag,Divest_Rate*J46,0) -> 0 | ... AB55: =IF(AB2>=Recycle_Lag,Divest_Rate*AA46,0) -> 2.5809097
A56: VRE offtake revenue | B56: $m | C56: =IF(C2>=Recycle_Lag,(C29-C48)*C55*VRE_CFe*8.76,0) -> 0 | D56: =IF(D2>=Recycle_Lag,(D29-D48)*D55*VRE_CFe*8.76,0) -> 0 | E56: =IF(E2>=Recycle_Lag,(E29-E48)*E55*VRE_CFe*8.76,0) -> 0 | F56: =IF(F2>=Recycle_Lag,(F29-F48)*F55*VRE_CFe*8.76,0) -> 0 | G56: =IF(G2>=Recycle_Lag,(G29-G48)*G55*VRE_CFe*8.76,0) -> 0 | H56: =IF(H2>=Recycle_Lag,(H29-H48)*H55*VRE_CFe*8.76,0) -> 0 | I56: =IF(I2>=Recycle_Lag,(I29-I48)*I55*VRE_CFe*8.76,0) -> 0 | J56: =IF(J2>=Recycle_Lag,(J29-J48)*J55*VRE_CFe*8.76,0) -> 0 | ... AB56: =IF(AB2>=Recycle_Lag,(AB29-AB48)*AB55*VRE_CFe*8.76,0) -> -63.064164
A57: Firm GW divested (offtake agreements sold to retailers) | B57: GW/yr | C57: =IF(C2>=Recycle_Lag,Divest_Rate*C51,0) -> 0 | D57: =IF(D2>=Recycle_Lag,Divest_Rate*C51,0) -> 0 | E57: =IF(E2>=Recycle_Lag,Divest_Rate*D51,0) -> 0 | F57: =IF(F2>=Recycle_Lag,Divest_Rate*E51,0) -> 0 | G57: =IF(G2>=Recycle_Lag,Divest_Rate*F51,0) -> 0 | H57: =IF(H2>=Recycle_Lag,Divest_Rate*G51,0) -> 0 | I57: =IF(I2>=Recycle_Lag,Divest_Rate*H51,0) -> 0 | J57: =IF(J2>=Recycle_Lag,Divest_Rate*I51,0) -> 0 | K57: =IF(K2>=Recycle_Lag,Divest_Rate*J51,0) -> 0 | ... AB57: =IF(AB2>=Recycle_Lag,Divest_Rate*AA51,0) -> 0.65519497
A58: Firm offtake revenue | B58: $m | C58: =IF(C2>=Recycle_Lag,(C29-C53)*C57*Firm_CFp*8.76,0) -> 0 | D58: =IF(D2>=Recycle_Lag,(D29-D53)*D57*Firm_CFp*8.76,0) -> 0 | E58: =IF(E2>=Recycle_Lag,(E29-E53)*E57*Firm_CFp*8.76,0) -> 0 | F58: =IF(F2>=Recycle_Lag,(F29-F53)*F57*Firm_CFp*8.76,0) -> 0 | G58: =IF(G2>=Recycle_Lag,(G29-G53)*G57*Firm_CFp*8.76,0) -> 0 | H58: =IF(H2>=Recycle_Lag,(H29-H53)*H57*Firm_CFp*8.76,0) -> 0 | I58: =IF(I2>=Recycle_Lag,(I29-I53)*I57*Firm_CFp*8.76,0) -> 0 | J58: =IF(J2>=Recycle_Lag,(J29-J53)*J57*Firm_CFp*8.76,0) -> 0 | ... AB58: =IF(AB2>=Recycle_Lag,(AB29-AB53)*AB57*Firm_CFp*8.76,0) -> -911.32903
A59: Admin cost | B59: $m | C59: =Admin_Cost -> -37 | D59: =Admin_Cost -> -37 | E59: =Admin_Cost -> -37 | F59: =Admin_Cost -> -37 | G59: =Admin_Cost -> -37 | H59: =Admin_Cost -> -37 | I59: =Admin_Cost -> -37 | J59: =Admin_Cost -> -37 | ... AB59: =Admin_Cost -> -37
A60: Net annual ESEM P&L — admin + VRE offtake + firm offtake | B60: $m | C60: =IF(ESEM_On*(C2>=ESEM_Start),C59+C56+C58,0) -> 0 | D60: =IF(ESEM_On*(D2>=ESEM_Start),D59+D56+D58,0) -> 0 | E60: =IF(ESEM_On*(E2>=ESEM_Start),E59+E56+E58,0) -> -37 | F60: =IF(ESEM_On*(F2>=ESEM_Start),F59+F56+F58,0) -> -37 | G60: =IF(ESEM_On*(G2>=ESEM_Start),G59+G56+G58,0) -> -37 | H60: =IF(ESEM_On*(H2>=ESEM_Start),H59+H56+H58,0) -> -37 | I60: =IF(ESEM_On*(I2>=ESEM_Start),I59+I56+I58,0) -> -37 | J60: =IF(ESEM_On*(J2>=ESEM_Start),J59+J56+J58,0) -> -37 | ... AB60: =IF(ESEM_On*(AB2>=ESEM_Start),AB59+AB56+AB58,0) -> -1011.3932
A61: Cumulative ESEM P&L | B61: $bn | C61: =0 -> 0 | D61: =C61+D60/1000 -> 0 | E61: =D61+E60/1000 -> -0.037 | F61: =E61+F60/1000 -> -0.074 | G61: =F61+G60/1000 -> -0.111 | H61: =G61+H60/1000 -> -0.148 | I61: =H61+I60/1000 -> -0.185 | J61: =I61+J60/1000 -> -0.222 | K61: =J61+K60/1000 -> -0.259 | ... AB61: =AA61+AB60/1000 -> -9.3351314
A62: ESEM levy | B62: $/MWh | C62: =IF(C9>0,-C60/C9,0) -> 0 | D62: =IF(D9>0,-D60/D9,0) -> 0 | E62: =IF(E9>0,-E60/E9,0) -> 0.19565074 | F62: =IF(F9>0,-F60/F9,0) -> 0.19087877 | G62: =IF(G9>0,-G60/G9,0) -> 0.18622319 | H62: =IF(H9>0,-H60/H9,0) -> 0.18168116 | I62: =IF(I9>0,-I60/I9,0) -> 0.17724991 | J62: =IF(J9>0,-J60/J9,0) -> 0.17292674 | ... AB62: =IF(AB9>0,-AB60/AB9,0) -> 3.0307554
A63: STEP 7 — CONSUMER PRICES
A64: Consumer price — wholesale spot + ESEM levy | B64: $/MWh | C64: =C27+C62 -> 112.22814 | D64: =D27+D62 -> 114.62601 | E64: =E27+E62 -> 122.56829 | F64: =F27+F62 -> 97.363618 | G64: =G27+G62 -> 94.769573 | H64: =H27+H62 -> 107.24661 | I64: =I27+I62 -> 102.49666 | J64: =J27+J62 -> 101.16413 | ... AB64: =AB27+AB62 -> 77.243632
A65: VRE Merchant viability | B65: WS/LRMC | C65: =IF(C22>0,C27/C22,0) -> 1 | D65: =IF(D22>0,D27/D22,0) -> 1.087957 | E65: =IF(E22>0,E27/E22,0) -> 1.2056249 | F65: =IF(F22>0,F27/F22,0) -> 0.99285467 | G65: =IF(G22>0,G27/G22,0) -> 0.99416739 | H65: =IF(H22>0,H27/H22,0) -> 1.1656084 | I65: =IF(I22>0,I27/I22,0) -> 1.1516627 | J65: =IF(J22>0,J27/J22,0) -> 1.1638235 | ... AB65: =IF(AB22>0,AB27/AB22,0) -> 0.9414965
A67: PRIVATE COST ACCUMULATORS
A68: Private VRE cost accumulator ($/MWh·GW) — GW × LRMC at build year. Mirrors ESEM strike accumulator logic; decays at VRE_Dep rate. | C68: =0 -> 0 | D68: =MAX(0,C68*(1-VRE_Dep)+D37*D22) -> 125.13192 | E68: =MAX(0,D68*(1-VRE_Dep)+E37*E22) -> 404.7792 | F68: =MAX(0,E68*(1-VRE_Dep)+F37*F22) -> 404.7792 | G68: =MAX(0,F68*(1-VRE_Dep)+G37*G22) -> 404.7792 | H68: =MAX(0,G68*(1-VRE_Dep)+H37*H22) -> 587.45813 | I68: =MAX(0,H68*(1-VRE_Dep)+I37*I22) -> 743.43571 | J68: =MAX(0,I68*(1-VRE_Dep)+J37*J22) -> 904.64702 | K68: =MAX(0,J68*(1-VRE_Dep)+K37*K22) -> 1049.7533 | ... AB68: =MAX(0,AA68*(1-VRE_Dep)+AB37*AB22) -> 2272.9258
A69: Private VRE blended LRMC ($/MWh) — portfolio-weighted avg LRMC at build year | C69: =IF(C40>0,C68/C40,C22) -> 0 | D69: =IF(D40>0,D68/D40,D22) -> 39.254949 | E69: =IF(E40>0,E68/E40,E22) -> 68.112774 | F69: =IF(F40>0,F68/F40,F22) -> 68.112774 | G69: =IF(G40>0,G68/G40,G22) -> 68.112774 | H69: =IF(H40>0,H68/H40,H22) -> 74.065599 | I69: =IF(I40>0,I68/I40,I22) -> 76.744064 | J69: =IF(J40>0,J68/J40,J22) -> 78.358282 | ... AB69: =IF(AB40>0,AB68/AB40,AB22) -> 79.88989
A70: Private firm cost accumulator ($/MWh·GW) — GW × Firm_LRMC at build year | C70: =0 -> 0 | D70: =MAX(0,C70*(1-Firm_Decay)+D49*IFERROR('Building assets'!C92,Firm_LRMC)) -> 0 | E70: =MAX(0,D70*(1-Firm_Decay)+E49*IFERROR('Building assets'!D92,Firm_LRMC)) -> 0 | F70: =MAX(0,E70*(1-Firm_Decay)+F49*IFERROR('Building assets'!E92,Firm_LRMC)) -> 0 | G70: =MAX(0,F70*(1-Firm_Decay)+G49*IFERROR('Building assets'!F92,Firm_LRMC)) -> 0 | H70: =MAX(0,G70*(1-Firm_Decay)+H49*IFERROR('Building assets'!G92,Firm_LRMC)) -> 0 | I70: =MAX(0,H70*(1-Firm_Decay)+I49*IFERROR('Building assets'!H92,Firm_LRMC)) -> 0 | J70: =MAX(0,I70*(1-Firm_Decay)+J49*IFERROR('Building assets'!I92,Firm_LRMC)) -> 0 | K70: =MAX(0,J70*(1-Firm_Decay)+K49*IFERROR('Building assets'!J92,Firm_LRMC)) -> 0 | ... AB70: =MAX(0,AA70*(1-Firm_Decay)+AB49*IFERROR('Building assets'!AA92,Firm_LRMC)) -> 826.56002
A71: Private firm blended LRMC ($/MWh) — portfolio-weighted avg Firm_LRMC at build year | C71: =IF(C50>0,C70/C50,IFERROR('Building assets'!B92,Firm_LRMC)) -> 250.49 | D71: =IF(D50>0,D70/D50,IFERROR('Building assets'!C92,Firm_LRMC)) -> 245.92055 | E71: =IF(E50>0,E70/E50,IFERROR('Building assets'!D92,Firm_LRMC)) -> 239.60784 | F71: =IF(F50>0,F70/F50,IFERROR('Building assets'!E92,Firm_LRMC)) -> 233.71774 | G71: =IF(G50>0,G70/G50,IFERROR('Building assets'!F92,Firm_LRMC)) -> 228.17101 | H71: =IF(H50>0,H70/H50,IFERROR('Building assets'!G92,Firm_LRMC)) -> 222.99407 | I71: =IF(I50>0,I70/I50,IFERROR('Building assets'!H92,Firm_LRMC)) -> 218.02842 | J71: =IF(J50>0,J70/J50,IFERROR('Building assets'!I92,Firm_LRMC)) -> 213.37974 | ... AB71: =IF(AB50>0,AB70/AB50,IFERROR('Building assets'!AA92,Firm_LRMC)) -> 206.21732
A73: TOTAL SYSTEM COST
A74: Resource cost of supplying electricity — capital, fuel and O&M. Excludes ESEM P&L (transfer, not resource cost) and transmission (not modelled). All in $m/yr. Levelised = total / demand ($/MWh).
A76: Coal fixed O&M ($m/yr) | C76: =IFERROR('Building assets'!B108,0) -> 0 | D76: =IFERROR('Building assets'!C108,0) -> 1.4267 | E76: =IFERROR('Building assets'!D108,0) -> 1.4267 | F76: =IFERROR('Building assets'!E108,0) -> 1.4267 | G76: =IFERROR('Building assets'!F108,0) -> 1.4267 | H76: =IFERROR('Building assets'!G108,0) -> 1.4267 | I76: =IFERROR('Building assets'!H108,0) -> 1.4267 | J76: =IFERROR('Building assets'!I108,0) -> 1.4267 | ... AB76: =IFERROR('Building assets'!AA108,0) -> 0.57317954
A77: Coal fuel + variable cost ($m/yr) | C77: =C15*C13/1000 -> 6.9361049 | D77: =D15*D13/1000 -> 7.0893546 | E77: =E15*E13/1000 -> 7.2465835 | F77: =F15*F13/1000 -> 7.4078851 | G77: =G15*G13/1000 -> 7.5733551 | H77: =H15*H13/1000 -> 7.7430919 | I77: =I15*I13/1000 -> 7.917196 | J77: =J15*J13/1000 -> 8.0957707 | ... AB77: =AB15*AB13/1000 -> 4.4522389
A78: VRE+Storage — ESEM fleet annualised cost ($m/yr) | C78: =C46*C48*VRE_CFe*8.76/1000 -> 0 | D78: =D46*D48*VRE_CFe*8.76/1000 -> 0 | E78: =E46*E48*VRE_CFe*8.76/1000 -> 0 | F78: =F46*F48*VRE_CFe*8.76/1000 -> 0 | G78: =G46*G48*VRE_CFe*8.76/1000 -> 0 | H78: =H46*H48*VRE_CFe*8.76/1000 -> 0 | I78: =I46*I48*VRE_CFe*8.76/1000 -> 0 | J78: =J46*J48*VRE_CFe*8.76/1000 -> 0 | ... AB78: =AB46*AB48*VRE_CFe*8.76/1000 -> 7.3130414
A79: VRE+Storage — private fleet annualised cost ($m/yr) | C79: =C40*C69*VRE_CFe*8.76/1000 -> 0 | D79: =D40*D69*VRE_CFe*8.76/1000 -> 0.28817931 | E79: =E40*E69*VRE_CFe*8.76/1000 -> 0.93220812 | F79: =F40*F69*VRE_CFe*8.76/1000 -> 0.93220812 | G79: =G40*G69*VRE_CFe*8.76/1000 -> 0.93220812 | H79: =H40*H69*VRE_CFe*8.76/1000 -> 1.3529184 | I79: =I40*I69*VRE_CFe*8.76/1000 -> 1.7121354 | J79: =J40*J69*VRE_CFe*8.76/1000 -> 2.0834057 | ... AB79: =AB40*AB69*VRE_CFe*8.76/1000 -> 5.2345572
A80: Firming — ESEM fleet annualised cost ($m/yr) | C80: =C51*C53*Firm_CFe*8.76/1000 -> 0 | D80: =D51*D53*Firm_CFe*8.76/1000 -> 0 | E80: =E51*E53*Firm_CFe*8.76/1000 -> 0 | F80: =F51*F53*Firm_CFe*8.76/1000 -> 0 | G80: =G51*G53*Firm_CFe*8.76/1000 -> 0 | H80: =H51*H53*Firm_CFe*8.76/1000 -> 0 | I80: =I51*I53*Firm_CFe*8.76/1000 -> 0 | J80: =J51*J53*Firm_CFe*8.76/1000 -> 0 | ... AB80: =AB51*AB53*Firm_CFe*8.76/1000 -> 4.738904
A81: Firming — private fleet annualised cost ($m/yr) | C81: =C50*C71*Firm_CFe*8.76/1000 -> 0 | D81: =D50*D71*Firm_CFe*8.76/1000 -> 0 | E81: =E50*E71*Firm_CFe*8.76/1000 -> 0 | F81: =F50*F71*Firm_CFe*8.76/1000 -> 0 | G81: =G50*G71*Firm_CFe*8.76/1000 -> 0 | H81: =H50*H71*Firm_CFe*8.76/1000 -> 0 | I81: =I50*I71*Firm_CFe*8.76/1000 -> 0 | J81: =J50*J71*Firm_CFe*8.76/1000 -> 0 | ... AB81: =AB50*AB71*Firm_CFe*8.76/1000 -> 1.5929465
A82: Gas baseline fuel cost ($m/yr) | C82: =(C18+C44+C50)*Firm_Gen_CF*8.76*Firm_VC/1000 -> 1.15632 | D82: =(D18+D44+D50)*Firm_Gen_CF*8.76*Firm_VC/1000 -> 1.15632 | E82: =(E18+E44+E50)*Firm_Gen_CF*8.76*Firm_VC/1000 -> 1.15632 | F82: =(F18+F44+F50)*Firm_Gen_CF*8.76*Firm_VC/1000 -> 1.15632 | G82: =(G18+G44+G50)*Firm_Gen_CF*8.76*Firm_VC/1000 -> 1.15632 | H82: =(H18+H44+H50)*Firm_Gen_CF*8.76*Firm_VC/1000 -> 1.1676631 | I82: =(I18+I44+I50)*Firm_Gen_CF*8.76*Firm_VC/1000 -> 1.1968364 | J82: =(J18+J44+J50)*Firm_Gen_CF*8.76*Firm_VC/1000 -> 1.2121901 | ... AB82: =(AB18+AB44+AB50)*Firm_Gen_CF*8.76*Firm_VC/1000 -> 2.3458272
A84: ★ Total system cost ($m/yr) | C84: =SUM(C76:C82) -> 8.0924249 | D84: =SUM(D76:D82) -> 9.9605539 | E84: =SUM(E76:E82) -> 10.761812 | F84: =SUM(F76:F82) -> 10.923113 | G84: =SUM(G76:G82) -> 11.088583 | H84: =SUM(H76:H82) -> 11.690373 | I84: =SUM(I76:I82) -> 12.252868 | J84: =SUM(J76:J82) -> 12.818066 | ... AB84: =SUM(AB76:AB82) -> 26.250695
A85: ★ Levelised system cost ($/MWh) | C85: =IF(C9>0,C84*1000/C9,0) -> 44.957916 | D85: =IF(D9>0,D84*1000/D9,0) -> 53.986742 | E85: =IF(E9>0,E84*1000/E9,0) -> 56.906929 | F85: =IF(F9>0,F84*1000/F9,0) -> 56.351092 | G85: =IF(G9>0,G84*1000/G9,0) -> 55.809495 | H85: =IF(H9>0,H84*1000/H9,0) -> 57.403259 | I85: =IF(I9>0,I84*1000/I9,0) -> 58.697831 | J85: =IF(J9>0,J84*1000/J9,0) -> 59.907743 | ... AB85: =IF(AB9>0,AB84*1000/AB9,0) -> 78.663209
A86: Cumulative system cost ($bn) — running sum | C86: =C84/1000 -> 0.0080924249 | D86: =C86+D84/1000 -> 0.018052979 | E86: =D86+E84/1000 -> 0.02881479 | F86: =E86+F84/1000 -> 0.039737904 | G86: =F86+G84/1000 -> 0.050826487 | H86: =G86+H84/1000 -> 0.06251686 | I86: =H86+I84/1000 -> 0.074769728 | J86: =I86+J84/1000 -> 0.087587795 | K86: =J86+K84/1000 -> 0.10119733 | ... AB86: =AA86+AB84/1000 -> 0.45410307

Sheet Dashboard
A1: ESEM Model v2 — Dashboard
A2: Key outputs auto-update when Assumptions change. Press F9 to recalculate.
A4: ACTIVE SCENARIO
A5: Scenario number | C5: =Scenario_Num -> 1 | D5: (edit in Assumptions!C4)
A7: Metric | C7: Yr 5 | D7: Yr 10 | E7: Yr 15 | F7: Yr 20
A8: ENERGY SCALE
A9: Demand (TWh) | C9: =Model!G9 -> 198.68632 | D9: =Model!L9 -> 224.79533 | E9: =Model!Q9 -> 254.33529 | F9: =Model!V9 -> 287.75703
A10: ↳ Baseline | C10: =Baseline!H9 -> 198.68632 | D10: =Baseline!M9 -> 224.79533 | E10: =Baseline!R9 -> 254.33529 | F10: =Baseline!W9 -> 287.75703
A11: Coal capacity (GW) | C11: =Model!G14 -> 22 | D11: =Model!L14 -> 21.610282 | E11: =Model!Q14 -> 18.233308 | F11: =Model!V14 -> 13.487847
A12: ↳ Baseline | C12: =Baseline!H14 -> #REF! | D12: =Baseline!M14 -> #REF! | E12: =Baseline!R14 -> #REF! | F12: =Baseline!W14 -> #REF!
A13: VRE online (GW) | C13: =Model!G23 -> 44.94278 | D13: =Model!L23 -> 59.544498 | E13: =Model!Q23 -> 79.839928 | F13: =Model!V23 -> 105.03199
A14: ↳ Baseline | C14: =Baseline!H23 -> #REF! | D14: =Baseline!M23 -> #REF! | E14: =Baseline!R23 -> #REF! | F14: =Baseline!W23 -> #REF!
A16: PRICES
A17: Wholesale $/MWh | C17: =Model!G27 -> 94.58335 | D17: =Model!L27 -> 94.601062 | E17: =Model!Q27 -> 90.036034 | F17: =Model!V27 -> 83.424686
A18: ↳ Baseline | C18: =Baseline!H27 -> #REF! | D18: =Baseline!M27 -> #REF! | E18: =Baseline!R27 -> #REF! | F18: =Baseline!W27 -> #REF!
A19: Forward price $/MWh | C19: =Model!G29 -> 94.861411 | D19: =Model!L29 -> 89.30866 | E19: =Model!Q29 -> 85.136209 | F19: =Model!V29 -> 81.141392
A20: Scarcity $/MWh | C20: =Model!G32 -> 180 | D20: =Model!L32 -> 211.52699 | E20: =Model!Q32 -> 226.55416 | F20: =Model!V32 -> 230.0998
A21: ↳ Baseline | C21: =Baseline!H32 -> #REF! | D21: =Baseline!M32 -> #REF! | E21: =Baseline!R32 -> #REF! | F21: =Baseline!W32 -> #REF!
A22: Consumer price $/MWh | C22: =Model!G64 -> 94.769573 | D22: =Model!L64 -> 94.862914 | E22: =Model!Q64 -> 91.26644 | F22: =Model!V64 -> 85.657127
A23: ↳ Baseline | C23: =Baseline!H65 -> #REF! | D23: =Baseline!M65 -> #REF! | E23: =Baseline!R65 -> #REF! | F23: =Baseline!W65 -> #REF!
A25: ESEM PROCUREMENT
A26: ESEM VRE contracted GW/yr | C26: =Model!G38 -> 0 | D26: =Model!L38 -> 1.5072626 | E26: =Model!Q38 -> 2.5938954 | F26: =Model!V38 -> 3.852049
A27: ESEM firm contracted GW/yr | C27: =Model!G41 -> 0 | D27: =Model!L41 -> 0.88977911 | E27: =Model!Q41 -> 1.4559603 | F27: =Model!V41 -> 1.9235855
A28: ESEM VRE stock (GW) | C28: =Model!G43 -> 0 | D28: =Model!L43 -> 5.8617938 | E28: =Model!Q43 -> 18.611167 | F28: =Model!V43 -> 38.436361
A29: ESEM firm stock (GW) | C29: =Model!G44 -> 0 | D29: =Model!L44 -> 2.6559347 | E29: =Model!Q44 -> 7.2799743 | F29: =Model!V44 -> 12.490068
A30: Private firm build GW/yr | C30: =Model!G49 -> 0 | D30: =Model!L49 -> 0.088419656 | E30: =Model!Q49 -> 0.34547569 | F30: =Model!V49 -> 0.39312401
A31: ↳ Baseline | C31: =Baseline!H50 -> #REF! | D31: =Baseline!M50 -> #REF! | E31: =Baseline!R50 -> #REF! | F31: =Baseline!W50 -> #REF!
A32: Private firm stock (GW) | C32: =Model!G50 -> 0 | D32: =Model!L50 -> 0.088419656 | E32: =Model!Q50 -> 1.3359686 | F32: =Model!V50 -> 2.7902514
A33: ↳ Baseline | C33: =Baseline!H51 -> #REF! | D33: =Baseline!M51 -> #REF! | E33: =Baseline!R51 -> #REF! | F33: =Baseline!W51 -> #REF!
A35: ESEM FISCAL [−ve = cost, +ve = revenue]
A36: VRE recycled (GW/yr) | C36: =Model!G46 -> 0 | D36: =Model!L46 -> 1.5166004 | E36: =Model!Q46 -> 8.7271076 | F36: =Model!V46 -> 19.290594
A37: VRE recycling P&L ($m) | C37: =Model!G48 -> 95.138254 | D37: =Model!L48 -> 92.566046 | E37: =Model!Q48 -> 87.860836 | F37: =Model!V48 -> 86.388529
A38: Firming CfD P&L ($m) | C38: =Model!G52 -> 0 | D38: =Model!L52 -> 190.82388 | E38: =Model!Q52 -> 924.92482 | F38: =Model!V52 -> 1654.2822
A39: Admin cost ($m) | C39: =Model!G59 -> -37 | D39: =Model!L59 -> -37 | E39: =Model!Q59 -> -37 | F39: =Model!V59 -> -37
A40: Net annual P&L ($m) | C40: =Model!G60 -> -37 | D40: =Model!L60 -> -58.863073 | E40: =Model!Q60 -> -312.93576 | F40: =Model!V60 -> -642.40053
A41: Cumulative P&L ($bn) | C41: =Model!G61 -> -0.111 | D41: =Model!L61 -> -0.31786307 | E41: =Model!Q61 -> -1.3606318 | F41: =Model!V61 -> -4.0272831
A42: Levy ($/MWh) | C42: =Model!G62 -> 0.18622319 | D42: =Model!L62 -> 0.26185184 | E42: =Model!Q62 -> 1.2304064 | F42: =Model!V62 -> 2.2324408
A43: Merchant viability | C43: =Model!G65 -> 0.99416739 | D43: =Model!L65 -> 1.1314679 | E43: =Model!Q65 -> 1.1272648 | F43: =Model!V65 -> 1.0589816
A44: ↳ Baseline | C44: =Baseline!H66 -> 0 | D44: =Baseline!M66 -> 0 | E44: =Baseline!R66 -> 0 | F44: =Baseline!W66 -> 0

Sheet Checks
A1: CHECKS — Balance & Constraint Verification
A2: GREEN = pass (within tolerance). RED = fail. Investigate any fail before using outputs.
A3: Check | B3: Tolerance | D3: Yr 1 | E3: Yr 2 | F3: Yr 3 | G3: Yr 4 | H3: Yr 5 | I3: Yr 6 | J3: Yr 7 | K3: Yr 8 | L3: Yr 9 | M3: Yr 10 | N3: Yr 11 | O3: Yr 12 | P3: Yr 13 | Q3: Yr 14 | R3: Yr 15 | S3: Yr 16 | T3: Yr 17 | U3: Yr 18 | V3: Yr 19 | W3: Yr 20 | X3: Yr 21 | Y3: Yr 22 | Z3: Yr 23 | AA3: Yr 24 | AB3: Yr 25 | AC3: Yr 26
A4: Energy balance: supply minus demand (TWh) [should ≈ 0] | B4: 5 | D4: =D15+D24+Other_Gen-D9 -> #REF! | E4: =E15+E24+Other_Gen-E9 -> #REF! | F4: =F15+F24+Other_Gen-F9 -> #REF! | G4: =G15+G24+Other_Gen-G9 -> #REF! | H4: =H15+H24+Other_Gen-H9 -> #REF! | I4: =I15+I24+Other_Gen-I9 -> #REF! | J4: =J15+J24+Other_Gen-J9 -> #REF! | K4: =K15+K24+Other_Gen-K9 -> #REF! | ... AC4: =AC15+AC24+Other_Gen-AC9 -> #REF!
A5: VRE share of demand [should be 0–1] | B5: 0.01 | D5: =MIN(MAX(0,D36),1)-D36 -> 0 | E5: =MIN(MAX(0,E36),1)-E36 -> 0 | F5: =MIN(MAX(0,F36),1)-F36 -> 0 | G5: =MIN(MAX(0,G36),1)-G36 -> 0 | H5: =MIN(MAX(0,H36),1)-H36 -> 0 | I5: =MIN(MAX(0,I36),1)-I36 -> 0 | J5: =MIN(MAX(0,J36),1)-J36 -> 0 | K5: =MIN(MAX(0,K36),1)-K36 -> 0 | ... AC5: =MIN(MAX(0,AC36),1)-AC36 -> 0
A6: Battery weight sum (must = 1) | B6: 0.001 | D6: =Batt_w1h+Batt_w2h+Batt_w4h+Batt_w8h-1 -> 0
A7: Levy consistency: levy×demand minus net cost ($m) [should ≈ 0] | B7: 1 | D7: =D63*D9-D61 -> 0 | E7: =E63*E9-E61 -> 0 | F7: =F63*F9-F61 -> 0 | G7: =G63*G9-G61 -> 0 | H7: =H63*H9-H61 -> 0 | I7: =I63*I9-I61 -> 0 | J7: =J63*J9-J61 -> 0 | K7: =K63*K9-K61 -> 0 | ... AC7: =AC63*AC9-AC61 -> 0
A8: LRMC must be positive ($/MWh) — negative signals BA error | B8: 0 | D8: =MAX(0,-D22) -> 0 | E8: =MAX(0,-E22) -> 0 | F8: =MAX(0,-F22) -> 0 | G8: =MAX(0,-G22) -> 0 | H8: =MAX(0,-H22) -> 0 | I8: =MAX(0,-I22) -> 0 | J8: =MAX(0,-J22) -> 0 | K8: =MAX(0,-K22) -> 0 | ... AC8: =MAX(0,-AC22) -> 0

Sheet Charts
A3: Year | B3: Coal GW | C3: Firm base GW | D3: Exist VRE GW | E3: Priv VRE cum | F3: ESEM VRE cum | G3: ESEM Firm cum | H3: Priv Firm cum | I3: WS_E $/MWh | J3: SC_E $/MWh | K3: Fwd $/MWh | L3: LRMC $/MWh | M3: Consumer_E | N3: Levy $/MWh | O3: NetCost $m | P3: CumCost $bn | Q3: WS/LRMC E | R3: Priv VRE ann | S3: ESEM VRE ann | T3: VRE Online GW | U3: Energy Bal TWh | V3: Settled VRE GW | W3: Settled Firm GW | X3: Firming Bal GW | Y3: WS Baseline | Z3: ESEM VRE ann | AA3: Bline Coal GW | AB3: Bline Firm GW | AC3: Bline PrvVRE GW | AD3: Bline VRE Online | AE3: Bline PrvFirm GW | AF3: Bline Cons Price | AG3: VRE Divest GW | AH3: Firm Divest GW | AI3: Recycle PnL
A4: Yr 1 | B4: =Model!C14 -> 22 | C4: =Model!C18 -> 22 | D4: =VRE_Start -> 30 | E4: =Model!C43 -> 0 | F4: =Model!C45 -> 0 | G4: =Model!#REF! -> #REF! | H4: =Model!C67 -> 0 | I4: =Model!C27 -> 112.22814 | J4: =Model!C32 -> 180 | K4: =Model!C29 -> 112.22814 | L4: =Model!C22 -> 112.22814 | M4: =Model!C61 -> 0 | N4: =Model!C60 -> 0 | O4: =Model!C58 -> 0 | P4: =Model!C59 -> -37 | Q4: =Model!C63 -> 0 | R4: =Model!C34 -> 0.383834 | S4: =Model!C39 -> 0 | T4: =Model!C23 -> 35 | U4: =Model!C26 -> -3.03486 | V4: =Model!C47 -> 0 | W4: =Model!C48 -> 112.22814 | X4: =Model!C30 -> 3.5348715 | Y4: =Baseline!D27 -> 0 | Z4: =Model!C39 -> 0 | AA4: =Baseline!D14 -> 22 | AB4: =Baseline!D18 -> 22 | AC4: =Baseline!D43 -> 0 | AD4: =Baseline!D23 -> 33 | AE4: =Baseline!D68 -> 0 | AF4: =Baseline!D62 -> 0 | AG4: =Model!C51 -> 0 | AH4: =Model!C52 -> 0 | AI4: =Model!C57 -> 0 | AJ4: =Model!C7 -> 0 | AK4: =IF(Model!$C$27>0,Baseline!D27/Model!$C$27*100,100) -> 0 | AL4: =IF(Model!$C$27>0,Baseline!D33/Model!$C$27*100,100) -> 0 | AM4: =Baseline!D14 -> 22 | AN4: =Baseline!D43 -> 0 | AO4: =Baseline!D62 -> 0 | AP4: =Baseline!D15 -> 86.724 | AQ4: =Baseline!D20 -> 42.3984 | AR4: =Baseline!D24 -> 75.999132 | AS4: =IF(Baseline!D22>0,Baseline!D27/Baseline!D22,0) -> 0 | AT4: =Baseline!D18 -> 22 | AU4: =Baseline!D43 -> 0 | AV4: =VRE_Start -> 30 | AW4: =VRE_Start -> 30
A5: Yr 2 | B5: =Model!D14 -> 22 | C5: =Model!D18 -> 22 | D5: =VRE_Start*(1-VRE_Dep)^1 -> 30 | E5: =Model!D43 -> 0 | F5: =Model!D45 -> 0 | G5: =Model!#REF! -> #REF! | H5: =Model!D67 -> 0 | I5: =Model!D27 -> 114.62601 | J5: =Model!D32 -> 180 | K5: =Model!D29 -> 110.10963 | L5: =Model!D22 -> 105.35894 | M5: =Model!D61 -> 0 | N5: =Model!D60 -> 0 | O5: =Model!D58 -> 0 | P5: =Model!D59 -> -37 | Q5: =Model!D63 -> 0 | R5: =Model!D34 -> 0.40848064 | S5: =Model!D39 -> 0 | T5: =Model!D23 -> 36.187673 | U5: =Model!D26 -> -6.900227 | V5: =Model!D47 -> 0 | W5: =Model!D48 -> 105.35894 | X5: =Model!D30 -> 2.677142 | Y5: =Baseline!E27 -> #REF! | Z5: =Model!D39 -> 0 | AA5: =Baseline!E14 -> 18.7 | AB5: =Baseline!E18 -> 22 | AC5: =Baseline!E43 -> 0 | AD5: =Baseline!E23 -> #REF! | AE5: =Baseline!E68 -> 0 | AF5: =Baseline!E62 -> 0 | AG5: =Model!D51 -> 0 | AH5: =Model!D52 -> 0 | AI5: =Model!D57 -> 0 | AJ5: =Model!D7 -> 0 | AK5: =IF(Model!$C$27>0,Baseline!E27/Model!$C$27*100,100) -> #REF! | AL5: =IF(Model!$C$27>0,Baseline!E33/Model!$C$27*100,100) -> 0 | AM5: =Baseline!E14 -> 18.7 | AN5: =Baseline!E43 -> 0 | AO5: =Baseline!E62 -> 0 | AP5: =Baseline!E15 -> 73.7154 | AQ5: =Baseline!E20 -> 42.3984 | AR5: =Baseline!E24 -> #REF! | AS5: =IF(Baseline!E22>0,Baseline!E27/Baseline!E22,0) -> 0 | AT5: =Baseline!E18 -> 22 | AU5: =Baseline!E43 -> 0 | AV5: =VRE_Start -> 30 | AW5: =VRE_Start -> 30
A6: Yr 3 | B6: =Model!E14 -> 22 | C6: =Model!E18 -> 22 | D6: =VRE_Start*(1-VRE_Dep)^2 -> 30 | E6: =Model!E43 -> 0 | F6: =Model!E45 -> 0 | G6: =Model!#REF! -> #REF! | H6: =Model!E67 -> 0 | I6: =Model!E27 -> 122.37264 | J6: =Model!E32 -> 180 | K6: =Model!E29 -> 112.52185 | L6: =Model!E22 -> 101.50142 | M6: =Model!E61 -> -0.037 | N6: =Model!E60 -> -37 | O6: =Model!E58 -> 0 | P6: =Model!E59 -> -37 | Q6: =Model!E63 -> 0 | R6: =Model!E34 -> 0.43312728 | S6: =Model!E39 -> 0 | T6: =Model!E23 -> 41.94278 | U6: =Model!E26 -> 0.33903056 | V6: =Model!E47 -> 0 | W6: =Model!E48 -> 101.50142 | X6: =Model!E30 -> 2.2308697 | Y6: =Baseline!F27 -> #REF! | Z6: =Model!E39 -> 0 | AA6: =Baseline!F14 -> #REF! | AB6: =Baseline!F18 -> 22 | AC6: =Baseline!F43 -> 0 | AD6: =Baseline!F23 -> #REF! | AE6: =Baseline!F68 -> 0 | AF6: =Baseline!F62 -> 0 | AG6: =Model!E51 -> 0 | AH6: =Model!E52 -> 0 | AI6: =Model!E57 -> 0 | AJ6: =Model!E7 -> 0 | AK6: =IF(Model!$C$27>0,Baseline!F27/Model!$C$27*100,100) -> #REF! | AL6: =IF(Model!$C$27>0,Baseline!F33/Model!$C$27*100,100) -> 0 | AM6: =Baseline!F14 -> #REF! | AN6: =Baseline!F43 -> 0 | AO6: =Baseline!F62 -> 0 | AP6: =Baseline!F15 -> #REF! | AQ6: =Baseline!F20 -> 42.3984 | AR6: =Baseline!F24 -> #REF! | AS6: =IF(Baseline!F22>0,Baseline!F27/Baseline!F22,0) -> 0 | AT6: =Baseline!F18 -> 22 | AU6: =Baseline!F43 -> 0 | AV6: =VRE_Start -> 30 | AW6: =VRE_Start -> 30
A7: Yr 4 | B7: =Model!F14 -> 22 | C7: =Model!F18 -> 22 | D7: =VRE_Start*(1-VRE_Dep)^3 -> 30 | E7: =Model!F43 -> 0 | F7: =Model!F45 -> 0 | G7: =Model!#REF! -> #REF! | H7: =Model!F67 -> 0 | I7: =Model!F27 -> 97.17274 | J7: =Model!F32 -> 180 | K7: =Model!F29 -> 97.523344 | L7: =Model!F22 -> 97.872068 | M7: =Model!F61 -> -0.074 | N7: =Model!F60 -> -37 | O7: =Model!F58 -> 0 | P7: =Model!F59 -> -37 | Q7: =Model!F63 -> 0 | R7: =Model!F34 -> 0.45777392 | S7: =Model!F39 -> 0 | T7: =Model!F23 -> 44.94278 | U7: =Model!F26 -> 0.28347605 | V7: =Model!F47 -> 0 | W7: =Model!F48 -> 97.872068 | X7: =Model!F30 -> 1.5189257 | Y7: =Baseline!G27 -> #REF! | Z7: =Model!F39 -> 0 | AA7: =Baseline!G14 -> #REF! | AB7: =Baseline!G18 -> 22 | AC7: =Baseline!G43 -> 0 | AD7: =Baseline!G23 -> #REF! | AE7: =Baseline!G68 -> 0 | AF7: =Baseline!G62 -> 0 | AG7: =Model!F51 -> 0 | AH7: =Model!F52 -> 0 | AI7: =Model!F57 -> 0 | AJ7: =Model!F7 -> 0 | AK7: =IF(Model!$C$27>0,Baseline!G27/Model!$C$27*100,100) -> #REF! | AL7: =IF(Model!$C$27>0,Baseline!G33/Model!$C$27*100,100) -> 0 | AM7: =Baseline!G14 -> #REF! | AN7: =Baseline!G43 -> 0 | AO7: =Baseline!G62 -> 0 | AP7: =Baseline!G15 -> #REF! | AQ7: =Baseline!G20 -> 42.3984 | AR7: =Baseline!G24 -> #REF! | AS7: =IF(Baseline!G22>0,Baseline!G27/Baseline!G22,0) -> 0 | AT7: =Baseline!G18 -> 22 | AU7: =Baseline!G43 -> 0 | AV7: =VRE_Start -> 30 | AW7: =VRE_Start -> 30
A8: Yr 5 | B8: =Model!G14 -> 22 | C8: =Model!G18 -> 22 | D8: =VRE_Start*(1-VRE_Dep)^4 -> 30 | E8: =Model!G43 -> 0 | F8: =Model!G45 -> 0 | G8: =Model!#REF! -> #REF! | H8: =Model!G67 -> 0 | I8: =Model!G27 -> 94.58335 | J8: =Model!G32 -> 180 | K8: =Model!G29 -> 94.861411 | L8: =Model!G22 -> 95.138254 | M8: =Model!G61 -> -0.111 | N8: =Model!G60 -> -37 | O8: =Model!G58 -> 0 | P8: =Model!G59 -> -37 | Q8: =Model!G63 -> 0 | R8: =Model!G34 -> 0.48242056 | S8: =Model!G39 -> 0 | T8: =Model!G23 -> 44.94278 | U8: =Model!G26 -> -6.0894642 | V8: =Model!G47 -> 0 | W8: =Model!G48 -> 95.138254 | X8: =Model!G30 -> 0.51832723 | Y8: =Baseline!H27 -> #REF! | Z8: =Model!G39 -> 0 | AA8: =Baseline!H14 -> #REF! | AB8: =Baseline!H18 -> 22 | AC8: =Baseline!H43 -> 0 | AD8: =Baseline!H23 -> #REF! | AE8: =Baseline!H68 -> 0 | AF8: =Baseline!H62 -> 0 | AG8: =Model!G51 -> 0 | AH8: =Model!G52 -> 0 | AI8: =Model!G57 -> 0 | AJ8: =Model!G7 -> 0 | AK8: =IF(Model!$C$27>0,Baseline!H27/Model!$C$27*100,100) -> #REF! | AL8: =IF(Model!$C$27>0,Baseline!H33/Model!$C$27*100,100) -> 0 | AM8: =Baseline!H14 -> #REF! | AN8: =Baseline!H43 -> 0 | AO8: =Baseline!H62 -> 0 | AP8: =Baseline!H15 -> #REF! | AQ8: =Baseline!H20 -> 42.3984 | AR8: =Baseline!H24 -> #REF! | AS8: =IF(Baseline!H22>0,Baseline!H27/Baseline!H22,0) -> 0 | AT8: =Baseline!H18 -> 22 | AU8: =Baseline!H43 -> 0 | AV8: =VRE_Start -> 30 | AW8: =VRE_Start -> 30
A9: Yr 6 | B9: =Model!H14 -> 22 | C9: =Model!H18 -> 22 | D9: =VRE_Start*(1-VRE_Dep)^5 -> 30 | E9: =Model!H43 -> 0.76167405 | F9: =Model!H45 -> 0 | G9: =Model!#REF! -> #REF! | H9: =Model!H67 -> 0 | I9: =Model!H27 -> 107.06493 | J9: =Model!H32 -> 183.84117 | K9: =Model!H29 -> 99.808508 | L9: =Model!H22 -> 91.853257 | M9: =Model!H61 -> -0.148 | N9: =Model!H60 -> -37 | O9: =Model!H58 -> 0 | P9: =Model!H59 -> -37 | Q9: =Model!H63 -> 0 | R9: =Model!H34 -> 0.5070672 | S9: =Model!H39 -> 0.23979125 | T9: =Model!H23 -> 47.693266 | U9: =Model!H26 -> -5.751447 | V9: =Model!H47 -> 0 | W9: =Model!H48 -> 91.853257 | X9: =Model!H30 -> -0.23979125 | Y9: =Baseline!I27 -> #REF! | Z9: =Model!H39 -> 0.23979125 | AA9: =Baseline!I14 -> #REF! | AB9: =Baseline!I18 -> 22 | AC9: =Baseline!I43 -> 0 | AD9: =Baseline!I23 -> #REF! | AE9: =Baseline!I68 -> 0 | AF9: =Baseline!I62 -> 0 | AG9: =Model!H51 -> 0 | AH9: =Model!H52 -> 0 | AI9: =Model!H57 -> 0 | AJ9: =Model!H7 -> 0 | AK9: =IF(Model!$C$27>0,Baseline!I27/Model!$C$27*100,100) -> #REF! | AL9: =IF(Model!$C$27>0,Baseline!I33/Model!$C$27*100,100) -> 0 | AM9: =Baseline!I14 -> #REF! | AN9: =Baseline!I43 -> 0 | AO9: =Baseline!I62 -> 0 | AP9: =Baseline!I15 -> #REF! | AQ9: =Baseline!I20 -> 42.3984 | AR9: =Baseline!I24 -> #REF! | AS9: =IF(Baseline!I22>0,Baseline!I27/Baseline!I22,0) -> 0 | AT9: =Baseline!I18 -> 22 | AU9: =Baseline!I43 -> 0 | AV9: =VRE_Start -> 30 | AW9: =VRE_Start -> 30
A10: Yr 7 | B10: =Model!I14 -> 22 | C10: =Model!I18 -> 22 | D10: =VRE_Start*(1-VRE_Dep)^6 -> 30 | E10: =Model!I43 -> 1.5751907 | F10: =Model!I45 -> 0 | G10: =Model!#REF! -> #REF! | H10: =Model!I67 -> 0 | I10: =Model!I27 -> 102.31941 | J10: =Model!I32 -> 193.4134 | K10: =Model!I29 -> 95.867408 | L10: =Model!I22 -> 88.844946 | M10: =Model!I61 -> -0.185 | N10: =Model!I60 -> -37 | O10: =Model!I58 -> 0 | P10: =Model!I59 -> -37 | Q10: =Model!I63 -> 0 | R10: =Model!I34 -> 0.53171384 | S10: =Model!I39 -> 0.8325328 | T10: =Model!I23 -> 50.262399 | U10: =Model!I26 -> -6.3337635 | V10: =Model!I47 -> 0 | W10: =Model!I48 -> 88.844946 | X10: =Model!I30 -> -0.8325328 | Y10: =Baseline!J27 -> #REF! | Z10: =Model!I39 -> 0.8325328 | AA10: =Baseline!J14 -> #REF! | AB10: =Baseline!J18 -> 22 | AC10: =Baseline!J43 -> 0 | AD10: =Baseline!J23 -> #REF! | AE10: =Baseline!J68 -> 0 | AF10: =Baseline!J62 -> 0 | AG10: =Model!I51 -> 0 | AH10: =Model!I52 -> 0 | AI10: =Model!I57 -> 0 | AJ10: =Model!I7 -> 0 | AK10: =IF(Model!$C$27>0,Baseline!J27/Model!$C$27*100,100) -> #REF! | AL10: =IF(Model!$C$27>0,Baseline!J33/Model!$C$27*100,100) -> 0 | AM10: =Baseline!J14 -> #REF! | AN10: =Baseline!J43 -> 0 | AO10: =Baseline!J62 -> 0 | AP10: =Baseline!J15 -> #REF! | AQ10: =Baseline!J20 -> 42.3984 | AR10: =Baseline!J24 -> #REF! | AS10: =IF(Baseline!J22>0,Baseline!J27/Baseline!J22,0) -> 0 | AT10: =Baseline!J18 -> 22 | AU10: =Baseline!J43 -> 0 | AV10: =VRE_Start -> 30 | AW10: =VRE_Start -> 30
A11: Yr 8 | B11: =Model!J14 -> 22 | C11: =Model!J18 -> 22 | D11: =VRE_Start*(1-VRE_Dep)^7 -> 30 | E11: =Model!J43 -> 2.686671 | F11: =Model!J45 -> 0 | G11: =Model!#REF! -> #REF! | H11: =Model!J67 -> 0 | I11: =Model!J27 -> 100.99121 | J11: =Model!J32 -> 197.48685 | K11: =Model!J29 -> 94.206566 | L11: =Model!J22 -> 86.775365 | M11: =Model!J61 -> -0.222 | N11: =Model!J60 -> -37 | O11: =Model!J58 -> 0 | P11: =Model!J59 -> -37 | Q11: =Model!J63 -> 0 | R11: =Model!J34 -> 0.55636048 | S11: =Model!J39 -> 1.0954343 | T11: =Model!J23 -> 53.231679 | U11: =Model!J26 -> -6.1680261 | V11: =Model!J47 -> 0 | W11: =Model!J48 -> 86.775365 | X11: =Model!J30 -> -1.0954343 | Y11: =Baseline!K27 -> #REF! | Z11: =Model!J39 -> 1.0954343 | AA11: =Baseline!K14 -> #REF! | AB11: =Baseline!K18 -> 22 | AC11: =Baseline!K43 -> 0 | AD11: =Baseline!K23 -> #REF! | AE11: =Baseline!K68 -> 0 | AF11: =Baseline!K62 -> 0 | AG11: =Model!J51 -> 0 | AH11: =Model!J52 -> 0 | AI11: =Model!J57 -> 0 | AJ11: =Model!J7 -> 0 | AK11: =IF(Model!$C$27>0,Baseline!K27/Model!$C$27*100,100) -> #REF! | AL11: =IF(Model!$C$27>0,Baseline!K33/Model!$C$27*100,100) -> 0 | AM11: =Baseline!K14 -> #REF! | AN11: =Baseline!K43 -> 0 | AO11: =Baseline!K62 -> 0 | AP11: =Baseline!K15 -> #REF! | AQ11: =Baseline!K20 -> 42.3984 | AR11: =Baseline!K24 -> #REF! | AS11: =IF(Baseline!K22>0,Baseline!K27/Baseline!K22,0) -> 0 | AT11: =Baseline!K18 -> 22 | AU11: =Baseline!K43 -> 0 | AV11: =VRE_Start -> 30 | AW11: =VRE_Start -> 30
A12: Yr 9 | B12: =Model!K14 -> 21.91168 | C12: =Model!K18 -> 22 | D12: =VRE_Start*(1-VRE_Dep)^8 -> 30 | E12: =Model!K43 -> 4.3545312 | F12: =Model!K45 -> 0 | G12: =Model!#REF! -> #REF! | H12: =Model!K67 -> 0 | I12: =Model!K27 -> 97.852878 | J12: =Model!K32 -> 206.04298 | K12: =Model!K29 -> 91.569231 | L12: =Model!K22 -> 84.717968 | M12: =Model!K61 -> -0.259 | N12: =Model!K60 -> -37 | O12: =Model!K58 -> 0 | P12: =Model!K59 -> -37 | Q12: =Model!K63 -> 0 | R12: =Model!K34 -> 0.58100712 | S12: =Model!K39 -> 1.6284744 | T12: =Model!K23 -> 56.612355 | U12: =Model!K26 -> -5.4177145 | V12: =Model!K47 -> 71.727633 | W12: =Model!K48 -> 94.171034 | X12: =Model!K30 -> -1.6284744 | Y12: =Baseline!L27 -> #REF! | Z12: =Model!K39 -> 1.6284744 | AA12: =Baseline!L14 -> #REF! | AB12: =Baseline!L18 -> 22 | AC12: =Baseline!L43 -> 0 | AD12: =Baseline!L23 -> #REF! | AE12: =Baseline!L68 -> 0 | AF12: =Baseline!L62 -> 0 | AG12: =Model!K51 -> 0.21581213 | AH12: =Model!K52 -> 54.599366 | AI12: =Model!K57 -> 0 | AJ12: =Model!K7 -> 0 | AK12: =IF(Model!$C$27>0,Baseline!L27/Model!$C$27*100,100) -> #REF! | AL12: =IF(Model!$C$27>0,Baseline!L33/Model!$C$27*100,100) -> 0 | AM12: =Baseline!L14 -> #REF! | AN12: =Baseline!L43 -> 0 | AO12: =Baseline!L62 -> 0 | AP12: =Baseline!L15 -> #REF! | AQ12: =Baseline!L20 -> 42.3984 | AR12: =Baseline!L24 -> #REF! | AS12: =IF(Baseline!L22>0,Baseline!L27/Baseline!L22,0) -> 0 | AT12: =Baseline!L18 -> 22 | AU12: =Baseline!L43 -> 0 | AV12: =VRE_Start -> 30 | AW12: =VRE_Start -> 30
A13: Yr 10 | B13: =Model!L14 -> 21.610282 | C13: =Model!L18 -> 22 | D13: =VRE_Start*(1-VRE_Dep)^9 -> 30 | E13: =Model!L43 -> 5.8617938 | F13: =Model!L45 -> 0 | G13: =Model!#REF! -> #REF! | H13: =Model!L67 -> 0 | I13: =Model!L27 -> 94.601062 | J13: =Model!L32 -> 211.52699 | K13: =Model!L29 -> 89.30866 | L13: =Model!L22 -> 83.609141 | M13: =Model!L61 -> -0.31786307 | N13: =Model!L60 -> -58.863073 | O13: =Model!L58 -> -21.423542 | P13: =Model!L59 -> -37 | Q13: =Model!L63 -> 0 | R13: =Model!L34 -> 0.60565376 | S13: =Model!L39 -> 1.9839383 | T13: =Model!L23 -> 59.544498 | U13: =Model!L26 -> -6.4834609 | V13: =Model!L47 -> 140.3857 | W13: =Model!L48 -> 92.566046 | X13: =Model!L30 -> -1.9839383 | Y13: =Baseline!M27 -> #REF! | Z13: =Model!L39 -> 1.9839383 | AA13: =Baseline!M14 -> #REF! | AB13: =Baseline!M18 -> 22 | AC13: =Baseline!M43 -> 0 | AD13: =Baseline!M23 -> #REF! | AE13: =Baseline!M68 -> 0 | AF13: =Baseline!M62 -> 0 | AG13: =Model!L51 -> 0.7542598 | AH13: =Model!L52 -> 190.82388 | AI13: =Model!L57 -> 0.016600933 | AJ13: =Model!L7 -> 0 | AK13: =IF(Model!$C$27>0,Baseline!M27/Model!$C$27*100,100) -> #REF! | AL13: =IF(Model!$C$27>0,Baseline!M33/Model!$C$27*100,100) -> 0 | AM13: =Baseline!M14 -> #REF! | AN13: =Baseline!M43 -> 0 | AO13: =Baseline!M62 -> 0 | AP13: =Baseline!M15 -> #REF! | AQ13: =Baseline!M20 -> 42.3984 | AR13: =Baseline!M24 -> #REF! | AS13: =IF(Baseline!M22>0,Baseline!M27/Baseline!M22,0) -> 0 | AT13: =Baseline!M18 -> 22 | AU13: =Baseline!M43 -> 0 | AV13: =VRE_Start -> 30 | AW13: =VRE_Start -> 30
A14: Yr 11 | B14: =Model!M14 -> 21.110289 | C14: =Model!M18 -> 22 | D14: =VRE_Start*(1-VRE_Dep)^10 -> 30 | E14: =Model!M43 -> 8.2380396 | F14: =Model!M45 -> 0 | G14: =Model!#REF! -> #REF! | H14: =Model!M67 -> 0 | I14: =Model!M27 -> 95.206972 | J14: =Model!M32 -> 213.24251 | K14: =Model!M29 -> 89.090581 | L14: =Model!M22 -> 82.421399 | M14: =Model!M61 -> -0.43041551 | N14: =Model!M60 -> -112.55244 | O14: =Model!M58 -> -74.974679 | P14: =Model!M59 -> -37 | Q14: =Model!M63 -> 0 | R14: =Model!M34 -> 0.6303004 | S14: =Model!M39 -> 2.1248938 | T14: =Model!M23 -> 63.588039 | U14: =Model!M26 -> -5.8964118 | V14: =Model!M47 -> 229.14443 | W14: =Model!M48 -> 91.241014 | X14: =Model!M30 -> -2.1248938 | Y14: =Baseline!N27 -> #REF! | Z14: =Model!M39 -> 2.1248938 | AA14: =Baseline!N14 -> #REF! | AB14: =Baseline!N18 -> 22 | AC14: =Baseline!N43 -> 0 | AD14: =Baseline!N23 -> #REF! | AE14: =Baseline!N68 -> 0 | AF14: =Baseline!N62 -> 0 | AG14: =Model!M51 -> 0.98835603 | AH14: =Model!M52 -> 250.04903 | AI14: =Model!M57 -> 0.058019985 | AJ14: =Model!M7 -> 0 | AK14: =IF(Model!$C$27>0,Baseline!N27/Model!$C$27*100,100) -> #REF! | AL14: =IF(Model!$C$27>0,Baseline!N33/Model!$C$27*100,100) -> 0 | AM14: =Baseline!N14 -> #REF! | AN14: =Baseline!N43 -> 0 | AO14: =Baseline!N62 -> 0 | AP14: =Baseline!N15 -> #REF! | AQ14: =Baseline!N20 -> 42.3984 | AR14: =Baseline!N24 -> #REF! | AS14: =IF(Baseline!N22>0,Baseline!N27/Baseline!N22,0) -> 0 | AT14: =Baseline!N18 -> 22 | AU14: =Baseline!N43 -> 0 | AV14: =VRE_Start -> 30 | AW14: =VRE_Start -> 30
A15: Yr 12 | B15: =Model!N14 -> 20.539529 | C15: =Model!N18 -> 22 | D15: =VRE_Start*(1-VRE_Dep)^11 -> 30 | E15: =Model!N43 -> 10.352225 | F15: =Model!N45 -> 0 | G15: =Model!#REF! -> #REF! | H15: =Model!N67 -> 0 | I15: =Model!N27 -> 92.758132 | J15: =Model!N32 -> 222.05706 | K15: =Model!N29 -> 87.401523 | L15: =Model!N22 -> 81.617483 | M15: =Model!N61 -> -0.56784985 | N15: =Model!N60 -> -137.43434 | O15: =Model!N58 -> -99.256655 | P15: =Model!N59 -> -37 | Q15: =Model!N63 -> 0 | R15: =Model!N34 -> 0.65494704 | S15: =Model!N39 -> 2.6854013 | T15: =Model!N23 -> 67.148234 | U15: =Model!N26 -> -6.5956585 | V15: =Model!N47 -> 358.94194 | W15: =Model!N48 -> 90.048554 | X15: =Model!N30 -> -2.6854013 | Y15: =Baseline!O27 -> #REF! | Z15: =Model!N39 -> 2.6854013 | AA15: =Baseline!O14 -> #REF! | AB15: =Baseline!O18 -> 22 | AC15: =Baseline!O43 -> 0 | AD15: =Baseline!O23 -> #REF! | AE15: =Baseline!O68 -> 0 | AF15: =Baseline!O62 -> 0 | AG15: =Model!N51 -> 1.6155073 | AH15: =Model!N52 -> 408.71509 | AI15: =Model!N57 -> 0.076027387 | AJ15: =Model!N7 -> 0 | AK15: =IF(Model!$C$27>0,Baseline!O27/Model!$C$27*100,100) -> #REF! | AL15: =IF(Model!$C$27>0,Baseline!O33/Model!$C$27*100,100) -> 0 | AM15: =Baseline!O14 -> #REF! | AN15: =Baseline!O43 -> 0 | AO15: =Baseline!O62 -> 0 | AP15: =Baseline!O15 -> #REF! | AQ15: =Baseline!O20 -> 42.3984 | AR15: =Baseline!O24 -> #REF! | AS15: =IF(Baseline!O22>0,Baseline!O27/Baseline!O22,0) -> 0 | AT15: =Baseline!O18 -> 22 | AU15: =Baseline!O43 -> 0 | AV15: =VRE_Start -> 30 | AW15: =VRE_Start -> 30
A16: Yr 13 | B16: =Model!O14 -> 19.828273 | C16: =Model!O18 -> 22 | D16: =VRE_Start*(1-VRE_Dep)^12 -> 30 | E16: =Model!O43 -> 12.911018 | F16: =Model!O45 -> 0 | G16: =Model!#REF! -> #REF! | H16: =Model!O67 -> 0 | I16: =Model!O27 -> 93.234805 | J16: =Model!O32 -> 218.33939 | K16: =Model!O29 -> 87.413787 | L16: =Model!O22 -> 81.084066 | M16: =Model!O61 -> -0.7683047 | N16: =Model!O60 -> -200.45485 | O16: =Model!O58 -> -162.22694 | P16: =Model!O59 -> -37 | Q16: =Model!O63 -> 0 | R16: =Model!O34 -> 0.67959368 | S16: =Model!O39 -> 2.518865 | T16: =Model!O23 -> 71.289457 | U16: =Model!O26 -> -6.6317803 | V16: =Model!O47 -> 462.41109 | W16: =Model!O48 -> 89.152664 | X16: =Model!O30 -> -2.518865 | Y16: =Baseline!P27 -> #REF! | Z16: =Model!O39 -> 2.518865 | AA16: =Baseline!P14 -> #REF! | AB16: =Baseline!P18 -> 22 | AC16: =Baseline!P43 -> 0 | AD16: =Baseline!P23 -> #REF! | AE16: =Baseline!P68 -> 0 | AF16: =Baseline!P62 -> 0 | AG16: =Model!O51 -> 2.3810166 | AH16: =Model!O52 -> 602.38504 | AI16: =Model!O57 -> 0.12426979 | AJ16: =Model!O7 -> 0 | AK16: =IF(Model!$C$27>0,Baseline!P27/Model!$C$27*100,100) -> #REF! | AL16: =IF(Model!$C$27>0,Baseline!P33/Model!$C$27*100,100) -> 0 | AM16: =Baseline!P14 -> #REF! | AN16: =Baseline!P43 -> 0 | AO16: =Baseline!P62 -> 0 | AP16: =Baseline!P15 -> #REF! | AQ16: =Baseline!P20 -> 42.3984 | AR16: =Baseline!P24 -> #REF! | AS16: =IF(Baseline!P22>0,Baseline!P27/Baseline!P22,0) -> 0 | AT16: =Baseline!P18 -> 22 | AU16: =Baseline!P43 -> 0 | AV16: =VRE_Start -> 30 | AW16: =VRE_Start -> 30
A17: Yr 14 | B17: =Model!P14 -> 19.068269 | C17: =Model!P18 -> 22 | D17: =VRE_Start*(1-VRE_Dep)^13 -> 30 | E17: =Model!P43 -> 16.017271 | F17: =Model!P45 -> 0 | G17: =Model!#REF! -> #REF! | H17: =Model!P67 -> 0 | I17: =Model!P27 -> 92.091816 | J17: =Model!P32 -> 221.67487 | K17: =Model!P29 -> 86.439646 | L17: =Model!P22 -> 80.30333 | M17: =Model!P61 -> -1.047696 | N17: =Model!P60 -> -279.39131 | O17: =Model!P58 -> -240.50494 | P17: =Model!P59 -> -37 | Q17: =Model!P63 -> 0 | R17: =Model!P34 -> 0.70424032 | S17: =Model!P39 -> 2.770971 | T17: =Model!P23 -> 75.92979 | U17: =Model!P26 -> -5.9449535 | V17: =Model!P47 -> 633.96097 | W17: =Model!P48 -> 88.492602 | X17: =Model!P30 -> -2.770971 | Y17: =Baseline!Q27 -> #REF! | Z17: =Model!P39 -> 2.770971 | AA17: =Baseline!Q14 -> #REF! | AB17: =Baseline!Q18 -> 22 | AC17: =Baseline!Q43 -> 0 | AD17: =Baseline!Q23 -> #REF! | AE17: =Baseline!Q68 -> 0 | AF17: =Baseline!Q62 -> 0 | AG17: =Model!P51 -> 2.6766039 | AH17: =Model!P52 -> 677.16713 | AI17: =Model!P57 -> 0.18315512 | AJ17: =Model!P7 -> 0 | AK17: =IF(Model!$C$27>0,Baseline!Q27/Model!$C$27*100,100) -> #REF! | AL17: =IF(Model!$C$27>0,Baseline!Q33/Model!$C$27*100,100) -> 0 | AM17: =Baseline!Q14 -> #REF! | AN17: =Baseline!Q43 -> 0 | AO17: =Baseline!Q62 -> 0 | AP17: =Baseline!Q15 -> #REF! | AQ17: =Baseline!Q20 -> 42.3984 | AR17: =Baseline!Q24 -> #REF! | AS17: =IF(Baseline!Q22>0,Baseline!Q27/Baseline!Q22,0) -> 0 | AT17: =Baseline!Q18 -> 22 | AU17: =Baseline!Q43 -> 0 | AV17: =VRE_Start -> 30 | AW17: =VRE_Start -> 30
A18: Yr 15 | B18: =Model!Q14 -> 18.233308 | C18: =Model!Q18 -> 22 | D18: =VRE_Start*(1-VRE_Dep)^14 -> 30 | E18: =Model!Q43 -> 18.611167 | F18: =Model!Q45 -> 0 | G18: =Model!#REF! -> #REF! | H18: =Model!Q67 -> 0 | I18: =Model!Q27 -> 90.036034 | J18: =Model!Q32 -> 226.55416 | K18: =Model!Q29 -> 85.136209 | L18: =Model!Q22 -> 79.871236 | M18: =Model!Q61 -> -1.3606318 | N18: =Model!Q60 -> -312.93576 | O18: =Model!Q58 -> -272.47785 | P18: =Model!Q59 -> -37 | Q18: =Model!Q63 -> 0 | R18: =Model!Q34 -> 0.72888696 | S18: =Model!Q39 -> 3.1218788 | T18: =Model!Q23 -> 79.839928 | U18: =Model!Q26 -> -6.9511031 | V18: =Model!Q47 -> 766.77097 | W18: =Model!Q48 -> 87.860836 | X18: =Model!Q30 -> -3.1218788 | Y18: =Baseline!R27 -> #REF! | Z18: =Model!Q39 -> 3.1218788 | AA18: =Baseline!R14 -> #REF! | AB18: =Baseline!R18 -> 22 | AC18: =Baseline!R43 -> 0 | AD18: =Baseline!R23 -> #REF! | AE18: =Baseline!R68 -> 0 | AF18: =Baseline!R62 -> 0 | AG18: =Model!Q51 -> 3.6559031 | AH18: =Model!Q52 -> 924.92482 | AI18: =Model!Q57 -> 0.20589261 | AJ18: =Model!Q7 -> 0 | AK18: =IF(Model!$C$27>0,Baseline!R27/Model!$C$27*100,100) -> #REF! | AL18: =IF(Model!$C$27>0,Baseline!R33/Model!$C$27*100,100) -> 0 | AM18: =Baseline!R14 -> #REF! | AN18: =Baseline!R43 -> 0 | AO18: =Baseline!R62 -> 0 | AP18: =Baseline!R15 -> #REF! | AQ18: =Baseline!R20 -> 42.3984 | AR18: =Baseline!R24 -> #REF! | AS18: =IF(Baseline!R22>0,Baseline!R27/Baseline!R22,0) -> 0 | AT18: =Baseline!R18 -> 22 | AU18: =Baseline!R43 -> 0 | AV18: =VRE_Start -> 30 | AW18: =VRE_Start -> 30
A19: Yr 16 | B19: =Model!R14 -> 17.321378 | C19: =Model!R18 -> 22 | D19: =VRE_Start*(1-VRE_Dep)^15 -> 30 | E19: =Model!R43 -> 22.492241 | F19: =Model!R45 -> 0 | G19: =Model!#REF! -> #REF! | H19: =Model!R67 -> 0 | I19: =Model!R27 -> 91.11384 | J19: =Model!R32 -> 218.18366 | K19: =Model!R29 -> 85.533423 | L19: =Model!R22 -> 79.47618 | M19: =Model!R61 -> -1.7718427 | N19: =Model!R60 -> -411.21098 | O19: =Model!R58 -> -371.28965 | P19: =Model!R59 -> -37 | Q19: =Model!R63 -> 0 | R19: =Model!R34 -> 0.7535336 | S19: =Model!R39 -> 2.6631625 | T19: =Model!R23 -> 85.235313 | U19: =Model!R26 -> -5.3319145 | V19: =Model!R47 -> 927.95855 | W19: =Model!R48 -> 87.422972 | X19: =Model!R30 -> -2.6631625 | Y19: =Baseline!S27 -> #REF! | Z19: =Model!R39 -> 2.6631625 | AA19: =Baseline!S14 -> #REF! | AB19: =Baseline!S18 -> 22 | AC19: =Baseline!S43 -> 0 | AD19: =Baseline!S23 -> #REF! | AE19: =Baseline!S68 -> 0 | AF19: =Baseline!S62 -> 0 | AG19: =Model!R51 -> 4.1441174 | AH19: =Model!R52 -> 1048.4406 | AI19: =Model!R57 -> 0.28122332 | AJ19: =Model!R7 -> 0 | AK19: =IF(Model!$C$27>0,Baseline!S27/Model!$C$27*100,100) -> #REF! | AL19: =IF(Model!$C$27>0,Baseline!S33/Model!$C$27*100,100) -> 0 | AM19: =Baseline!S14 -> #REF! | AN19: =Baseline!S43 -> 0 | AO19: =Baseline!S62 -> 0 | AP19: =Baseline!S15 -> #REF! | AQ19: =Baseline!S20 -> 42.3984 | AR19: =Baseline!S24 -> #REF! | AS19: =IF(Baseline!S22>0,Baseline!S27/Baseline!S22,0) -> 0 | AT19: =Baseline!S18 -> 22 | AU19: =Baseline!S43 -> 0 | AV19: =VRE_Start -> 30 | AW19: =VRE_Start -> 30
A20: Yr 17 | B20: =Model!S14 -> 16.410631 | C20: =Model!S18 -> 22 | D20: =VRE_Start*(1-VRE_Dep)^16 -> 30 | E20: =Model!S43 -> 25.840515 | F20: =Model!S45 -> 0 | G20: =Model!#REF! -> #REF! | H20: =Model!S67 -> 0 | I20: =Model!S27 -> 87.635966 | J20: =Model!S32 -> 228.14573 | K20: =Model!S29 -> 83.50711 | L20: =Model!S22 -> 79.116979 | M20: =Model!S61 -> -2.24157 | N20: =Model!S60 -> -469.72727 | O20: =Model!S58 -> -425.96481 | P20: =Model!S59 -> -37 | Q20: =Model!S63 -> 0 | R20: =Model!S34 -> 0.77818024 | S20: =Model!S39 -> 3.3468509 | T20: =Model!S23 -> 89.68112 | U20: =Model!S26 -> -5.8165689 | V20: =Model!S47 -> 1124.0107 | W20: =Model!S48 -> 87.103362 | X20: =Model!S30 -> -3.3468509 | Y20: =Baseline!T27 -> #REF! | Z20: =Model!S39 -> 3.3468509 | AA20: =Baseline!T14 -> #REF! | AB20: =Baseline!T18 -> 22 | AC20: =Baseline!T43 -> 0 | AD20: =Baseline!T23 -> #REF! | AE20: =Baseline!T68 -> 0 | AF20: =Baseline!T62 -> 0 | AG20: =Model!S51 -> 4.5600466 | AH20: =Model!S52 -> 1153.6685 | AI20: =Model!S57 -> 0.31877826 | AJ20: =Model!S7 -> 0 | AK20: =IF(Model!$C$27>0,Baseline!T27/Model!$C$27*100,100) -> #REF! | AL20: =IF(Model!$C$27>0,Baseline!T33/Model!$C$27*100,100) -> 0 | AM20: =Baseline!T14 -> #REF! | AN20: =Baseline!T43 -> 0 | AO20: =Baseline!T62 -> 0 | AP20: =Baseline!T15 -> #REF! | AQ20: =Baseline!T20 -> 42.3984 | AR20: =Baseline!T24 -> #REF! | AS20: =IF(Baseline!T22>0,Baseline!T27/Baseline!T22,0) -> 0 | AT20: =Baseline!T18 -> 22 | AU20: =Baseline!T43 -> 0 | AV20: =VRE_Start -> 30 | AW20: =VRE_Start -> 30
A21: Yr 18 | B21: =Model!T14 -> 15.429502 | C21: =Model!T18 -> 22 | D21: =VRE_Start*(1-VRE_Dep)^17 -> 30 | E21: =Model!T43 -> 29.704058 | F21: =Model!T45 -> 0 | G21: =Model!#REF! -> #REF! | H21: =Model!T67 -> 0 | I21: =Model!T27 -> 88.121252 | J21: =Model!T32 -> 222.69977 | K21: =Model!T29 -> 83.725818 | L21: =Model!T22 -> 79.03377 | M21: =Model!T61 -> -2.7534676 | N21: =Model!T60 -> -511.8976 | O21: =Model!T58 -> -468.11243 | P21: =Model!T59 -> -37 | Q21: =Model!T63 -> 0 | R21: =Model!T34 -> 0.80282688 | S21: =Model!T39 -> 3.0658234 | T21: =Model!T23 -> 94.717674 | U21: =Model!T26 -> -5.1116931 | V21: =Model!T47 -> 1257.5457 | W21: =Model!T48 -> 86.693888 | X21: =Model!T30 -> -3.0658234 | Y21: =Baseline!U27 -> #REF! | Z21: =Model!T39 -> 3.0658234 | AA21: =Baseline!U14 -> #REF! | AB21: =Baseline!U18 -> 22 | AC21: =Baseline!U43 -> 0 | AD21: =Baseline!U23 -> #REF! | AE21: =Baseline!U68 -> 0 | AF21: =Baseline!U62 -> 0 | AG21: =Model!T51 -> 5.6652341 | AH21: =Model!T52 -> 1433.2753 | AI21: =Model!T57 -> 0.35077281 | AJ21: =Model!T7 -> 0 | AK21: =IF(Model!$C$27>0,Baseline!U27/Model!$C$27*100,100) -> #REF! | AL21: =IF(Model!$C$27>0,Baseline!U33/Model!$C$27*100,100) -> 0 | AM21: =Baseline!U14 -> #REF! | AN21: =Baseline!U43 -> 0 | AO21: =Baseline!U62 -> 0 | AP21: =Baseline!U15 -> #REF! | AQ21: =Baseline!U20 -> 42.3984 | AR21: =Baseline!U24 -> #REF! | AS21: =IF(Baseline!U22>0,Baseline!U27/Baseline!U22,0) -> 0 | AT21: =Baseline!U18 -> 22 | AU21: =Baseline!U43 -> 0 | AV21: =VRE_Start -> 30 | AW21: =VRE_Start -> 30
A22: Yr 19 | B22: =Model!U14 -> 14.46257 | C22: =Model!U18 -> 22 | D22: =VRE_Start*(1-VRE_Dep)^18 -> 30 | E22: =Model!U43 -> 34.584312 | F22: =Model!U45 -> 0 | G22: =Model!#REF! -> #REF! | H22: =Model!U67 -> 0 | I22: =Model!U27 -> 86.580835 | J22: =Model!U32 -> 219.28992 | K22: =Model!U29 -> 82.831844 | L22: =Model!U22 -> 78.866961 | M22: =Model!U61 -> -3.3848825 | N22: =Model!U60 -> -631.41491 | O22: =Model!U58 -> -584.63713 | P22: =Model!U59 -> -37 | Q22: =Model!U63 -> 0 | R22: =Model!U34 -> 0.82747352 | S22: =Model!U39 -> 2.9004669 | T22: =Model!U23 -> 100.58915 | U22: =Model!U26 -> -3.2176951 | V22: =Model!U47 -> 1496.2914 | W22: =Model!U48 -> 86.636835 | X22: =Model!U30 -> -2.9004669 | Y22: =Baseline!V27 -> #REF! | Z22: =Model!U39 -> 2.9004669 | AA22: =Baseline!V14 -> #REF! | AB22: =Baseline!V18 -> 22 | AC22: =Baseline!V43 -> 0 | AD22: =Baseline!V23 -> #REF! | AE22: =Baseline!V68 -> 0 | AF22: =Baseline!V62 -> 0 | AG22: =Model!U51 -> 5.6546922 | AH22: =Model!U52 -> 1430.6083 | AI22: =Model!U57 -> 0.43578724 | AJ22: =Model!U7 -> 0 | AK22: =IF(Model!$C$27>0,Baseline!V27/Model!$C$27*100,100) -> #REF! | AL22: =IF(Model!$C$27>0,Baseline!V33/Model!$C$27*100,100) -> 0 | AM22: =Baseline!V14 -> #REF! | AN22: =Baseline!V43 -> 0 | AO22: =Baseline!V62 -> 0 | AP22: =Baseline!V15 -> #REF! | AQ22: =Baseline!V20 -> 42.3984 | AR22: =Baseline!V24 -> #REF! | AS22: =IF(Baseline!V22>0,Baseline!V27/Baseline!V22,0) -> 0 | AT22: =Baseline!V18 -> 22 | AU22: =Baseline!V43 -> 0 | AV22: =VRE_Start -> 30 | AW22: =VRE_Start -> 30
A23: Yr 20 | B23: =Model!V14 -> 13.487847 | C23: =Model!V18 -> 22 | D23: =VRE_Start*(1-VRE_Dep)^19 -> 30 | E23: =Model!V43 -> 38.436361 | F23: =Model!V45 -> 0 | G23: =Model!#REF! -> #REF! | H23: =Model!V67 -> 0 | I23: =Model!V27 -> 83.424686 | J23: =Model!V32 -> 230.0998 | K23: =Model!V29 -> 81.141392 | L23: =Model!V22 -> 78.778222 | M23: =Model!V61 -> -4.0272831 | N23: =Model!V60 -> -642.40053 | O23: =Model!V58 -> -589.34638 | P23: =Model!V59 -> -37 | Q23: =Model!V63 -> 0 | R23: =Model!V34 -> 0.85212016 | S23: =Model!V39 -> 3.6794995 | T23: =Model!V23 -> 105.03199 | U23: =Model!V26 -> -3.9896461 | V23: =Model!V47 -> 1666.486 | W23: =Model!V48 -> 86.388529 | X23: =Model!V30 -> -3.6794995 | Y23: =Baseline!W27 -> #REF! | Z23: =Model!V39 -> 3.6794995 | AA23: =Baseline!W14 -> #REF! | AB23: =Baseline!W18 -> 22 | AC23: =Baseline!W43 -> 0 | AD23: =Baseline!W23 -> #REF! | AE23: =Baseline!W68 -> 0 | AF23: =Baseline!W62 -> 0 | AG23: =Model!V51 -> 6.5387966 | AH23: =Model!V52 -> 1654.2822 | AI23: =Model!V57 -> 0.43497632 | AJ23: =Model!V7 -> 0 | AK23: =IF(Model!$C$27>0,Baseline!W27/Model!$C$27*100,100) -> #REF! | AL23: =IF(Model!$C$27>0,Baseline!W33/Model!$C$27*100,100) -> 0 | AM23: =Baseline!W14 -> #REF! | AN23: =Baseline!W43 -> 0 | AO23: =Baseline!W62 -> 0 | AP23: =Baseline!W15 -> #REF! | AQ23: =Baseline!W20 -> 42.3984 | AR23: =Baseline!W24 -> #REF! | AS23: =IF(Baseline!W22>0,Baseline!W27/Baseline!W22,0) -> 0 | AT23: =Baseline!W18 -> 22 | AU23: =Baseline!W43 -> 0 | AV23: =VRE_Start -> 30 | AW23: =VRE_Start -> 30
A24: Yr 21 | B24: =Model!W14 -> 12.498095 | C24: =Model!W18 -> 22 | D24: =VRE_Start*(1-VRE_Dep)^20 -> 30 | E24: =Model!W43 -> 44.260786 | F24: =Model!W45 -> 0 | G24: =Model!#REF! -> #REF! | H24: =Model!W67 -> 0 | I24: =Model!W27 -> 84.445251 | J24: =Model!W32 -> 214.79182 | K24: =Model!W29 -> 81.676197 | L24: =Model!W22 -> 78.789539 | M24: =Model!W61 -> -4.7594775 | N24: =Model!W60 -> -732.19447 | O24: =Model!W58 -> -679.3692 | P24: =Model!W59 -> -37 | Q24: =Model!W63 -> 0 | R24: =Model!W34 -> 0.8767668 | S24: =Model!W39 -> 2.7008778 | T24: =Model!W23 -> 111.57808 | U24: =Model!W26 -> -0.69909443 | V24: =Model!W47 -> 1870.2933 | W24: =Model!W48 -> 86.306977 | X24: =Model!W30 -> -2.7008778 | Y24: =Baseline!X27 -> #REF! | Z24: =Model!W39 -> 2.7008778 | AA24: =Baseline!X14 -> #REF! | AB24: =Baseline!X18 -> 22 | AC24: =Baseline!X43 -> 0 | AD24: =Baseline!X23 -> #REF! | AE24: =Baseline!X68 -> 0 | AF24: =Baseline!X62 -> 0 | AG24: =Model!W51 -> 7.2251599 | AH24: =Model!W52 -> 1827.9286 | AI24: =Model!W57 -> 0.50298435 | AJ24: =Model!W7 -> 0 | AK24: =IF(Model!$C$27>0,Baseline!X27/Model!$C$27*100,100) -> #REF! | AL24: =IF(Model!$C$27>0,Baseline!X33/Model!$C$27*100,100) -> 0 | AM24: =Baseline!X14 -> #REF! | AN24: =Baseline!X43 -> 0 | AO24: =Baseline!X62 -> 0 | AP24: =Baseline!X15 -> #REF! | AQ24: =Baseline!X20 -> 42.3984 | AR24: =Baseline!X24 -> #REF! | AS24: =IF(Baseline!X22>0,Baseline!X27/Baseline!X22,0) -> 0 | AT24: =Baseline!X18 -> 22 | AU24: =Baseline!X43 -> 0 | AV24: =VRE_Start -> 30 | AW24: =VRE_Start -> 30
A25: Yr 22 | B25: =Model!X14 -> 11.556434 | C25: =Model!X18 -> 22 | D25: =VRE_Start*(1-VRE_Dep)^21 -> 30 | E25: =Model!X43 -> 49.582409 | F25: =Model!X45 -> 0 | G25: =Model!#REF! -> #REF! | H25: =Model!X67 -> 0 | I25: =Model!X27 -> 79.596131 | J25: =Model!X32 -> 224.14984 | K25: =Model!X29 -> 79.128933 | L25: =Model!X22 -> 78.658402 | M25: =Model!X61 -> -5.5866644 | N25: =Model!X60 -> -827.1869 | O25: =Model!X58 -> -761.84267 | P25: =Model!X59 -> -37 | Q25: =Model!X63 -> 0 | R25: =Model!X34 -> 0.90141344 | S25: =Model!X39 -> 3.4197264 | T25: =Model!X23 -> 117.01734 | U25: =Model!X26 -> -0.0968167 | V25: =Model!X47 -> 2152.7316 | W25: =Model!X48 -> 86.512215 | X25: =Model!X30 -> -3.4197264 | Y25: =Baseline!Y27 -> #REF! | Z25: =Model!X39 -> 3.4197264 | AA25: =Baseline!Y14 -> #REF! | AB25: =Baseline!Y18 -> 22 | AC25: =Baseline!Y43 -> 0 | AD25: =Baseline!Y23 -> #REF! | AE25: =Baseline!Y68 -> 0 | AF25: =Baseline!Y62 -> 0 | AG25: =Model!X51 -> 7.022213 | AH25: =Model!X52 -> 1776.5841 | AI25: =Model!X57 -> 0.55578153 | AJ25: =Model!X7 -> 0 | AK25: =IF(Model!$C$27>0,Baseline!Y27/Model!$C$27*100,100) -> #REF! | AL25: =IF(Model!$C$27>0,Baseline!Y33/Model!$C$27*100,100) -> 0 | AM25: =Baseline!Y14 -> #REF! | AN25: =Baseline!Y43 -> 0 | AO25: =Baseline!Y62 -> 0 | AP25: =Baseline!Y15 -> #REF! | AQ25: =Baseline!Y20 -> 42.3984 | AR25: =Baseline!Y24 -> #REF! | AS25: =IF(Baseline!Y22>0,Baseline!Y27/Baseline!Y22,0) -> 0 | AT25: =Baseline!Y18 -> 22 | AU25: =Baseline!Y43 -> 0 | AV25: =VRE_Start -> 30 | AW25: =VRE_Start -> 30
A26: Yr 23 | B26: =Model!Y14 -> 10.605733 | C26: =Model!Y18 -> 22 | D26: =VRE_Start*(1-VRE_Dep)^22 -> 30 | E26: =Model!Y43 -> 55.035086 | F26: =Model!Y45 -> 0 | G26: =Model!#REF! -> #REF! | H26: =Model!Y67 -> 0 | I26: =Model!Y27 -> 78.986048 | J26: =Model!Y32 -> 223.58678 | K26: =Model!Y29 -> 78.922893 | L26: =Model!Y22 -> 78.859676 | M26: =Model!Y61 -> -6.3978854 | N26: =Model!Y60 -> -811.22098 | O26: =Model!Y58 -> -741.32081 | P26: =Model!Y59 -> -37 | Q26: =Model!Y63 -> 0 | R26: =Model!Y34 -> 0.92606008 | S26: =Model!Y39 -> 3.4481262 | T26: =Model!Y23 -> 122.48582 | U26: =Model!Y26 -> 1.2215003 | V26: =Model!Y47 -> 2317.0077 | W26: =Model!Y48 -> 86.386253 | X26: =Model!Y30 -> -3.4481262 | Y26: =Baseline!Z27 -> #REF! | Z26: =Model!Y39 -> 3.4481262 | AA26: =Baseline!Z14 -> #REF! | AB26: =Baseline!Z18 -> 22 | AC26: =Baseline!Z43 -> 0 | AD26: =Baseline!Z23 -> #REF! | AE26: =Baseline!Z68 -> 0 | AF26: =Baseline!Z62 -> 0 | AG26: =Model!Y51 -> 8.4056283 | AH26: =Model!Y52 -> 2126.581 | AI26: =Model!Y57 -> 0.54017023 | AJ26: =Model!Y7 -> 0 | AK26: =IF(Model!$C$27>0,Baseline!Z27/Model!$C$27*100,100) -> #REF! | AL26: =IF(Model!$C$27>0,Baseline!Z33/Model!$C$27*100,100) -> 0 | AM26: =Baseline!Z14 -> #REF! | AN26: =Baseline!Z43 -> 0 | AO26: =Baseline!Z62 -> 0 | AP26: =Baseline!Z15 -> #REF! | AQ26: =Baseline!Z20 -> 42.3984 | AR26: =Baseline!Z24 -> #REF! | AS26: =IF(Baseline!Z22>0,Baseline!Z27/Baseline!Z22,0) -> 0 | AT26: =Baseline!Z18 -> 22 | AU26: =Baseline!Z43 -> 0 | AV26: =VRE_Start -> 30 | AW26: =VRE_Start -> 30
A27: Yr 24 | B27: =Model!Z14 -> 9.7010187 | C27: =Model!Z18 -> 22 | D27: =VRE_Start*(1-VRE_Dep)^23 -> 30 | E27: =Model!Z43 -> 61.035086 | F27: =Model!Z45 -> 0 | G27: =Model!#REF! -> #REF! | H27: =Model!Z67 -> 0 | I27: =Model!Z27 -> 77.496475 | J27: =Model!Z32 -> 211.94288 | K27: =Model!Z29 -> 78.115912 | L27: =Model!Z22 -> 78.728066 | M27: =Model!Z61 -> -7.3678051 | N27: =Model!Z60 -> -969.91972 | O27: =Model!Z58 -> -891.47889 | P27: =Model!Z59 -> -37 | Q27: =Model!Z63 -> 0 | R27: =Model!Z34 -> 0.95070672 | S27: =Model!Z39 -> 2.6496222 | T27: =Model!Z23 -> 128.48582 | U27: =Model!Z26 -> 2.7363411 | V27: =Model!Z47 -> 2655.7261 | W27: =Model!Z48 -> 86.837474 | X27: =Model!Z30 -> -2.6496222 | Y27: =Baseline!AA27 -> #REF! | Z27: =Model!Z39 -> 2.6496222 | AA27: =Baseline!AA14 -> #REF! | AB27: =Baseline!AA18 -> 22 | AC27: =Baseline!AA43 -> 0 | AD27: =Baseline!AA23 -> #REF! | AE27: =Baseline!AA68 -> 0 | AF27: =Baseline!AA62 -> 0 | AG27: =Model!Z51 -> 8.1410534 | AH27: =Model!Z52 -> 2059.645 | AI27: =Model!Z57 -> 0.64658679 | AJ27: =Model!Z7 -> 0 | AK27: =IF(Model!$C$27>0,Baseline!AA27/Model!$C$27*100,100) -> #REF! | AL27: =IF(Model!$C$27>0,Baseline!AA33/Model!$C$27*100,100) -> 0 | AM27: =Baseline!AA14 -> #REF! | AN27: =Baseline!AA43 -> 0 | AO27: =Baseline!AA62 -> 0 | AP27: =Baseline!AA15 -> #REF! | AQ27: =Baseline!AA20 -> 42.3984 | AR27: =Baseline!AA24 -> #REF! | AS27: =IF(Baseline!AA22>0,Baseline!AA27/Baseline!AA22,0) -> 0 | AT27: =Baseline!AA18 -> 22 | AU27: =Baseline!AA43 -> 0 | AV27: =VRE_Start -> 30 | AW27: =VRE_Start -> 30
A28: Yr 25 | B28: =Model!AA14 -> 8.8385434 | C28: =Model!AA18 -> 22 | D28: =VRE_Start*(1-VRE_Dep)^24 -> 30 | E28: =Model!AA43 -> 67.035086 | F28: =Model!AA45 -> 0 | G28: =Model!#REF! -> #REF! | H28: =Model!AA67 -> 0 | I28: =Model!AA27 -> 76.048931 | J28: =Model!AA32 -> 224.8912 | K28: =Model!AA29 -> 77.399298 | L28: =Model!AA22 -> 78.715214 | M28: =Model!AA61 -> -8.3237382 | N28: =Model!AA60 -> -955.93309 | O28: =Model!AA58 -> -866.95687 | P28: =Model!AA59 -> -37 | Q28: =Model!AA63 -> 0 | R28: =Model!AA34 -> 0.97535336 | S28: =Model!AA39 -> 3.6836684 | T28: =Model!AA23 -> 134.48582 | U28: =Model!AA26 -> 4.9067287 | V28: =Model!AA47 -> 2918.7674 | W28: =Model!AA48 -> 86.992803 | X28: =Model!AA30 -> -3.6836684 | Y28: =Baseline!AB27 -> #REF! | Z28: =Model!AA39 -> 3.6836684 | AA28: =Baseline!AB14 -> #REF! | AB28: =Baseline!AB18 -> 22 | AC28: =Baseline!AB43 -> 0 | AD28: =Baseline!AB23 -> #REF! | AE28: =Baseline!AB68 -> 0 | AF28: =Baseline!AB62 -> 0 | AG28: =Model!AA51 -> 8.5175346 | AH28: =Model!AA52 -> 2154.8928 | AI28: =Model!AA57 -> 0.62623488 | AJ28: =Model!AA7 -> 0 | AK28: =IF(Model!$C$27>0,Baseline!AB27/Model!$C$27*100,100) -> #REF! | AL28: =IF(Model!$C$27>0,Baseline!AB33/Model!$C$27*100,100) -> 0 | AM28: =Baseline!AB14 -> #REF! | AN28: =Baseline!AB43 -> 0 | AO28: =Baseline!AB62 -> 0 | AP28: =Baseline!AB15 -> #REF! | AQ28: =Baseline!AB20 -> 42.3984 | AR28: =Baseline!AB24 -> #REF! | AS28: =IF(Baseline!AB22>0,Baseline!AB27/Baseline!AB22,0) -> 0 | AT28: =Baseline!AB18 -> 22 | AU28: =Baseline!AB43 -> 0 | AV28: =VRE_Start -> 30 | AW28: =VRE_Start -> 30
A29: Yr 26 | B29: =Model!AB14 -> 8.0227624 | C29: =Model!AB18 -> 22 | D29: =VRE_Start*(1-VRE_Dep)^25 -> 30 | E29: =Model!AB43 -> 73.035086 | F29: =Model!AB45 -> 0 | G29: =Model!#REF! -> #REF! | H29: =Model!AB67 -> 0 | I29: =Model!AB27 -> 74.212876 | J29: =Model!AB32 -> 215.40336 | K29: =Model!AB29 -> 76.570744 | L29: =Model!AB22 -> 78.824379 | M29: =Model!AB61 -> -9.3351314 | N29: =Model!AB60 -> -1011.3932 | O29: =Model!AB58 -> -911.32903 | P29: =Model!AB59 -> -37 | Q29: =Model!AB63 -> 0 | R29: =Model!AB34 -> 1 | S29: =Model!AB39 -> 3.0299645 | T29: =Model!AB23 -> 140.48582 | U29: =Model!AB26 -> 6.8551743 | V29: =Model!AB47 -> 3175.4358 | W29: =Model!AB48 -> 87.180738 | X29: =Model!AB30 -> -3.0299645 | Y29: =Baseline!AC27 -> #REF! | Z29: =Model!AB39 -> 3.0299645 | AA29: =Baseline!AC14 -> #REF! | AB29: =Baseline!AC18 -> 22 | AC29: =Baseline!AC43 -> 0 | AD29: =Baseline!AC23 -> #REF! | AE29: =Baseline!AC68 -> 0 | AF29: =Baseline!AC62 -> 0 | AG29: =Model!AB51 -> 9.719398 | AH29: =Model!AB52 -> 2458.9581 | AI29: =Model!AB57 -> 0.65519497 | AJ29: =Model!AB7 -> 0 | AK29: =IF(Model!$C$27>0,Baseline!AC27/Model!$C$27*100,100) -> #REF! | AL29: =IF(Model!$C$27>0,Baseline!AC33/Model!$C$27*100,100) -> 0 | AM29: =Baseline!AC14 -> #REF! | AN29: =Baseline!AC43 -> 0 | AO29: =Baseline!AC62 -> 0 | AP29: =Baseline!AC15 -> #REF! | AQ29: =Baseline!AC20 -> 42.3984 | AR29: =Baseline!AC24 -> #REF! | AS29: =IF(Baseline!AC22>0,Baseline!AC27/Baseline!AC22,0) -> 0 | AT29: =Baseline!AC18 -> 22 | AU29: =Baseline!AC43 -> 0 | AV29: =VRE_Start -> 30 | AW29: =VRE_Start -> 30

Sheet Model Guide
A1: ESEM GENERIC GRID MODEL — ROW-BY-ROW GUIDE
A2: 26-year illustrative NEM transition model. NOT a forecasting tool. MY0=4: col D = Year 1 (t=0) through col AC = Year 26 (t=25). Period offset t is stored in row 2. Demand = 170 TWh, growth 2.5%/yr. All edits via Python/openpyxl — see HANDOFF.md for script pattern.
A4: SECTION 1 — DEMAND & SHOCKS (R4–R9)
A5: Row | B5: Name | C5: Units | D5: Description | E5: Formula / Notes
A6: R4 | B6: Demand shock | C6: rate | D6: Scenario-driven fractional shock to demand. Reads from Scenarios sheet based on Dashboard dropdown (Scenario A/B/C). Applied multiplicatively to base demand in R7. | E6: =Scenarios lookup by scenario name -> #NAME?
A7: R5 | B7: Supply shock | C7: rate | D7: Fractional shock to generation output (positive = more supply noise). Applied to coal generation (R15) and VRE generation (R24). Same scenario structure as R4. | E7: =Scenarios lookup by scenario name -> #NAME?
A8: R6 | B8: Base demand | C8: TWh | D8: Pure trend demand before shocks. Grows at Dem_Growth=2.5%/yr from Dem_Start=170 TWh. 170 TWh represents NEM operational demand net of rooftop solar self-consumption. | E8: =Dem_Start*(1+Dem_Growth)^t -> #NAME?
A9: R7 | B9: Effective demand | C9: TWh | D9: Demand after applying demand shock from R4. This is the target energy requirement used in R26 (energy balance), R39 (ESEM VRE target) and R61 (levy calculation). | E9: =R6*(1+R4) -> 0
A10: R8 | B10: Peak demand (base) | C10: GW | D10: Instantaneous peak demand trend. Peak_Start=36 GW growing at Peak_Growth=2%/yr. Used as the basis for the firm adequacy requirement. | E10: =Peak_Start*(1+Peak_Growth)^t -> #NAME?
A11: R9 | B11: Peak firm requirement | C11: GW | D11: Effective peak demand after shock — the capacity adequacy target. Used in R31 (firming balance) and R41 (ESEM firm procurement gap). = R8*(1+R4). | E11: =R8*(1+R4) -> 0
A13: SECTION 2 — COAL (R11–R16) Coal_Start=20 GW | Coal_CFe=0.45 | Coal_CFp=0.75 | Coal_SRMC=$80 | Coal_Esc=4%/yr | Coal_Accel=0.10
A14: Row | B14: Name | C14: Units | D14: Description | E14: Formula / Notes
A15: R11 | B15: Coal SRMC | C15: $/MWh | D15: Marginal running cost of coal fleet, escalating 4%/yr (fuel + O&M + carbon). Used in R13 economic attrition: coal exits faster when WS exceeds this threshold. | E15: =Coal_SRMC*(1+Coal_Esc)^t -> #NAME?
A16: R12 | B16: Scheduled closures | C16: rate | D16: Fraction of coal fleet retiring this year per announced closure schedule. Reads from Scenarios sheet (same mechanism as demand/supply shocks). Applied multiplicatively in R14. | E16: =Scenarios lookup -> #NAME?
A17: R13 | B17: Economic attrition rate | C17: rate | D17: Additional coal exits driven by high wholesale price. = Coal_Accel * MAX(0, (WS_prev - Coal_SRMC_prev) / WS_prev). Coal_Accel=0.10 (reduced from 0.30). Uses PRIOR-year WS (F27) to avoid circular reference — Year 1 attrition = 0. At WS=$180, SRMC=$80: attrition = 0.10*0.56 = 5.6%/yr.
A18: R14 | B18: Coal capacity | C18: GW | D18: Surviving coal fleet. Starts at Coal_Start=20 GW and declines each year through both scheduled closures (R12) and economic attrition (R13). MAX(0) prevents negative. Coal is the key price-setting unit in deficit years. | E18: =MAX(0, prev*(1-R12)*(1-R13)) -> #NAME?
A19: R15 | B19: Coal generation | C19: TWh | D19: Energy produced by coal fleet. Capacity factor Coal_CFe=0.45 applied to R14. Supply shock (R5) also applied. Included in R26 energy balance. | E19: =R14 * Coal_CFe * 8.76 * (1+R5) -> 0
A20: R16 | B20: Coal firm capacity | C20: GW | D20: Peak-period availability of coal fleet. Coal_CFp=0.75 applied to R14. Used in R31 firming balance as reliable capacity contribution. | E20: =R14 * Coal_CFp -> 0
A22: SECTION 3 — DISPATCHABLE FIRMING (R17–R20) Firm_Start=22 GW | Firm_SRMC=$180 | Firm_LRMC=$350 | Firm_CFe=0.22 | Firm_CFp=0.90
A23: Row | B23: Name | C23: Units | D23: Description | E23: Formula / Notes
A24: R17 | B24: Firm SRMC | C24: $/MWh | D24: Gas/firming dispatch cost = Firm_SRMC constant = $180/MWh. This is the WS ceiling — R27 is MIN(Firm_SRMC, ...) so WS can never exceed $180. Also used as the CfD strike reference for new firm builds (R51). | E24: =Firm_SRMC #REF! -> #REF!
A25: R18 | B25: Legacy firm capacity | C25: GW | D25: Existing gas/hydro/storage fleet. Starts at Firm_Start=22 GW. Firm_Decay=0 so no assumed retirements (conservative — full fleet available throughout). Does NOT include ESEM or private new builds — those are tracked in R46/R68. | E25: =Firm_Start*(1-Firm_Decay)^t -> #NAME?
A26: R19 | B26: Legacy firm peak | C26: GW | D26: Peak availability of legacy fleet = R18 * Firm_CFp. Used in R31 firming balance. | E26: =R18 * Firm_CFp -> 0
A27: R20 | B27: Legacy firm energy | C27: TWh | D27: Maximum energy if fully dispatched = R18 * Firm_CFe * 8.76. Firm_CFe=0.22 (peaker). NOT included in R26 energy balance by design: gas is the last-resort price-setting marginal unit, not a merit-order supply source. Its cost is captured in WS price.
A29: SECTION 4 — VRE (R22–R24) VRE_Start=27 GW | VRE_CFe=0.32 | VRE_Dep=4%/yr | VRE_LRMC=$85 | Trend1=-2.5%/yr | BP=Year 10 | Trend2=+1%/yr
A30: Row | B30: Name | C30: Units | D30: Description | E30: Formula / Notes
A31: R22 | B31: VRE LRMC | C31: $/MWh | D31: Long-run marginal cost of new VRE (build + finance cost). Piecewise trend: falls at 2.5%/yr from $85 to ~$64 by Year 10 (technology learning), then rises at 1%/yr after the breakpoint (grid integration costs). Key investment trigger: private VRE enters when forward price > R22 (see R35). | E31: =IF(t<=BP, LRMC*(1+T1)^t, LRMC*(1+T1)^BP*(1+T2)^(t-BP)) -> #NAME?
A32: R23 | B32: VRE online | C32: GW | D32: Total commissioned VRE fleet. Three components: (1) VRE_Start*(1-VRE_Dep)^t — existing 27 GW fleet depreciating at 4%/yr, falls to ~22 GW by Year 6 as old panels/turbines retire; (2) lag3(R43) — private VRE commissioned 3 years ago (construction lag); (3) lag3(R45) — ESEM VRE commissioned 3 years ago. Flat in Years 1-3 (bar depreciation) — no new builds commissioned yet. | E32: =VRE_Start*(1-VRE_Dep)^t + LAG3(R43) + LAG3(R45) -> #NAME?
A33: R24 | B33: VRE generation | C33: TWh | D33: Energy produced by online VRE fleet. VRE_CFe=0.32. Supply shock (R5) applied. Included in R26 energy balance alongside coal (R15) and Other_Gen. | E33: =R23 * VRE_CFe * 8.76 * (1+R5) -> 0
A35: SECTION 5 — ENERGY BALANCE & PRICES (R26–R34)
A36: Row | B36: Name | C36: Units | D36: Description | E36: Formula / Notes
A37: R26 | B37: Energy balance | C37: TWh | D37: Generation surplus (+) or deficit (-) relative to demand. = R15 (coal) + R24 (VRE) + Other_Gen (15 TWh/yr hydro+imports) - R7 (demand). Gas/firming generation deliberately EXCLUDED — gas is the marginal price-setter, not a merit-order source. Negative R26 means 'gas is running' not 'lights out'. With Other_Gen=15, Year 1 balance is approximately zero. Uses PRIOR-YEAR value (F26) in WS formula to avoid circular reference. | E37: =R15 + R24 + Other_Gen - R7 -> #REF!
A38: R27 | B38: Wholesale price | C38: $/MWh | D38: Market clearing price. Year 1 = VRE_LRMC (no prior balance). Year 2+: MIN(Firm_SRMC, VRE_LRMC * EXP(elasticity * |F26/R7|)). Surplus (F26>0): price decays below LRMC with elasticity Surp_Elas=3. Deficit (F26<0): price rises above LRMC with elasticity Def_Elas=2, capped at Firm_SRMC=$180 (gas price ceiling). WS <= Firm_SRMC always, which ensures firm CfD costs (R57) are non-negative.
A39: R28 | B39: WS (for fwd calc) | C39: $/MWh | D39: Current WS echoed for use in R30 forward price averaging window. | E39: =R27 -> 0
A40: R29 | B40: VRE_CFe | C40: — | D40: Capacity factor constant passed through for formula convenience in R24, R37, R39. | E40: =VRE_CFe #REF! -> #REF!
A41: R30 | B41: Forward price | C41: $/MWh | D41: Expected price that drives private and ESEM investment decisions. Weighted blend: Fwd_Alpha=0.35 * avg_LRMC_forward (next Fwd_Window=10yr) + (1-Fwd_Alpha-Fwd_SC_Wt) * avg_WS_spot * noise + Fwd_SC_Wt=0.15 * avg_SC. NOTE: Fwd_SC_Wt>0 couples the VRE and firming markets — can cause oscillation. Consider setting Fwd_SC_Wt=0, Fwd_Alpha=0.50 for cleaner dynamics. Baseline reads =Model!col30 — same draw prevents stochastic divergence. | E41: =Alpha*avg_LRMC + (1-Alpha-SC_Wt)*avg_WS*noise + SC_Wt*avg_SC -> #NAME?
A42: R31 | B42: Firming balance | C42: GW | D42: Firm capacity surplus (+) or deficit (-) relative to peak demand. = R16 (coal firm) + R19 (legacy firm) + lag3(R46 ESEM firm) + lag3(R68 priv firm) + R23*VRE_ELCC (VRE effective load carrying) + Other_Firm (3 GW) - R9 (peak). Negative in Years 1-6 (adequacy gap) until ESEM firm builds commission. Positive after ~Year 7 as ESEM firm stock commissions (3yr build lag from Year 3 start). | E42: =R16+R19+LAG3(R46)+LAG3(R68)+R23*ELCC+Other_Firm-R9 -> #REF!
A43: R32 | B43: Firming tightness | C43: — | E43: =-R31/R9 -> #DIV/0!
A44: R33 | B44: Scarcity price | C44: $/MWh | D44: Firm capacity price = Firm_SRMC * EXP(Firm_Tight * R32). Exponential premium when firming is tight. Firm_Tight=3.5. At 10% gap (R32=0.10): SC = $180 * exp(0.35) = $251. At 20% gap: SC = $180 * exp(0.70) = $360. Drives private firming entry (R36) and ESEM firm procurement (R41). | E44: =Firm_SRMC * EXP(Firm_Tight * R32) -> 180
A45: R34 | B45: Firm LRMC | C45: $/MWh | D45: Build cost for new dispatchable firming = Firm_LRMC constant = $350/MWh. Private firming enters when SC > Firm_LRMC (R36). At default SC levels this threshold is rarely met, so private firming is near-zero — ESEM fills the gap. | E45: =Firm_LRMC #REF! -> #REF!
A47: SECTION 6 — MARKET ENTRY (R35–R41)
A48: Row | B48: Name | C48: Units | D48: Description | E48: Formula / Notes
A49: R35 | B49: Private VRE procurement | C49: GW/yr | D49: New VRE contracted by private investors this year. Linear supply curve: entry begins when forward price (R30) exceeds VRE LRMC (R22). VRE_Sprd=8 $/MWh-per-GW — each GW of entry compresses the spread by $8. Goes into R43 cumulative stock; commissions in R23 after 3-year lag. | E49: =MAX(0, (R30 - R22) / VRE_Sprd) -> 0
A50: R36 | B50: Private firm procurement | C50: GW/yr | D50: New firming contracted by private investors. Enters when scarcity price (R33) exceeds Firm_LRMC=$350. Firm_Sprd=60 — very steep, so private firming rarely enters at current parameters. Goes into R68; commissions in R31 after 3-year lag. | E50: =MAX(0, (R33 - R34) / Firm_Sprd) -> 0
A51: R37 | B51: Private VRE pipeline | C51: TWh | D51: Private VRE ordered in the last 2 years still under construction (not yet in R23). = MAX(0, prev_R43 - lag3_R43) * VRE_CFe * 8.76. Subtracted from ESEM's shortfall in R39 so ESEM doesn't build on top of private builds already committed.
A52: R38 | B52: ESEM VRE target share | C52: — | D52: Linear ramp of VRE share target from VRE_Share0=36% (Year 1) to VRE_ShareT=95% (Year 26) of effective demand. = VRE_Share0 + (VRE_ShareT - VRE_Share0)/25 * t. ESEM procures to close the gap between actual VRE gen and this target. | E52: =VRE_Share0 + (VRE_ShareT-VRE_Share0)/25*t -> #NAME?
A53: R39 | B53: ESEM VRE procurement | C53: GW/yr | D53: ESEM CfD contracts for new VRE this year (when active, i.e. ESEM_On=1 and t>=ESEM_Start). Shortfall = target_TWh (R38*R7) - actual_TWh (R24) - private_pipeline (R37) - ESEM_own_pipeline (MAX(0,prev_R45-lag3_R45)*CFe*8760). Divides by (VRE_CFe*8760) to convert TWh shortfall to GW/yr procurement. Multiplied by RE_Cov=75% (partial coverage). MAX(0) ensures no negative procurement. Goes into R45 cumulative stock. | E53: =IF(active, MAX(0, shortfall_TWh - pipelines) / (CFe*8760) * RE_Cov, 0) -> #NAME?
A54: R40 | B54: Firming adequacy gap | C54: GW | D54: Raw adequacy gap before pipeline adjustments. = MAX(0, R9 - total_firm_available). 'Total firm available' = R16 + R19 + lag3(R46) + lag3(R68) + R23*VRE_ELCC + Other_Firm. | E54: =MAX(0, R9 - (R16+R19+LAG3(R46)+LAG3(R68)+R23*ELCC+Other_Firm)) -> #REF!
A55: R41 | B55: ESEM firm procurement | C55: GW/yr | D55: ESEM CfD contracts for new firm capacity this year (when active). Gap = R40 minus private firm pipeline (MAX(0,prev_R68-lag3_R68)) minus ESEM own pipeline (MAX(0,prev_R46-lag3_R46)). Both pipeline deductions prevent over-procurement. Multiplied by Firm_Cov=90%. Goes into R46 cumulative stock. | E55: =IF(active, MAX(0, gap - priv_pipe - ESEM_pipe)*Firm_Cov, 0) -> #NAME?
A57: SECTION 7 — CUMULATIVE STOCKS (R43–R46) VRE_Dep=4%/yr | Firm_Dep_New=0%/yr
A58: Row | B58: Name | C58: Units | D58: Description | E58: Formula / Notes
A59: R43 | B59: Private VRE cum. stock | C59: GW | D59: Running total of private VRE builds with 4%/yr depreciation. Year 1 = R35 (first cohort). Subsequent years: prev*(1-VRE_Dep) + R35. Lag-3 of this (lag3_R43) appears in R23 as commissioned online VRE. Also used in R37 pipeline calculation. | E59: =prev*(1-VRE_Dep) + R35 -> #NAME?
A60: R44 | B60: Unused (Baseline ESEM) | C60: GW | D60: Zero in Model sheet. Used in Baseline sheet as the ESEM VRE placeholder (always zero since Baseline has no ESEM). Included in Baseline R23 for symmetry.
A61: R45 | B61: ESEM VRE cum. stock | C61: GW | D61: Running total of ESEM VRE contracts procured, with 4%/yr depreciation. = prev*(1-VRE_Dep) + R39. Lag-3 in R23 (commissioned ESEM VRE online). Lag-3 also used in R39's own-pipeline check to prevent over-procurement. | E61: =prev*(1-VRE_Dep) + R39 -> #NAME?
A62: R46 | B62: ESEM firm cum. stock | C62: GW | D62: Running total of ESEM firm contracts procured. = prev*(1-Firm_Dep_New) + R41. Currently Firm_Dep_New=0 (no depreciation — stock accumulates indefinitely). Lag-3 in R31 (commissioned ESEM firm in firming balance). Lag-3 also in R41 own-pipeline check. | E62: =prev*(1-Firm_Dep_New) + R41 -> #NAME?
A64: SECTION 8 — SETTLED STOCK & DIVESTMENT (R48–R55) 6-year lag to settlement (3yr build + 3yr private period) | Divest_Rate=10%/yr
A65: Row | B65: Name | C65: Units | D65: Description | E65: Formula / Notes
A66: R48 | B66: ESEM VRE settled stock | C66: GW | D66: Running balance of ESEM VRE CfDs in active settlement. A cohort enters when it clears the 6-year total lag (3yr construction + 3yr private period). = MAX(0, prev*(1-Divest_Rate) + cohort_from_6yr_ago). Divest_Rate=10%/yr — portfolio transferred to private market at 10%/yr. Zero until Year 7. Peaks at ~10-20 GW, then gradually declines as divestment outpaces new cohorts entering settlement. | E66: =MAX(0, prev*(1-Divest_Rate) + lag6_R39_cohort) -> #NAME?
A67: R49 | B67: ESEM firm settled stock | C67: GW | D67: Same structure as R48 for firm capacity. = MAX(0, prev*(1-Divest_Rate) + firm_cohort_from_6yr_ago). | E67: =MAX(0, prev*(1-Divest_Rate) + lag6_R41_cohort) -> #NAME?
A68: R50 | B68: VRE CfD strike price | C68: $/MWh | D68: Fixed VRE strike = R22 (VRE_LRMC at time of contracting). NOT floating — locked at the cost of new VRE when ESEM signs the contract. As WS falls below this in later years, ESEM pays generators the difference (R56 positive). | E68: =R22 #REF! -> #REF!
A69: R51 | B69: Firm CfD strike price | C69: $/MWh | D69: Fixed firm strike = R17 (Firm_SRMC = $180). Locked at gas SRMC when ESEM contracts. WS <= Firm_SRMC always (from R27 MIN), so R57 (firm CfD cost) is always >= 0. | E69: =R17 #REF! -> #REF!
A70: R52 | B70: VRE divested stock | C70: GW | D70: GW of VRE settled stock transferred to private market this year = Divest_Rate * prev_R48 = 10% * R48. This stock generates recycling income in R58 (sold at current market prices). | E70: =Divest_Rate * prev_R48 -> #NAME?
A71: R53 | B71: Firm divested stock | C71: GW | D71: GW of firm settled stock divested this year = Divest_Rate * prev_R49. | E71: =Divest_Rate * prev_R49 -> #NAME?
A72: R54–R55 | B72: Intermediate | C72: — | D72: Rolling reference values for tracking strike prices and settlement inputs. Used in R56-R58 calculations. | E72: Various
A74: SECTION 9 — COST RECOVERY (R56–R62) Two-way CfD settled vs WS | Firm settled vs WS (not SC)
A75: Row | B75: Name | C75: Units | D75: Description | E75: Formula / Notes
A76: R56 | B76: VRE CfD annual cost | C76: $m | D76: Two-way contract settlement: (R50 - R27) * R48 * VRE_CFe * 8760. Strike (R50) fixed at LRMC when contracted. WS (R27) falls below LRMC as VRE surplus builds in later years. Positive = ESEM pays generators (surplus period). Negative = generators pay ESEM back (deficit period, WS > strike — rare). | E76: =(R50 - R27) * R48 * VRE_CFe * 8760 -> 0
A77: R57 | B77: Firm CfD annual cost | C77: $m | D77: Firm settlement: (R17 - R27) * R49 * Firm_CFe * 8760. Settled against WS (NOT scarcity price SC) — ensures always >= 0 since WS <= Firm_SRMC. Uses Firm_CFe=0.22 (energy generation factor, NOT Firm_CFp=0.90 peak availability). Key fix: using Firm_CFp would overstate costs by 0.90/0.22 = 4x.
A78: R58 | B78: Recycling income | C78: $m | D78: Income from divesting contracts to private market at current prices. Two legs: VRE leg: (R22-R30)*R52*VRE_CFe*8760 (divested VRE at forward price vs LRMC). Firm leg: (R17-R27)*R53*Firm_CFe*8760 (divested firm at WS vs SRMC). Negative R58 = ESEM earns when divesting at a premium; positive = cost when divesting at discount. | E78: =(R22-R30)*R52*CFe*8760 + (R17-R27)*R53*Firm_CFe*8760 -> #NAME?
A79: R59 | B79: Net ESEM annual cost | C79: $m | D79: Total annual programme net cost to consumers = R56 + R57 + R58 + Admin_Cost. Admin_Cost=$37m/yr when ESEM is active. Zero when ESEM_On=0 or before ESEM_Start. Positive = net outflow from consumers to generators. Typically: admin-only $37m in Years 3-7, then rising $100m-$2bn as settled stock grows. | E79: =IF(active, R56+R57+R58+Admin_Cost, 0) -> #NAME?
A80: R60 | B80: Cumulative ESEM cost | C80: $bn | D80: Running total cost to consumers across all years. = prev + R59/1000. Should reach $10-25bn over 26 years (after all bug fixes). Represents the total transfer from consumers to generator contract-holders via ESEM CfDs — the price of the transition guarantee. | E80: =prev + R59/1000 -> #NAME?
A81: R61 | B81: ESEM levy | C81: $/MWh | D81: Annual net cost spread over total energy demand = R59/R7. The per-MWh surcharge on consumer bills to fund ESEM. | E81: =R59 / R7 -> #DIV/0!
A82: R62 | B82: Consumer price | C82: $/MWh | D82: Total price faced by consumers = R27 (wholesale) + R61 (ESEM levy). In early years: WS high (deficit), levy small → consumer price near WS. In later years: WS falls (VRE surplus), levy rises (CfD payments) → prices stay elevated. The levy is the mechanism by which ESEM cost recovery shows up in consumer bills. | E82: =R27 + R61 -> 0
A84: SECTION 10 — DERIVED METRICS (R63–R68)
A85: Row | B85: Name | C85: Units | D85: Description | E85: Formula / Notes
A86: R63 | B86: Private CfD est. value | C86: $m | D86: Rough estimate: (R56+R57)*5. Illustrative measure of the private market value of ESEM contracts being divested. Factor of 5 = stylised market multiple.
A87: R64 | B87: WS / LRMC ratio | C87: — | E87: =R27/R22 -> #DIV/0!
A88: R65 | B88: ESEM market share | C88: — | D88: ESEM's share of total capacity = (R45+R46) / (coal+legacy_firm+VRE_Start+R43+R45+R46). Tracks how dominant ESEM becomes in the total generation and firming portfolio. | E88: =(R45+R46)/total_capacity -> #NAME?
A89: R66 | B89: Coal gen reference | C89: TWh | D89: =R15. Echo for chart use. -> #NAME? | E89: =R15 -> 0
A90: R67 | B90: WS reference | C90: $/MWh | D90: =R27. Echo for chart use. -> #NAME? | E90: =R27 -> 0
A91: R68 | B91: Private firm cum. stock | C91: GW | D91: Running total of private firming builds = prev*(1-Firm_Dep_New) + R36. Near-zero at current parameters (Firm_LRMC=$350 rarely triggered by scarcity price). Lag-3 in R31 firming balance and in R41 pipeline check. | E91: =prev*(1-Firm_Dep_New) + R36 -> #NAME?
A93: KEY PARAMETERS: Dem_Start=170 TWh | Coal_Start=20 GW | Coal_Accel=0.10 | Firm_SRMC=$180 | VRE_Start=27 GW | VRE_Dep=4%/yr | Other_Gen=15 TWh | Lag=3yr | Private_Lag=3yr | Divest_Rate=10%/yr | RE_Cov=75% | Firm_Cov=90%
A94: BASELINE SHEET differences: R4=Model!R4 (same demand draw), R5=Model!R5 (same supply draw), R12=Model!R12 (same closure schedule), R22=Model!R22 (same LRMC), R30=Model!R30 (same forward — prevents stochastic divergence). All ESEM rows (R39,R41,R45,R46,R48-R62) = 0. Coal exits against Baseline WS (higher than ESEM — no VRE surplus suppression). R23 uses R44 (not R45) for ESEM VRE column (always 0).

Sheet SENSITIVITY_ANALYSIS
A1: SENSITIVITY ANALYSIS -- VRE+Storage LRMC
A2: Pre-computed by phase3_optimizer.py. Re-run script to refresh after parameter changes. Base case: Alpha_Solar=0.67, VRE_Ratio=3, Direct=0.80, Drought=0.08, Batt_WACC=8%, Sol_WACC=7%, Wind_WACC=8%.
A4: Scenario | B4: Year | C4: w_1h | D4: w_2h | E4: w_4h | F4: w_8h | G4: Hrs_Effective | H4: Delivered_Energy_Factor | I4: LRMC_$/MWh
A5: Solar_share=0.0 | B5: Yr1 | C5: 0.8 | D5: 0 | E5: 0.1 | F5: 0.1 | G5: 2 | H5: 0.9467 | I5: 131.48
A6: Solar_share=0.0 | B6: Yr5 | C6: 0.8 | D6: 0 | E6: 0.1 | F6: 0.1 | G6: 2 | H6: 0.9467 | I6: 114.65
A7: Solar_share=0.0 | B7: Yr10 | C7: 0.8 | D7: 0 | E7: 0.1 | F7: 0.1 | G7: 2 | H7: 0.9467 | I7: 100.97
A8: Solar_share=0.0 | B8: Yr20 | C8: 0.8 | D8: 0 | E8: 0.1 | F8: 0.1 | G8: 2 | H8: 0.9467 | I8: 94.73
A9: Solar_share=0.0 | B9: Yr25 | C9: 0.8 | D9: 0 | E9: 0.1 | F9: 0.1 | G9: 2 | H9: 0.9467 | I9: 94.13
A10: Solar_share=0.1 | B10: Yr1 | C10: 0.7 | D10: 0.05 | E10: 0.05 | F10: 0.2 | G10: 2.6 | H10: 0.9115 | I10: 131.38
A11: Solar_share=0.1 | B11: Yr5 | C11: 0.7 | D11: 0.05 | E11: 0.05 | F11: 0.2 | G11: 2.6 | H11: 0.9115 | I11: 114.07
A12: Solar_share=0.1 | B12: Yr10 | C12: 0.7 | D12: 0.05 | E12: 0.05 | F12: 0.2 | G12: 2.6 | H12: 0.9115 | I12: 100.34
A13: Solar_share=0.1 | B13: Yr20 | C13: 0.7 | D13: 0.05 | E13: 0.05 | F13: 0.2 | G13: 2.6 | H13: 0.9115 | I13: 93.81
A14: Solar_share=0.1 | B14: Yr25 | C14: 0.7 | D14: 0.05 | E14: 0.05 | F14: 0.2 | G14: 2.6 | H14: 0.9115 | I14: 93.11
A15: Solar_share=0.2 | B15: Yr1 | C15: 0.6 | D15: 0.1 | E15: 0 | F15: 0.3 | G15: 3.2 | H15: 0.8764 | I15: 131.26
A16: Solar_share=0.2 | B16: Yr5 | C16: 0.6 | D16: 0.1 | E16: 0 | F16: 0.3 | G16: 3.2 | H16: 0.8764 | I16: 113.44
... A489: WACC(b+0.02,s+0.01,w+0.01) | B489: Yr25 | C489: 0.25 | D489: 0 | E489: 0.05 | F489: 0.7 | G489: 6.05 | H489: 0.7111 | I489: 93.07

Sheet CHANGELOG
A1: ESEM MODEL CHANGELOG
A2: Documents every structural change made in Phase 1, 2 and 3.
A4: Phase | B4: Sheet | C4: Cell/Row | D4: Old Assumption | E4: New Assumption | F4: Reason
A5: Ph1 | B5: Dashboard | C5: R33 VRE_CFe | D5: 0.32 (hardcoded) | E5: ='Building assets'!B71 -> 28.71 | F5: Aligns supply CF with LRMC asset CF
A6: Ph1 | B6: Dashboard | C6: R48 Fwd_Alpha | D6: 0.50 | E6: 0.65 | F6: Enable private VRE entry at realistic WS levels
A7: Ph1 | B7: Dashboard | C7: R39-42 | D7: WACCs added | E7: Batt/Sol/Wind/Gas WACC named ranges | F7: Move WACC to user-editable Dashboard
A8: Ph1 | B8: Dashboard | C8: R43 ESEM_WACC_Disc | D8: (new) | E8: 0.0 default | F8: Live dial for ESEM de-risking channel
A9: Ph1 | B9: Building assets | C9: R72 direct_flow | D9: 0.65 | E9: 0.80 | F9: Realistic battery cycling (~368 cycles/yr)
A10: Ph1 | B10: Building assets | C10: R73 label | D10: CF_bulk | E10: Delivered_Energy_Factor | F10: Honest label; value can exceed 1.0
A11: Ph1 | B11: Model | C11: R22 all 26 cols | F11: Piecewise LRMC toggle + SIC adder
A12: Ph2 | B12: Dashboard | C12: R115-120 | D12: (new) | E12: LRMC_Mode, Trend1, BP, Trend2, SIC_Base, SIC_Exp | F12: Scenario capability
A13: Ph2 | B13: Dashboard | C13: R121-136 | D13: (new) | E13: Alpha_Solar, Alpha_Wind, Optimize_Battery_Mix, CF_Solar/Wind, RTE_1h-8h, Direct_Flow, Drought_Gap | F13: Phase 3 configurable parameters
A14: Ph3 | B14: Building assets | C14: R5 (B5) | D14: 3 (hardcoded) | E14: =VRE_Ratio -> 3 | F14: Parameterise from Dashboard
A15: Ph3 | B15: Building assets | C15: R31-R34 annuities | D15: ×0.25 (fixed) | E15: ×w_1h_active...w_8h_active | F15: Battery weights now decision variables
A16: Ph3 | B16: Building assets | C16: R35-R36 VRE annuities | D16: ×2/3 or ×1/3 | E16: ×Alpha_Solar or ×Alpha_Wind | F16: Solar share now user-configurable
A17: Ph3 | B17: Building assets | C17: R47 Battery O&M | D17: ×0.25 (fixed) | E17: ×active weights | F17: Consistent with optimised battery mix
A18: Ph3 | B18: Building assets | C18: R48 VRE O&M | D18: ×2/3, ×1/3 | E18: ×Alpha_Solar, ×Alpha_Wind | F18: Consistent with Alpha parameter
A19: Ph3 | B19: Building assets | C19: R55-R58 replacement | D19: ×0.25 (fixed) | E19: ×active weights | F19: Consistent with optimised mix
A20: Ph3 | B20: Building assets | C20: R67 CF_Solar | D20: 0.22 (hardcoded) | E20: =CF_Solar (named range) -> #NAME? | F20: User-configurable from Dashboard
A21: Ph3 | B21: Building assets | C21: R68 CF_Wind | D21: 0.35 (hardcoded) | E21: =CF_Wind (named range) -> #NAME? | F21: User-configurable from Dashboard
A22: Ph3 | B22: Building assets | C22: R69 VRE_CF | D22: =2/3*B67+1/3*B68 -> 0 | E22: =Alpha_Solar*B67+Alpha_Wind*B68 -> 0 | F22: Parameterise solar share
A23: Ph3 | B23: Building assets | C23: R70 RTE | D23: 0.9 (hardcoded) | E23: =Battery_RTE_1h (named range) -> #NAME? | F23: Link to Dashboard param
A24: Ph3 | B24: Building assets | C24: R71 Drought | D24: 0.08 (hardcoded) | E24: =Drought_Gap (named range) -> #REF! | F24: Link to Dashboard param
A25: Ph3 | B25: Building assets | C25: R72 Direct_Flow | D25: 0.80 (hardcoded) | E25: =Direct_Flow (named range) -> #NAME? | F25: Link to Dashboard param
A26: Ph3 | B26: Building assets | C26: R141 (new) | D26: (none) | E26: Per-year DEF using Battery_RTE_Effective | F26: Supports different RTE by duration
A27: Ph3 | B27: Building assets | C27: R78 LRMC formula | D27: 1000*B61/(8760*$B$73) | E27: 1000*{c}61/(8760*{c}141) | F27: Per-year DEF; active weights flow through R61
A28: Ph3 | B28: Building assets | C28: R129-132 (new) | D28: (none) | E28: Active battery weight rows (IF optimise/equal) | F28: New decision variable infrastructure
A29: Ph3 | B29: SENSITIVITY_ANALYSIS | C29: (new sheet) | D29: (none) | E29: Pre-computed scenario sweep | F29: Part 9 of specification
A30: Ph3 | B30: CHANGELOG | C30: (new sheet) | D30: (none) | E30: This changelog | F30: Documentation requirement
A31: Ph3 | B31: METHODOLOGY_NOTE | C31: (new sheet) | D31: (none) | E31: Concise methodology explanation | F31: Documentation requirement

Sheet METHODOLOGY_NOTE
A1: ESEM MODEL — VRE+Storage LRMC Methodology Note
A3: PURPOSE
A4: This module derives a reduced-form Long-Run Marginal Cost (LRMC) for a stylised new-build VRE+battery storage entrant. The LRMC acts as an investment signal in the broader ESEM electricity market model: private VRE enters when the forward price exceeds this LRMC.
A6: WHY SOLAR SHARE IS NOW EXPLICIT
A7: The original model hardcoded 2/3 solar and 1/3 wind throughout all cost and CF calculations. This prevented sensitivity analysis over the generation mix. Alpha_Solar (Dashboard R121) now drives all solar/wind weights. Alpha_Wind = 1 - Alpha_Solar is derived automatically. The base case (Alpha_Solar=0.67) reproduces the original results.
A9: WHY BATTERY MIX IS NOW ENDOGENOUS
A10: The original model assumed equal 25% weight across 1h, 2h, 4h and 8h batteries. In reality an investor would choose the duration mix that minimises LRMC subject to a storage adequacy constraint (Storage_Target_Hours). The optimizer shows that longer-duration batteries are cheaper per MWh of storage capacity at current costs, so the optimal mix concentrates on fewer but longer-duration units when the hours target allows.
A12: WHAT DELIVERED ENERGY FACTOR (DEF) MEANS
A13: DEF = (Direct_Flow + (1-Direct_Flow) x RTE_eff) x VRE_Ratio x VRE_CF_blended x (1-Drought_Gap). This is NOT a conventional capacity factor. It represents the annual MWh delivered per kW of storage-reference capacity. It can exceed 1.0 when VRE_Ratio > 1 because the VRE nameplate capacity is larger than the storage reference capacity. The formula accounts for: (a) the share of VRE energy that flows directly to load (no battery losses); (b) the share that passes through the battery (reduced by RTE); (c) the VRE oversizing ratio; (d) the blended capacity factor of the VRE fleet; and (e) drought/curtailment gaps.
A15: HOW THE BATTERY OPTIMISATION WORKS
A16: 1. Determine Storage_Target_Hours: if Storage_Target_Mode="fixed_hours" use Storage_Target_Hours_Fixed; if "mix_based" use Alpha_Solar*Storage_Target_Hours_Solar + Alpha_Wind*Storage_Target_Hours_Wind. 2. Grid-search over (w_1h, w_2h, w_4h, w_8h) at Battery_Mix_Step (default 0.05) increments, subject to: all weights >= 0, weights sum to 1, Battery_Hours_Effective >= Storage_Target_Hours. 3. For each feasible combination compute LRMC = 1000*All_In_Cost/(8760*DEF). 4. Select the combination with the minimum LRMC. 5. Run separately for each of the 26 model years (capex trajectories differ by year). 6. Store optimal weights in Building assets rows. Toggle Optimize_Battery_Mix=0 on Dashboard to revert to equal 25% weights.
A18: KEY SENSITIVITIES
... A22: Setting Alpha_Solar=0.67, Optimize_Battery_Mix=0 (equal 25% weights) and all other Dashboard parameters to their defaults reproduces the Phase 2 LRMC values to within spreadsheet rounding.
